Workbook

Sheet NBFC-Vehicle Finance
C2: NBFC - VEHICLE FINANCE
C3: IKF Finance | G3: Cholamandalam | K3: SK Finance | N3: Shriram Finance | T3: Indostar Capital Finance
C4: ='IKF Finance'!C3 -> FY23 | D4: ='IKF Finance'!D3 -> FY24 | E4: ='IKF Finance'!E3 -> FY25 | F4: ='IKF Finance'!F3 -> FY26 | G4: FY23 | H4: FY24 | I4: FY25 | J4: FY26 | K4: FY 24 | L4: FY 25 | M4: FY 26 | N4: FY 21 | O4: FY 22 | P4: FY 23 | Q4: FY 24 | R4: FY 25 | S4: FY 26 | T4: FY 23 | U4: FY 24 | V4: FY 25 | W4: FY 26
B5: Particulars | C5: ='IKF Finance'!C4 -> Aud | D5: ='IKF Finance'!D4 -> Aud | E5: ='IKF Finance'!E4 -> Aud | F5: ='IKF Finance'!F4 -> Aud | G5: Aud | J5: Aud | K5: Aud | L5: Aud | M5: Aud | N5: Aud | O5: Aud | P5: Aud | Q5: Aud | R5: Aud | S5: Aud | T5: Aud | U5: Aud | V5: Aud | W5: Aud
C6: Rs in Crores | G6: Rs in Crores | K6: Rs in Crores | N6: Rs in Crore | T6: Rs in Crores
B7: Revenue from operations | C7: ='IKF Finance'!C6 -> 287 | D7: ='IKF Finance'!D6 -> 437 | E7: ='IKF Finance'!E6 -> 660 | F7: ='IKF Finance'!F6 -> 908 | G7: ='Cholamandalam Inv & Fin'!C6 -> 12757 | H7: ='Cholamandalam Inv & Fin'!D6 -> 18845 | I7: ='Cholamandalam Inv & Fin'!E6 -> 25746 | J7: ='Cholamandalam Inv & Fin'!F6 -> 30982 | K7: ='SK Finance'!C6 -> 1791 | L7: ='SK Finance'!D6 -> 2378 | M7: ='SK Finance'!E6 -> 2824 | N7: 17420.45 | O7: 19255.17 | P7: ='Shriram Finance'!E6 -> 29772.16 | Q7: 34964 | R7: 41834 | S7: 48118 | T7: ='Indostar Capital '!C6 -> 969 | U7: ='Indostar Capital '!D6 -> 1104 | V7: ='Indostar Capital '!E6 -> 1404 | W7: ='Indostar Capital '!F6 -> 1392.8917
B8: Interest Income | C8: ='IKF Finance'!C7 -> 284 | D8: ='IKF Finance'!D7 -> 421 | E8: ='IKF Finance'!E7 -> 618 | F8: ='IKF Finance'!F7 -> 855 | G8: ='Cholamandalam Inv & Fin'!C7 -> 12082 | H8: ='Cholamandalam Inv & Fin'!D7 -> 17614 | I8: ='Cholamandalam Inv & Fin'!E7 -> 23720 | J8: ='Cholamandalam Inv & Fin'!F7 -> 28373 | K8: ='SK Finance'!C7 -> 1499 | L8: ='SK Finance'!D7 -> 1899 | M8: ='SK Finance'!E7 -> 2262 | N8: 16611.31 | O8: 18028.13 | P8: ='Shriram Finance'!E7 -> 27504.2 | Q8: 33600 | R8: 40308 | S8: 46644 | T8: ='Indostar Capital '!C7 -> 864 | U8: ='Indostar Capital '!D7 -> 876 | V8: ='Indostar Capital '!E7 -> 1153 | W8: ='Indostar Capital '!F7 -> 1262.5166
B9: Other Operation Income | C9: ='IKF Finance'!C9 -> 3 | D9: ='IKF Finance'!D9 -> 4 | E9: ='IKF Finance'!E9 -> 7 | F9: ='IKF Finance'!F9 -> 8 | G9: ='Cholamandalam Inv & Fin'!C9 -> 674 | H9: ='Cholamandalam Inv & Fin'!D9 -> 1232 | I9: ='Cholamandalam Inv & Fin'!E9 -> 2025 | J9: ='Cholamandalam Inv & Fin'!F9 -> 2609 | K9: ='SK Finance'!C9 -> 97 | L9: ='SK Finance'!D9 -> 161 | M9: ='SK Finance'!E9 -> 215 | N9: =N7-N8 -> 809.14 | O9: =O7-O8 -> 1227.04 | P9: ='Shriram Finance'!E9 -> 2267.96 | Q9: =Q7-Q8 -> 1364 | R9: =R7-R8 -> 1526 | S9: =S7-S8 -> 1474 | T9: =SUM('Indostar Capital '!C8:C9) -> 105 | U9: =SUM('Indostar Capital '!D8:D9) -> 228 | V9: =SUM('Indostar Capital '!E8:E9) -> 251 | W9: =SUM('Indostar Capital '!F8:F9) -> 130.3751
B10: Interest expended | C10: ='IKF Finance'!C10 -> 154 | D10: ='IKF Finance'!D10 -> 220 | E10: ='IKF Finance'!E10 -> 332 | F10: ='IKF Finance'!F10 -> 417 | G10: ='Cholamandalam Inv & Fin'!C10 -> 5749 | H10: ='Cholamandalam Inv & Fin'!D10 -> 9231 | I10: ='Cholamandalam Inv & Fin'!E10 -> 12485 | J10: ='Cholamandalam Inv & Fin'!F10 -> 14374 | K10: ='SK Finance'!C10 -> 747 | L10: ='SK Finance'!D10 -> 971 | M10: ='SK Finance'!E10 -> 1119 | N10: 9054.26 | O10: 9734.31 | P10: ='Shriram Finance'!E10 -> 12545.76 | Q10: 14806 | R10: 18455 | S10: 21520 | T10: ='Indostar Capital '!C10 -> 518 | U10: ='Indostar Capital '!D10 -> 581 | V10: ='Indostar Capital '!E10 -> 741 | W10: ='Indostar Capital '!F10 -> 621.16
B11: Net Interest Income | C11: =C8-C10 -> 130 | D11: =D8-D10 -> 201 | E11: =E8-E10 -> 286 | F11: =F8-F10 -> 438 | G11: ='Cholamandalam Inv & Fin'!C11 -> 6333 | H11: ='Cholamandalam Inv & Fin'!D11 -> 8383 | I11: ='Cholamandalam Inv & Fin'!E11 -> 11235 | J11: ='Cholamandalam Inv & Fin'!F11 -> 13998 | K11: ='SK Finance'!C11 -> 752 | L11: ='SK Finance'!D11 -> 928 | M11: ='SK Finance'!E11 -> 1142 | N11: =N8-N10 -> 7557.05 | O11: =O8-O10 -> 8293.82 | P11: ='Shriram Finance'!E11 -> 14958.44 | Q11: =Q8-Q10 -> 18794 | R11: =R8-R10 -> 21853 | S11: =S8-S10 -> 25124 | T11: ='Indostar Capital '!C11 -> 346 | U11: ='Indostar Capital '!D11 -> 295 | V11: ='Indostar Capital '!E11 -> 412 | W11: ='Indostar Capital '!F11 -> 641.3566
B12: Total Operating Income | C12: =C8+C9 -> 287 | D12: =D8+D9 -> 425 | E12: =E8+E9 -> 625 | F12: =F8+F9 -> 863 | G12: =G8+G9 -> 12756 | H12: =H8+H9 -> 18846 | I12: =I8+I9 -> 25745 | J12: =J8+J9 -> 30982 | ... M12: =M8+M9 -> 2477 | N12: =SUM(N8:N9) -> 17420.45 | O12: =SUM(O8:O9) -> 19255.17 | P12: ='Shriram Finance'!E12 -> 29772.16 | Q12: =SUM(Q8:Q9) -> 34964 | R12: =SUM(R8:R9) -> 41834 | S12: =SUM(S8:S9) -> 48118 | T12: =T8+T9 -> 969 | U12: =U8+U9 -> 1104 | V12: =V8+V9 -> 1404 | W12: =W8+W9 -> 1392.8917
B13: Other income | C13: ='IKF Finance'!C13 -> 0 | D13: ='IKF Finance'!D13 -> 12 | E13: ='IKF Finance'!E13 -> 35 | F13: ='IKF Finance'!F13 -> 46 | G13: ='Cholamandalam Inv & Fin'!C13 -> 221 | H13: ='Cholamandalam Inv & Fin'!D13 -> 371 | I13: ='Cholamandalam Inv & Fin'!E13 -> 309 | J13: ='Cholamandalam Inv & Fin'!F13 -> 463 | K13: ='SK Finance'!C13 -> 6.7545 | L13: ='SK Finance'!D13 -> 8 | M13: ='SK Finance'!E13 -> 4 | N13: 15.95 | O13: 19.06 | P13: ='Shriram Finance'!E13 -> 30.73 | Q13: 33.2 | R13: 25.05 | S13: 60 | T13: ='Indostar Capital '!C13 -> 24 | U13: ='Indostar Capital '!D13 -> 21 | V13: ='Indostar Capital '!E13 -> 8 | W13: ='Indostar Capital '!F13 -> 1
B14: Total Income | C14: =C12+C13 -> 287 | D14: =D12+D13 -> 437 | E14: =E12+E13 -> 660 | F14: =F12+F13 -> 909 | G14: =G12+G13 -> 12977 | H14: =H12+H13 -> 19217 | I14: =I12+I13 -> 26054 | J14: =J12+J13 -> 31445 | ... W14: =W12+W13 -> 1393.8917
B15: Operating expenses | C15: ='IKF Finance'!C15 -> 60 | D15: ='IKF Finance'!D15 -> 97 | E15: ='IKF Finance'!E15 -> 144 | F15: ='IKF Finance'!F15 -> 186 | G15: ='Cholamandalam Inv & Fin'!C15 -> 2780 | H15: ='Cholamandalam Inv & Fin'!D15 -> 4082 | I15: ='Cholamandalam Inv & Fin'!E15 -> 5339 | J15: ='Cholamandalam Inv & Fin'!F15 -> 6574 | K15: ='SK Finance'!C15 -> 531.852 | L15: ='SK Finance'!D15 -> 688 | M15: ='SK Finance'!E15 -> 816 | N15: =906.25+137.36+863.23+78.89 -> 1985.73 | O15: =997.09+135.37+905.61+91.74 -> 2129.81 | P15: 4913.07 | Q15: 5990 | R15: 7143 | S15: 8027 | T15: ='Indostar Capital '!C15 -> 328 | U15: ='Indostar Capital '!D15 -> 389 | V15: ='Indostar Capital '!E15 -> 481 | W15: ='Indostar Capital '!F15 -> 505.9526
B16: Operating profit before finance costs | C16: ='IKF Finance'!C16 -> 227 | D16: ='IKF Finance'!D16 -> 328 | E16: ='IKF Finance'!E16 -> 481 | F16: ='IKF Finance'!F16 -> 677 | G16: ='Cholamandalam Inv & Fin'!C16 -> 9976 | H16: ='Cholamandalam Inv & Fin'!D16 -> 14764 | I16: ='Cholamandalam Inv & Fin'!E16 -> 20406 | J16: ='Cholamandalam Inv & Fin'!F16 -> 24408 | K16: ='SK Finance'!C16 -> 1259.148 | L16: ='SK Finance'!D16 -> 1690 | M16: ='SK Finance'!E16 -> 2008 | N16: =N12-N15 -> 15434.72 | O16: =O12-O15 -> 17125.36 | P16: 24859.09 | Q16: =Q12-Q15 -> 28974 | R16: =R12-R15 -> 34691 | S16: =S12-S15 -> 40091 | T16: =T12-T15 -> 641 | U16: =U12-U15 -> 715 | V16: =V12-V15 -> 923 | W16: =W12-W15 -> 886.9391
B17: Pre-provisioning operating profit | C17: ='IKF Finance'!C17 -> 73 | D17: ='IKF Finance'!D17 -> 108 | E17: ='IKF Finance'!E17 -> 149 | F17: ='IKF Finance'!F17 -> 260 | G17: ='Cholamandalam Inv & Fin'!C17 -> 4227 | H17: ='Cholamandalam Inv & Fin'!D17 -> 5533 | I17: ='Cholamandalam Inv & Fin'!E17 -> 7921 | J17: ='Cholamandalam Inv & Fin'!F17 -> 10034 | K17: ='SK Finance'!C17 -> 512.148 | L17: ='SK Finance'!D17 -> 719 | M17: ='SK Finance'!E17 -> 889 | N17: =N14-N15-N10 -> 6396.41 | O17: =O14-O15-O10 -> 7410.11 | P17: =P14-P15-P10 -> 12344.06 | Q17: =Q14-Q15-Q10 -> 14201.2 | R17: =R14-R15-R10 -> 16261.05 | S17: =S14-S15-S10 -> 18631 | T17: =T16-T10 -> 123 | U17: =U16-U10 -> 134 | V17: =V16-V10 -> 182 | W17: =W16-W10 -> 265.7791
B18: Provisions | C18: ='IKF Finance'!C18 -> 5 | D18: ='IKF Finance'!D18 -> 16 | E18: ='IKF Finance'!E18 -> 40 | F18: ='IKF Finance'!F18 -> 84 | G18: ='Cholamandalam Inv & Fin'!C18 -> 850 | H18: ='Cholamandalam Inv & Fin'!D18 -> 1322 | I18: ='Cholamandalam Inv & Fin'!E18 -> 2494 | J18: ='Cholamandalam Inv & Fin'!F18 -> 3536 | K18: ='SK Finance'!C18 -> 119.4335 | L18: ='SK Finance'!D18 -> 239 | M18: ='SK Finance'!E18 -> 326 | N18: 3118.4 | O18: 3860.86 | P18: 4159 | Q18: 4518 | R18: 5312 | S18: 5339 | T18: ='Indostar Capital '!C18 -> -40 | U18: ='Indostar Capital '!D18 -> 83 | V18: ='Indostar Capital '!E18 -> 138 | W18: ='Indostar Capital '!F18 -> 621
B19: PAT | C19: ='IKF Finance'!C19 -> 50 | D19: ='IKF Finance'!D19 -> 77 | E19: ='IKF Finance'!E19 -> 108 | F19: ='IKF Finance'!F19 -> 165 | G19: ='Cholamandalam Inv & Fin'!C19 -> 2666 | H19: ='Cholamandalam Inv & Fin'!D19 -> 3423 | I19: ='Cholamandalam Inv & Fin'!E19 -> 4259 | J19: ='Cholamandalam Inv & Fin'!F19 -> 5220 | K19: ='SK Finance'!C19 -> 311.9233 | L19: ='SK Finance'!D19 -> 380 | M19: ='SK Finance'!E19 -> 431 | N19: 2487.26 | O19: 2707.93 | P19: 5979 | Q19: 7190 | R19: 9761 | S19: 9998 | T19: ='Indostar Capital '!C19 -> 187 | U19: ='Indostar Capital '!D19 -> 72 | V19: ='Indostar Capital '!E19 -> 53 | W19: ='Indostar Capital '!F19 -> 130.2015
B20: TNW | C20: ='IKF Finance'!C20 -> 691 | D20: ='IKF Finance'!D20 -> 879 | E20: ='IKF Finance'!E20 -> 987 | F20: ='IKF Finance'!F20 -> 1895 | G20: ='Cholamandalam Inv & Fin'!C20 -> 13637 | H20: ='Cholamandalam Inv & Fin'!D20 -> 18867 | I20: ='Cholamandalam Inv & Fin'!E20 -> 22649 | J20: ='Cholamandalam Inv & Fin'!F20 -> 29203 | K20: ='SK Finance'!C20 -> 3075.2917 | L20: ='SK Finance'!D20 -> 3479 | M20: ='SK Finance'!E20 -> 3953 | N20: 21568.37 | O20: 25932.19 | P20: 43306.64 | Q20: 43244 | R20: 50698 | S20: 59916 | T20: ='Indostar Capital '!C20 -> 2386 | U20: ='Indostar Capital '!D20 -> 2475 | V20: ='Indostar Capital '!E20 -> 2804 | W20: ='Indostar Capital '!F20 -> 3156
B21: Total Debt | C21: ='IKF Finance'!C22 -> 2037 | D21: ='IKF Finance'!D22 -> 2733 | E21: ='IKF Finance'!E22 -> 3927 | F21: ='IKF Finance'!F22 -> 4743 | G21: ='Cholamandalam Inv & Fin'!C22 -> 97356 | H21: ='Cholamandalam Inv & Fin'!D22 -> 134474 | I21: ='Cholamandalam Inv & Fin'!E22 -> 175036 | J21: ='Cholamandalam Inv & Fin'!F22 -> 210867 | K21: ='SK Finance'!C22 -> 8934.8797 | L21: ='SK Finance'!D22 -> 11604 | M21: ='SK Finance'!E22 -> 12820 | N21: =40061.87+45281.37+16232.41+4620.76 -> 106196.41 | O21: =41256.55+46676.93+21948.98+4614.25 -> 114496.71 | P21: 157906.29 | Q21: 185841 | R21: 234472 | S21: 250748 | T21: ='Indostar Capital '!C22 -> 4813 | U21: ='Indostar Capital '!D22 -> 6049 | V21: ='Indostar Capital '!E22 -> 6916 | W21: ='Indostar Capital '!F22 -> 5476.8355
B22: Total Assets | C22: ='IKF Finance'!C23 -> 2764 | D22: ='IKF Finance'!D23 -> 3676 | E22: ='IKF Finance'!E23 -> 5012 | F22: ='IKF Finance'!F23 -> 6757 | G22: ='Cholamandalam Inv & Fin'!C23 -> 113516 | H22: ='Cholamandalam Inv & Fin'!D23 -> 156451 | I22: ='Cholamandalam Inv & Fin'!E23 -> 201648 | J22: ='Cholamandalam Inv & Fin'!F23 -> 245070 | K22: ='SK Finance'!C23 -> 12309.122 | L22: ='SK Finance'!D23 -> 15419 | M22: ='SK Finance'!E23 -> 17152 | N22: 129761.34 | O22: 142106.09 | P22: 203663.86 | Q22: 237276 | R22: 293808 | S22: 321155 | T22: ='Indostar Capital '!C23 -> 8139 | U22: ='Indostar Capital '!D23 -> 9390 | V22: ='Indostar Capital '!E23 -> 10762 | W22: ='Indostar Capital '!F23 -> 9511.4377
B23: Loans & Advances (Gross) | C23: ='IKF Finance'!C24 -> 2137 | D23: ='IKF Finance'!D24 -> 3291 | E23: ='IKF Finance'!E24 -> 4574 | F23: ='IKF Finance'!F24 -> 5873 | G23: ='Cholamandalam Inv & Fin'!C24 -> 104748 | H23: ='Cholamandalam Inv & Fin'!D24 -> 144424 | I23: ='Cholamandalam Inv & Fin'!E24 -> 181930 | J23: ='Cholamandalam Inv & Fin'!F24 -> 217571 | K23: ='SK Finance'!C24 -> 9813.4221 | L23: ='SK Finance'!D24 -> 12074 | M23: ='SK Finance'!E24 -> 14154 | N23: 116191.59 | O23: 125699.03 | P23: 183338.42 | Q23: 221668 | R23: 259916 | S23: 300216 | T23: ='Indostar Capital '!C24 -> 5737 | U23: ='Indostar Capital '!D24 -> 6298 | V23: ='Indostar Capital '!E24 -> 7464 | W23: ='Indostar Capital '!F24 -> 7850.1015
B24: Gross NPAs | C24: ='IKF Finance'!C25 -> 61 | D24: ='IKF Finance'!D25 -> 77 | E24: ='IKF Finance'!E25 -> 103 | F24: ='IKF Finance'!F25 -> 148 | G24: ='Cholamandalam Inv & Fin'!C25 -> 4953 | H24: ='Cholamandalam Inv & Fin'!D25 -> 5205 | I24: ='Cholamandalam Inv & Fin'!E25 -> 5213 | J24: ='Cholamandalam Inv & Fin'!F25 -> 6767 | K24: ='SK Finance'!C25 -> 343.3181 | L24: ='SK Finance'!D25 -> 573 | M24: ='SK Finance'!E25 -> 614 | N24: 8292.81 | O24: 8887.55 | P24: 11382.18 | Q24: 12081 | R24: 11839 | S24: 13743 | T24: ='Indostar Capital '!C25 -> 462 | U24: ='Indostar Capital '!D25 -> 313 | V24: ='Indostar Capital '!E25 -> 337 | W24: ='Indostar Capital '!F25 -> 374.6938
B25: Net NPAs | C25: ='IKF Finance'!C26 -> 48 | D25: ='IKF Finance'!D26 -> 59 | E25: ='IKF Finance'!E26 -> 68 | F25: ='IKF Finance'!F26 -> 98 | G25: ='Cholamandalam Inv & Fin'!C26 -> 3281 | H25: ='Cholamandalam Inv & Fin'!D26 -> 3374 | I25: ='Cholamandalam Inv & Fin'!E26 -> 2853 | J25: ='Cholamandalam Inv & Fin'!F26 -> 3567 | K25: ='SK Finance'!C26 -> 239.5362 | L25: ='SK Finance'!D26 -> 407 | M25: ='SK Finance'!E26 -> 401 | N25: 4806.68 | O25: 4446.05 | P25: 5674.91 | Q25: 5824 | R25: 6714 | S25: 6825 | T25: ='Indostar Capital '!C26 -> 207 | U25: ='Indostar Capital '!D26 -> 128 | V25: ='Indostar Capital '!E26 -> 180 | W25: ='Indostar Capital '!F26 -> 159.6127
C27: ='IKF Finance'!J3 -> FY23(A) | D27: ='IKF Finance'!K3 -> FY24 (A) | E27: ='IKF Finance'!L3 -> FY25 (A) | F27: ='IKF Finance'!M3 -> FY26 (A) | G27: ='Cholamandalam Inv & Fin'!K2 -> FY23 (A) | H27: ='Cholamandalam Inv & Fin'!L2 -> FY24 (A) | I27: ='Cholamandalam Inv & Fin'!M2 -> FY25 (A) | J27: ='Cholamandalam Inv & Fin'!N2 -> FY26 (A) | K27: FY24 (A) | L27: FY25 (A) | M27: FY26 (A) | N27: FY21 (A) | O27: FY22 (A) | P27: FY23 (A) | Q27: FY24 (A) | R27: FY25 (A) | S27: FY26 (A) | T27: FY23 (A) | U27: FY24 (A) | V27: FY25 (A) | W27: FY26 (A)
B28: Profitability
B29: Net Interest Margin | C29: ='IKF Finance'!J5 -> 0.060832943 | D29: ='IKF Finance'!K5 -> 0.074060427 | E29: ='IKF Finance'!L5 -> 0.072727273 | F29: ='IKF Finance'!M5 -> 0.083851823 | G29: ='Cholamandalam Inv & Fin'!K4 -> 0.060459388 | H29: ='Cholamandalam Inv & Fin'!L4 -> 0.067286854 | I29: ='Cholamandalam Inv & Fin'!M4 -> 0.068851615 | J29: ='Cholamandalam Inv & Fin'!N4 -> 0.070077422 | K29: ='SK Finance'!I4 -> 0.0888 | L29: ='SK Finance'!J4 -> 0.0848 | M29: ='SK Finance'!K4 -> 0.0871 | N29: 0.067265468 | O29: 0.068574962 | P29: ='Shriram Finance'!N4 -> 0.087440192 | Q29: ='Shriram Finance'!O4 -> 0.096064836 | R29: ='Shriram Finance'!P4 -> 0.093419747 | S29: ='Shriram Finance'!Q4 -> 0.089707426 | T29: ='Indostar Capital '!J4 -> 0.060310267 | U29: ='Indostar Capital '!K4 -> 0.049023681 | V29: ='Indostar Capital '!L4 -> 0.059875018 | W29: ='Indostar Capital '!M4 -> 0.083760265
B30: Capitalization
B31: Leverage (Debt/TNW) | C31: ='IKF Finance'!J7 -> 3.1242331 | D31: ='IKF Finance'!K7 -> 3.3533742 | E31: ='IKF Finance'!L7 -> 4.2044968 | F31: ='IKF Finance'!M7 -> 2.8367225 | G31: ='Cholamandalam Inv & Fin'!K6 -> 7.1391068 | H31: ='Cholamandalam Inv & Fin'!L6 -> 7.1274712 | I31: ='Cholamandalam Inv & Fin'!M6 -> 7.7281999 | J31: ='Cholamandalam Inv & Fin'!N6 -> 7.2207307 | K31: ='SK Finance'!I6 -> 2.91 | L31: ='SK Finance'!J6 -> 3.34 | M31: ='SK Finance'!K6 -> 3.24 | N31: 4.9237105 | O31: 4.4152349 | P31: ='Shriram Finance'!N6 -> 3.6462374 | Q31: ='Shriram Finance'!O6 -> 3.8263805 | R31: ='Shriram Finance'!P6 -> 4.6248767 | S31: ='Shriram Finance'!Q6 -> 4.1849923 | T31: ='Indostar Capital '!J6 -> 2.21593 | U31: ='Indostar Capital '!K6 -> 2.6647577 | V31: ='Indostar Capital '!L6 -> 2.4664765 | W31: ='Indostar Capital '!M6 -> 1.7353725
B32: CAR | C32: ='IKF Finance'!J8 -> 0.3302 | D32: ='IKF Finance'!K8 -> 0.265 | E32: ='IKF Finance'!L8 -> 0.2086 | F32: ='IKF Finance'!M8 -> 0.2734 | G32: ='Cholamandalam Inv & Fin'!K7 -> 0.1713 | H32: ='Cholamandalam Inv & Fin'!L7 -> 0.1857 | I32: ='Cholamandalam Inv & Fin'!M7 -> 0.198 | J32: ='Cholamandalam Inv & Fin'!N7 -> 0.192 | K32: ='SK Finance'!I7 -> 0.3386 | L32: ='SK Finance'!J7 -> 0.2951 | M32: ='SK Finance'!K7 -> 0.2541 | N32: 0.225 | O32: 0.2297 | P32: ='Shriram Finance'!N7 -> 0.2261 | Q32: ='Shriram Finance'!O7 -> 0.203 | R32: ='Shriram Finance'!P7 -> 0.2066 | S32: ='Shriram Finance'!Q7 -> 0.204 | T32: ='Indostar Capital '!J7 -> 0.315 | U32: ='Indostar Capital '!K7 -> 0.289 | V32: ='Indostar Capital '!L7 -> 0.285 | W32: ='Indostar Capital '!M7 -> 0.361
B33: TNW/Loan Book | C33: ='IKF Finance'!J9 -> 0.30510061 | D33: ='IKF Finance'!K9 -> 0.24764509 | E33: ='IKF Finance'!L9 -> 0.20419764 | F33: ='IKF Finance'!M9 -> 0.28469266 | G33: ='Cholamandalam Inv & Fin'!K8 -> 0.13018864 | H33: ='Cholamandalam Inv & Fin'!L8 -> 0.13063618 | I33: ='Cholamandalam Inv & Fin'!M8 -> 0.12449294 | J33: ='Cholamandalam Inv & Fin'!N8 -> 0.13422285 | K33: ='SK Finance'!I8 -> 0.31334635 | L33: ='SK Finance'!J8 -> 0.2881398 | M33: ='SK Finance'!K8 -> 0.27928501 | N33: 0.18562763 | O33: 0.20630382 | P33: ='Shriram Finance'!N8 -> 0.23621148 | Q33: ='Shriram Finance'!O8 -> 0.23358115 | R33: ='Shriram Finance'!P8 -> 0.19505533 | S33: ='Shriram Finance'!Q8 -> 0.19957631 | T33: ='Indostar Capital '!J8 -> 0.37859508 | U33: ='Indostar Capital '!K8 -> 0.36043188 | V33: ='Indostar Capital '!L8 -> 0.37566988 | W33: ='Indostar Capital '!M8 -> 0.40203302
B34: Operational Efficiency
B35: Cost to Income (on total operating income net-off interest expenses) | C35: ='IKF Finance'!J11 -> 0.45112782 | D35: ='IKF Finance'!K11 -> 0.47317073 | E35: ='IKF Finance'!L11 -> 0.49146758 | F35: ='IKF Finance'!M11 -> 0.41704036 | G35: ='Cholamandalam Inv & Fin'!K10 -> 0.39674611 | H35: ='Cholamandalam Inv & Fin'!L10 -> 0.42454498 | I35: ='Cholamandalam Inv & Fin'!M10 -> 0.40263952 | J35: ='Cholamandalam Inv & Fin'!N10 -> 0.39583333 | K35: ='SK Finance'!I10 -> 0.50943678 | L35: ='SK Finance'!J10 -> 0.48898365 | M35: ='SK Finance'!K10 -> 0.47859238 | N35: 0.23735177 | O35: 0.22369933 | P35: ='Shriram Finance'!N10 -> 0.28520585 | Q35: ='Shriram Finance'!O10 -> 0.29712391 | R35: ='Shriram Finance'!P10 -> 0.3055306 | S35: ='Shriram Finance'!Q10 -> 0.30178961 | T35: ='Indostar Capital '!J10 -> 0.72727273 | U35: ='Indostar Capital '!K10 -> 0.74378585 | V35: ='Indostar Capital '!L10 -> 0.7254902 | W35: ='Indostar Capital '!M10 -> 0.65560686
B36: Cost to Income (on total operating income) | C36: ='IKF Finance'!J12 -> 0.20905923 | D36: ='IKF Finance'!K12 -> 0.22823529 | E36: ='IKF Finance'!L12 -> 0.2304 | F36: ='IKF Finance'!M12 -> 0.21552723 | G36: ='Cholamandalam Inv & Fin'!K11 -> 0.21793666 | H36: ='Cholamandalam Inv & Fin'!L11 -> 0.21659769 | I36: ='Cholamandalam Inv & Fin'!M11 -> 0.20738007 | J36: ='Cholamandalam Inv & Fin'!N11 -> 0.21218772 | K36: ='SK Finance'!I11 -> 0.29695812 | L36: ='SK Finance'!J11 -> 0.28931876 | M36: ='SK Finance'!K11 -> 0.28895184 | N36: 0.11398844 | O36: 0.11060977 | P36: ='Shriram Finance'!N11 -> 0.16502229 | Q36: ='Shriram Finance'!O11 -> 0.17130305 | R36: ='Shriram Finance'!P11 -> 0.17074628 | S36: ='Shriram Finance'!Q11 -> 0.16681907 | T36: ='Indostar Capital '!J11 -> 0.33849329 | U36: ='Indostar Capital '!K11 -> 0.35235507 | V36: ='Indostar Capital '!L11 -> 0.34259259 | W36: ='Indostar Capital '!M11 -> 0.36323901
B37: Operating Expenses: Avg. Assets | C37: ='IKF Finance'!J13 -> 0.02170767 | D37: ='IKF Finance'!K13 -> 0.026387378 | E37: ='IKF Finance'!L13 -> 0.028731045 | F37: ='IKF Finance'!M13 -> 0.027527009 | G37: ='Cholamandalam Inv & Fin'!K12 -> 0.02448994 | H37: ='Cholamandalam Inv & Fin'!L12 -> 0.030240733 | I37: ='Cholamandalam Inv & Fin'!M12 -> 0.02981857 | J37: ='Cholamandalam Inv & Fin'!N12 -> 0.029432438 | K37: ='SK Finance'!I12 -> 0.043207955 | L37: ='SK Finance'!J12 -> 0.049624709 | M37: ='SK Finance'!K12 -> 0.050105922 | N37: 0.016283818 | O37: 0.015668004 | P37: ='Shriram Finance'!N12 -> 0.025467037 | Q37: ='Shriram Finance'!O12 -> 0.027167015 | R37: ='Shriram Finance'!P12 -> 0.026899699 | S37: ='Shriram Finance'!Q12 -> 0.026105636 | T37: ='Indostar Capital '!J12 -> 0.040299791 | U37: ='Indostar Capital '!K12 -> 0.04142705 | V37: ='Indostar Capital '!L12 -> 0.044694295 | W37: ='Indostar Capital '!M12 -> 0.053194124
B38: Loan Book Performance
B39: Gross NPA % | C39: ='IKF Finance'!J15 -> 0.028544689 | D39: ='IKF Finance'!K15 -> 0.023397144 | E39: ='IKF Finance'!L15 -> 0.022518583 | F39: ='IKF Finance'!M15 -> 0.025200068 | G39: ='Cholamandalam Inv & Fin'!K14 -> 0.047284912 | H39: ='Cholamandalam Inv & Fin'!L14 -> 0.036039716 | I39: ='Cholamandalam Inv & Fin'!M14 -> 0.028653878 | J39: ='Cholamandalam Inv & Fin'!N14 -> 0.031102491 | K39: ='SK Finance'!I14 -> 0.034984544 | L39: ='SK Finance'!J14 -> 0.047457346 | M39: ='SK Finance'!K14 -> 0.043379963 | N39: 0.071371861 | O39: 0.070705001 | P39: ='Shriram Finance'!N14 -> 0.062082896 | Q39: ='Shriram Finance'!O14 -> 0.058101449 | R39: ='Shriram Finance'!P14 -> 0.045549331 | S39: ='Shriram Finance'!Q14 -> 0.045777041 | T39: ='Indostar Capital '!J14 -> 0.080529894 | U39: ='Indostar Capital '!K14 -> 0.049698317 | V39: ='Indostar Capital '!L14 -> 0.045150054 | W39: ='Indostar Capital '!M14 -> 0.047731077
B40: Net NPA% | C40: ='IKF Finance'!J16 -> 0.022461394 | D40: ='IKF Finance'!K16 -> 0.017927682 | E40: ='IKF Finance'!L16 -> 0.014866638 | F40: ='IKF Finance'!M16 -> 0.016686532 | G40: ='Cholamandalam Inv & Fin'!K15 -> 0.031322794 | H40: ='Cholamandalam Inv & Fin'!L15 -> 0.023361768 | I40: ='Cholamandalam Inv & Fin'!M15 -> 0.015681856 | J40: ='Cholamandalam Inv & Fin'!N15 -> 0.016394648 | K40: ='SK Finance'!I15 -> 0.024409039 | L40: ='SK Finance'!J15 -> 0.033708796 | M40: ='SK Finance'!K15 -> 0.028331214 | N40: 0.041368571 | O40: 0.035370599 | P40: ='Shriram Finance'!N15 -> 0.030953196 | Q40: ='Shriram Finance'!O15 -> 0.028009506 | R40: ='Shriram Finance'!P15 -> 0.025831422 | S40: ='Shriram Finance'!Q15 -> 0.022733632 | T40: ='Indostar Capital '!J15 -> 0.036081576 | U40: ='Indostar Capital '!K15 -> 0.020323912 | V40: ='Indostar Capital '!L15 -> 0.024115756 | W40: ='Indostar Capital '!M15 -> 0.020332565
B41: Provision coverage Ratio | C41: ='IKF Finance'!J17 -> 0.21311475 | D41: ='IKF Finance'!K17 -> 0.23376623 | E41: ='IKF Finance'!L17 -> 0.33980583 | F41: ='IKF Finance'!M17 -> 0.33783784 | G41: =(G39-G40)/G39 -> 0.33757319 | H41: =(H39-H40)/H39 -> 0.35177714 | I41: =(I39-I40)/I39 -> 0.45271437 | J41: =(J39-J40)/J39 -> 0.47288311 | K41: ='SK Finance'!I16 -> 0.30229079 | L41: ='SK Finance'!J16 -> 0.28970332 | M41: ='SK Finance'!K16 -> 0.34690554 | N41: 0.42037982 | O41: 0.49974402 | P41: ='Shriram Finance'!N16 -> 0.50142152 | Q41: ='Shriram Finance'!O16 -> 0.5179207 | R41: ='Shriram Finance'!P16 -> 0.43289129 | S41: ='Shriram Finance'!Q16 -> 0.50338354 | T41: ='Indostar Capital '!J16 -> 0.55194805 | U41: ='Indostar Capital '!K16 -> 0.59105431 | V41: ='Indostar Capital '!L16 -> 0.46587537 | W41: ='Indostar Capital '!M16 -> 0.57401831
B42: 31-60 | C42: NA | D42: 0.038 | E42: 0.0348 | F42: 0.0176 | G42: NA | H42: NA | I42: NA | J42: NA | K42: NA | L42: NA | M42: 0.074 | N42: NA | O42: NA | P42: NA | Q42: NA | R42: NA | S42: NA | T42: NA | U42: NA | V42: 0.06
B43: 61-90/ stage 2 | C43: NA | D43: 0.028 | E43: 0.0371 | F43: 0.0474 | G43: NA | H43: NA | I43: NA | J43: NA | K43: NA | L43: NA | M43: 0.0426 | N43: NA | O43: NA | P43: NA | Q43: NA | R43: NA | S43: NA | T43: NA | U43: NA | V43: 0.02
B44: Credit Cost | C44: ='IKF Finance'!J18 -> 0.0023397286 | D44: ='IKF Finance'!K18 -> 0.0048617442 | E44: ='IKF Finance'!L18 -> 0.0087450809 | F44: ='IKF Finance'!M18 -> 0.014302741 | G44: ='Cholamandalam Inv & Fin'!K16 -> 0.0081147134 | H44: ='Cholamandalam Inv & Fin'!L16 -> 0.010611144 | I44: ='Cholamandalam Inv & Fin'!M16 -> 0.015284017 | J44: ='Cholamandalam Inv & Fin'!N16 -> 0.017702083 | K44: ='SK Finance'!I17 -> 0.012170423 | L44: ='SK Finance'!J17 -> 0.021839027 | M44: ='SK Finance'!K17 -> 0.024858929 | N44: 0.027756947 | O44: 0.031922362 | P44: ='Shriram Finance'!N17 -> 0.024312604 | Q44: ='Shriram Finance'!O17 -> 0.023095893 | R44: ='Shriram Finance'!P17 -> 0.022708356 | S44: ='Shriram Finance'!Q17 -> 0.019063364 | T44: ='Indostar Capital '!J17 -> -0.0069722852 | U44: ='Indostar Capital '!K17 -> 0.013793103 | V44: ='Indostar Capital '!L17 -> 0.020055225 | W44: ='Indostar Capital '!M17 -> 0.081101722
B45: Return Indicators
B46: Pre Provisioning operating profit (PPOP)margin | C46: ='IKF Finance'!J20 -> 0.026410999 | D46: ='IKF Finance'!K20 -> 0.029379761 | E46: ='IKF Finance'!L20 -> 0.029728651 | F46: ='IKF Finance'!M20 -> 0.038478615 | G46: ='Cholamandalam Inv & Fin'!K18 -> 0.037237041 | H46: ='Cholamandalam Inv & Fin'!L18 -> 0.040990195 | I46: ='Cholamandalam Inv & Fin'!M18 -> 0.044239163 | J46: ='Cholamandalam Inv & Fin'!N18 -> 0.044923195 | K46: ='SK Finance'!I19 -> 0.041607191 | L46: ='SK Finance'!J19 -> 0.051860706 | M46: ='SK Finance'!K19 -> 0.054588438 | N46: 0.052453241 | O46: 0.054512672 | P46: ='Shriram Finance'!N19 -> 0.063985782 | Q46: ='Shriram Finance'!O19 -> 0.064416856 | R46: ='Shriram Finance'!P19 -> 0.061237204 | S46: ='Shriram Finance'!Q19 -> 0.060592263 | T46: ='Indostar Capital '!J19 -> 0.015112422 | U46: ='Indostar Capital '!K19 -> 0.01528895 | V46: ='Indostar Capital '!L19 -> 0.018062723 | W46: ='Indostar Capital '!M19 -> 0.026219441
B47: RoA | C47: ='IKF Finance'!J21 -> 0.0223 | D47: ='IKF Finance'!K21 -> 0.0239 | E47: ='IKF Finance'!L21 -> 0.0248 | F47: ='IKF Finance'!M21 -> 0.028 | G47: ='Cholamandalam Inv & Fin'!K19 -> 0.023485676 | H47: ='Cholamandalam Inv & Fin'!L19 -> 0.025358655 | I47: ='Cholamandalam Inv & Fin'!M19 -> 0.023786718 | J47: ='Cholamandalam Inv & Fin'!N19 -> 0.023370448 | K47: ='SK Finance'!I20 -> 0.025340824 | L47: ='SK Finance'!J20 -> 0.027408996 | M47: ='SK Finance'!K20 -> 0.026465261 | N47: 0.020396574 | O47: 0.019920959 | P47: ='Shriram Finance'!N20 -> 0.030994077 | Q47: ='Shriram Finance'!O20 -> 0.032614334 | R47: ='Shriram Finance'!P20 -> 0.036758779 | S47: ='Shriram Finance'!Q20 -> 0.032515777 | T47: ='Indostar Capital '!J20 -> 0.022975796 | U47: ='Indostar Capital '!K20 -> 0.0082149581 | V47: ='Indostar Capital '!L20 -> 0.0052600238 | W47: ='Indostar Capital '!M20 -> 0.012844541
B48: RoE | C48: ='IKF Finance'!J22 -> 0.0987 | D48: ='IKF Finance'!K22 -> 0.1049 | E48: ='IKF Finance'!L22 -> 0.1234 | F48: ='IKF Finance'!M22 -> 0.1265 | G48: ='Cholamandalam Inv & Fin'!K20 -> 0.19549754 | H48: ='Cholamandalam Inv & Fin'!L20 -> 0.21062023 | I48: ='Cholamandalam Inv & Fin'!M20 -> 0.20517391 | J48: ='Cholamandalam Inv & Fin'!N20 -> 0.20134228 | K48: ='SK Finance'!I21 -> 0.10142885 | L48: ='SK Finance'!J21 -> 0.11595456 | M48: ='SK Finance'!K21 -> 0.11598493 | N48: 0.12570322 | O48: 0.11401676 | P48: ='Shriram Finance'!N21 -> 0.154627 | Q48: ='Shriram Finance'!O21 -> 0.1565274 | R48: ='Shriram Finance'!P21 -> 0.19666274 | S48: ='Shriram Finance'!Q21 -> 0.18077278 | T48: ='Indostar Capital '!J21 -> 0.078373847 | U48: ='Indostar Capital '!K21 -> 0.029623534 | V48: ='Indostar Capital '!L21 -> 0.020079561 | W48: ='Indostar Capital '!M21 -> 0.043691779
B49: Spread
B50: Yields (A) | C50: ='IKF Finance'!J24 -> 0.1523 | D50: ='IKF Finance'!K24 -> 0.1553 | E50: ='IKF Finance'!L24 -> 0.1572 | F50: ='IKF Finance'!M24 -> 0.165 | G50: ='Cholamandalam Inv & Fin'!K22 -> 0.11534349 | H50: ='Cholamandalam Inv & Fin'!L22 -> 0.14138025 | I50: ='Cholamandalam Inv & Fin'!M22 -> 0.14536362 | J50: ='Cholamandalam Inv & Fin'!N22 -> 0.1420422 | K50: ='SK Finance'!I23 -> 0.177 | L50: ='SK Finance'!J23 -> 0.1735 | M50: ='SK Finance'!K23 -> 0.1725 | N50: 0.14785764 | O50: 0.14906018 | P50: ='Shriram Finance'!N23 -> 0.16077696 | Q50: ='Shriram Finance'!O23 -> 0.17174762 | R50: ='Shriram Finance'!P23 -> 0.17231333 | S50: ='Shriram Finance'!Q23 -> 0.16654646 | T50: ='Indostar Capital '!J23 -> 0.15060136 | U50: ='Indostar Capital '!K23 -> 0.14557541 | V50: ='Indostar Capital '!L23 -> 0.16756285 | W50: ='Indostar Capital '!M23 -> 0.16488288
B51: Avg. Cost of Borrowing(B) | C51: ='IKF Finance'!J25 -> 0.0921 | D51: ='IKF Finance'!K25 -> 0.0923 | E51: ='IKF Finance'!L25 -> 0.0997 | F51: ='IKF Finance'!M25 -> 0.0962 | G51: ='Cholamandalam Inv & Fin'!K23 -> 0.059051317 | H51: ='Cholamandalam Inv & Fin'!L23 -> 0.09481696 | I51: ='Cholamandalam Inv & Fin'!M23 -> 0.092843226 | J51: ='Cholamandalam Inv & Fin'!N23 -> 0.08212025 | K51: ='SK Finance'!I24 -> 0.0935 | L51: ='SK Finance'!J24 -> 0.0946 | M51: ='SK Finance'!K24 -> 0.0916 | N51: 0.090286115 | O51: 0.088215799 | P51: ='Shriram Finance'!N24 -> 0.082800785 | Q51: ='Shriram Finance'!O24 -> 0.086145342 | R51: ='Shriram Finance'!P24 -> 0.08781548 | S51: ='Shriram Finance'!Q24 -> 0.088702032 | T51: ='Indostar Capital '!J24 -> 0.10762518 | U51: ='Indostar Capital '!K24 -> 0.10697846 | V51: ='Indostar Capital '!L24 -> 0.11430775 | W51: ='Indostar Capital '!M24 -> 0.10024502
B52: Spread(A-B) | C52: ='IKF Finance'!J26 -> 0.0601 | D52: ='IKF Finance'!K26 -> 0.0629 | E52: ='IKF Finance'!L26 -> 0.0575 | F52: ='IKF Finance'!M26 -> 0.0687 | G52: ='Cholamandalam Inv & Fin'!K24 -> 0.056292174 | H52: ='Cholamandalam Inv & Fin'!L24 -> 0.046563291 | I52: ='Cholamandalam Inv & Fin'!M24 -> 0.052520397 | J52: ='Cholamandalam Inv & Fin'!N24 -> 0.059921948 | K52: ='SK Finance'!I25 -> 0.0835 | L52: ='SK Finance'!J25 -> 0.0789 | M52: ='SK Finance'!K25 -> 0.0808 | N52: 0.05757152 | O52: 0.060844383 | P52: ='Shriram Finance'!N25 -> 0.077976177 | Q52: ='Shriram Finance'!O25 -> 0.085602281 | R52: ='Shriram Finance'!P25 -> 0.084497849 | S52: ='Shriram Finance'!Q25 -> 0.077844425 | T52: ='Indostar Capital '!J25 -> 0.042976178 | U52: ='Indostar Capital '!K25 -> 0.038596948 | V52: ='Indostar Capital '!L25 -> 0.053255103 | W52: ='Indostar Capital '!M25 -> 0.064637866

Sheet NBFC-Educational Loans
C2: NBFC - Educational Loans
C3: Avanse Financial | F3: Auxilo Finserve | I3: HDFC Credila | L3: EdGro Finance
C4: FY 24 | D4: FY 25 | E4: FY 26 | F4: FY 24 | G4: FY 25 | H4: FY 26 | I4: FY 24 | J4: FY 25 | K4: FY 26 | L4: FY 24 | M4: FY 25 | N4: FY 26
B5: Particulars | C5: Aud | D5: Aud | E5: Aud | F5: Aud | G5: Aud | H5: Aud | I5: Aud | J5: Aud | K5: Aud | L5: Aud | M5: Aud | N5: Aud
C6: Rs in Crores | F6: Rs in Crores | I6: Rs in Crores | L6: Rs in Crores
B7: Revenue from operations | C7: ='Avanse Financial'!C6 -> 1726.2 | D7: ='Avanse Financial'!D6 -> 2013 | E7: ='Avanse Financial'!E6 -> 2882 | F7: ='Auxilo Finserve '!C6 -> 356.7 | G7: ='Auxilo Finserve '!D6 -> 528.1 | H7: ='Auxilo Finserve '!E6 -> 675.8 | I7: ='Hdfc Credila'!C6 -> 2771.04 | J7: ='Hdfc Credila'!D6 -> 4726 | K7: ='Hdfc Credila'!E6 -> 6061.49 | L7: ='EdGro Finance'!C6 -> 4 | M7: ='EdGro Finance'!D6 -> 48 | N7: ='EdGro Finance'!E6 -> 102
B8: Interest Income | C8: ='Avanse Financial'!C7 -> 1386.4 | D8: ='Avanse Financial'!D7 -> 1963.7 | E8: ='Avanse Financial'!E7 -> 2462.4 | F8: ='Auxilo Finserve '!C7 -> 312.1 | G8: ='Auxilo Finserve '!D7 -> 463.9 | H8: ='Auxilo Finserve '!E7 -> 596.3 | I8: ='Hdfc Credila'!C7 -> 2535.35 | J8: ='Hdfc Credila'!D7 -> 4165.57 | K8: ='Hdfc Credila'!E7 -> 5690.4 | L8: ='EdGro Finance'!C7 -> 3 | M8: ='EdGro Finance'!D7 -> 32 | N8: ='EdGro Finance'!E7 -> 74
B9: Other Operation Income | C9: ='Avanse Financial'!C9 -> 339.7 | D9: ='Avanse Financial'!D9 -> 49.3 | E9: ='Avanse Financial'!E9 -> 419.6 | F9: ='Auxilo Finserve '!C9 -> 44.6 | G9: ='Auxilo Finserve '!D9 -> 64.2 | H9: ='Auxilo Finserve '!E9 -> 79.5 | I9: ='Hdfc Credila'!C9 -> 235.69 | J9: ='Hdfc Credila'!D9 -> 560.43 | K9: ='Hdfc Credila'!E9 -> 371.09 | L9: ='EdGro Finance'!C9 -> 1 | M9: ='EdGro Finance'!D9 -> 16 | N9: ='EdGro Finance'!E9 -> 19
B10: Interest expended | C10: ='Avanse Financial'!C10 -> 875.6 | D10: ='Avanse Financial'!D10 -> 1217 | E10: ='Avanse Financial'!E10 -> 1530 | F10: ='Auxilo Finserve '!C10 -> 195.3 | G10: ='Auxilo Finserve '!D10 -> 282.2 | H10: ='Auxilo Finserve '!E10 -> 384.7 | I10: ='Hdfc Credila'!C10 -> 1731.02 | J10: ='Hdfc Credila'!D10 -> 2893.44 | K10: ='Hdfc Credila'!E10 -> 3639.34 | L10: ='EdGro Finance'!C10 -> 3 | M10: ='EdGro Finance'!D10 -> 24 | N10: ='EdGro Finance'!E10 -> 34
B11: Net Interest Income | C11: ='Avanse Financial'!C11 -> 510.8 | D11: ='Avanse Financial'!D11 -> 746.7 | E11: ='Avanse Financial'!E11 -> 932.4 | F11: ='Auxilo Finserve '!C11 -> 116.9 | G11: ='Auxilo Finserve '!D11 -> 181.7 | H11: ='Auxilo Finserve '!E11 -> 211.6 | I11: ='Hdfc Credila'!C11 -> 804.33 | J11: ='Hdfc Credila'!D11 -> 1272.13 | K11: ='Hdfc Credila'!E11 -> 2051.06 | L11: ='EdGro Finance'!C11 -> 0 | M11: ='EdGro Finance'!D11 -> 8 | N11: ='EdGro Finance'!E11 -> 40
B12: Total Operating Income | C12: ='Avanse Financial'!C12 -> 1726.1 | D12: ='Avanse Financial'!D12 -> 2013 | E12: ='Avanse Financial'!E12 -> 2882 | F12: ='Auxilo Finserve '!C12 -> 356.7 | G12: ='Auxilo Finserve '!D12 -> 528.1 | H12: ='Auxilo Finserve '!E12 -> 675.8 | I12: ='Hdfc Credila'!C12 -> 2771.04 | J12: ='Hdfc Credila'!D12 -> 4726 | K12: ='Hdfc Credila'!E12 -> 6061.49 | L12: ='EdGro Finance'!C12 -> 4 | M12: ='EdGro Finance'!D12 -> 48 | N12: ='EdGro Finance'!E12 -> 93
B13: Other income | C13: ='Avanse Financial'!C13 -> 2.1 | D13: ='Avanse Financial'!D13 -> 337.8 | E13: ='Avanse Financial'!E13 -> 6.9 | F13: ='Auxilo Finserve '!C13 -> 10.6 | G13: ='Auxilo Finserve '!D13 -> 15.5 | H13: ='Auxilo Finserve '!E13 -> 13.9 | I13: ='Hdfc Credila'!C13 -> 0 | J13: ='Hdfc Credila'!D13 -> 0 | K13: ='Hdfc Credila'!E13 -> 5.54 | L13: ='EdGro Finance'!C13 -> 3 | M13: ='EdGro Finance'!D13 -> 3 | N13: ='EdGro Finance'!E13 -> 9
B14: Total Income | C14: ='Avanse Financial'!C14 -> 1728.3 | D14: ='Avanse Financial'!D14 -> 2350.8 | E14: ='Avanse Financial'!E14 -> 2888.9 | F14: ='Auxilo Finserve '!C14 -> 367.3 | G14: ='Auxilo Finserve '!D14 -> 543.6 | H14: ='Auxilo Finserve '!E14 -> 689.7 | I14: ='Hdfc Credila'!C14 -> 2771.04 | J14: ='Hdfc Credila'!D14 -> 4726 | K14: ='Hdfc Credila'!E14 -> 6067.03 | L14: ='EdGro Finance'!C14 -> 7 | M14: ='EdGro Finance'!D14 -> 51 | N14: ='EdGro Finance'!E14 -> 102
B15: Operating expenses | C15: ='Avanse Financial'!C15 -> 313.4 | D15: ='Avanse Financial'!D15 -> 394.2 | E15: ='Avanse Financial'!E15 -> 438.1 | F15: ='Auxilo Finserve '!C15 -> 72.6 | G15: ='Auxilo Finserve '!D15 -> 98.5 | H15: ='Auxilo Finserve '!E15 -> 135.6 | I15: ='Hdfc Credila'!C15 -> 281.87 | J15: ='Hdfc Credila'!D15 -> 360.04 | K15: ='Hdfc Credila'!E15 -> 498.13 | L15: ='EdGro Finance'!C15 -> 4 | M15: ='EdGro Finance'!D15 -> 21 | N15: ='EdGro Finance'!E15 -> 54
B16: Operating profit | C16: ='Avanse Financial'!C16 -> 1412.7 | D16: ='Avanse Financial'!D16 -> 1618.8 | E16: ='Avanse Financial'!E16 -> 2443.9 | F16: ='Auxilo Finserve '!C16 -> 284.1 | G16: ='Auxilo Finserve '!D16 -> 429.6 | H16: ='Auxilo Finserve '!E16 -> 540.2 | I16: ='Hdfc Credila'!C16 -> 2489.17 | J16: ='Hdfc Credila'!D16 -> 4365.96 | K16: ='Hdfc Credila'!E16 -> 5563.36 | L16: ='EdGro Finance'!C16 -> 0 | M16: ='EdGro Finance'!D16 -> 27 | N16: ='EdGro Finance'!E16 -> 39
B17: Pre-Provisioning Operating Profit | C17: ='Avanse Financial'!C17 -> 539.3 | D17: ='Avanse Financial'!D17 -> 739.6 | E17: ='Avanse Financial'!E17 -> 920.8 | F17: ='Auxilo Finserve '!C17 -> 99.4 | G17: ='Auxilo Finserve '!D17 -> 162.9 | H17: ='Auxilo Finserve '!E17 -> 169.4 | I17: ='Hdfc Credila'!C17 -> 758.15 | J17: ='Hdfc Credila'!D17 -> 1472.52 | K17: ='Hdfc Credila'!E17 -> 1929.56 | L17: ='EdGro Finance'!C17 -> -3 | M17: ='EdGro Finance'!D17 -> 3 | N17: ='EdGro Finance'!E17 -> 5
B18: Provisions | C18: ='Avanse Financial'!C18 -> 79.6 | D18: ='Avanse Financial'!D18 -> 64.7 | E18: ='Avanse Financial'!E18 -> 116.3 | F18: ='Auxilo Finserve '!C18 -> 6.8 | G18: ='Auxilo Finserve '!D18 -> 12.9 | H18: ='Auxilo Finserve '!E18 -> 12.7 | I18: ='Hdfc Credila'!C18 -> 49.79 | J18: ='Hdfc Credila'!D18 -> 146.54 | K18: ='Hdfc Credila'!E18 -> 173.33 | L18: ='EdGro Finance'!C18 -> 1 | M18: ='EdGro Finance'!D18 -> 3 | N18: ='EdGro Finance'!E18 -> 8
B19: PAT | C19: ='Avanse Financial'!C19 -> 342.6 | D19: ='Avanse Financial'!D19 -> 504.2 | E19: ='Avanse Financial'!E19 -> 597.9 | F19: ='Auxilo Finserve '!C19 -> 69.2 | G19: ='Auxilo Finserve '!D19 -> 111.9 | H19: ='Auxilo Finserve '!E19 -> 116.9 | I19: ='Hdfc Credila'!C19 -> 528.84 | J19: ='Hdfc Credila'!D19 -> 989.96 | K19: ='Hdfc Credila'!E19 -> 1316.3 | L19: ='EdGro Finance'!C19 -> 0.31 | M19: ='EdGro Finance'!D19 -> 2 | N19: ='EdGro Finance'!E19 -> 5
B20: TNW | C20: ='Avanse Financial'!C20 -> 3600.5 | D20: ='Avanse Financial'!D20 -> 4065 | E20: ='Avanse Financial'!E20 -> 5999.4 | F20: ='Auxilo Finserve '!C20 -> 982.6 | G20: ='Auxilo Finserve '!D20 -> 1387.5 | H20: ='Auxilo Finserve '!E20 -> 1505 | I20: ='Hdfc Credila'!C20 -> 4981.23 | J20: ='Hdfc Credila'!D20 -> 8619.57 | K20: ='Hdfc Credila'!E20 -> 9923.31 | L20: ='EdGro Finance'!C20 -> 107 | M20: ='EdGro Finance'!D20 -> 113 | N20: ='EdGro Finance'!E20 -> 351
B21: Total Debt | C21: ='Avanse Financial'!C22 -> 10135.2 | D21: ='Avanse Financial'!D22 -> 14473.6 | E21: ='Avanse Financial'!E22 -> 18471.4 | F21: ='Auxilo Finserve '!C22 -> 2345.2 | G21: ='Auxilo Finserve '!D22 -> 3417.8 | H21: ='Auxilo Finserve '!E22 -> 3931.4 | I21: ='Hdfc Credila'!C22 -> 26032.83 | J21: ='Hdfc Credila'!D22 -> 38869.01 | K21: ='Hdfc Credila'!E22 -> 45866.02 | L21: ='EdGro Finance'!C22 -> 156 | M21: ='EdGro Finance'!D22 -> 221 | N21: ='EdGro Finance'!E22 -> 450
B22: Total Assets | C22: ='Avanse Financial'!C23 -> 14267.6 | D22: ='Avanse Financial'!D23 -> 18931.9 | E22: ='Avanse Financial'!E23 -> 25114.3 | F22: ='Auxilo Finserve '!C23 -> 3363.6 | G22: ='Auxilo Finserve '!D23 -> 4858.9 | H22: ='Auxilo Finserve '!E23 -> 5489.1 | I22: ='Hdfc Credila'!C23 -> 31503.84 | J22: ='Hdfc Credila'!D23 -> 48119.57 | K22: ='Hdfc Credila'!E23 -> 57272.75 | L22: ='EdGro Finance'!C23 -> 271 | M22: ='EdGro Finance'!D23 -> 354 | N22: ='EdGro Finance'!E23 -> 830
B23: Loans & Advances (Gross) | C23: ='Avanse Financial'!C24 -> 12520.7 | D23: ='Avanse Financial'!D24 -> 17419.9 | E23: ='Avanse Financial'!E24 -> 20600.5 | F23: ='Auxilo Finserve '!C24 -> 2859.4 | G23: ='Auxilo Finserve '!D24 -> 4298.5 | H23: ='Auxilo Finserve '!E24 -> 4936.7 | I23: ='Hdfc Credila'!C24 -> 28187.2 | J23: ='Hdfc Credila'!D24 -> 41709.64 | K23: ='Hdfc Credila'!E24 -> 50653.56 | L23: ='EdGro Finance'!C24 -> 153 | M23: ='EdGro Finance'!D24 -> 279 | N23: ='EdGro Finance'!E24 -> 608
B24: Gross NPAs | C24: ='Avanse Financial'!C25 -> 53.1 | D24: ='Avanse Financial'!D25 -> 44.5 | E24: ='Avanse Financial'!E25 -> 75 | F24: ='Auxilo Finserve '!C25 -> 25 | G24: ='Auxilo Finserve '!D25 -> 22.6 | H24: ='Auxilo Finserve '!E25 -> 18 | I24: ='Hdfc Credila'!C25 -> 21.46 | J24: ='Hdfc Credila'!D25 -> 79.88 | K24: ='Hdfc Credila'!E25 -> 131.7 | L24: ='EdGro Finance'!C25 -> 0 | M24: ='EdGro Finance'!D25 -> 3 | N24: ='EdGro Finance'!E25 -> 0
B25: Net NPAs | C25: ='Avanse Financial'!C26 -> 16 | D25: ='Avanse Financial'!D26 -> 6.8 | E25: ='Avanse Financial'!E26 -> 12.2 | F25: ='Auxilo Finserve '!C26 -> 14.4 | G25: ='Auxilo Finserve '!D26 -> 3.5 | H25: ='Auxilo Finserve '!E26 -> 5 | I25: ='Hdfc Credila'!C26 -> 9.79 | J25: ='Hdfc Credila'!D26 -> 27.95 | K25: ='Hdfc Credila'!E26 -> 50.65 | L25: ='EdGro Finance'!C26 -> 0 | M25: ='EdGro Finance'!D26 -> 1 | N25: ='EdGro Finance'!E26 -> 0
C27: ='Avanse Financial'!H3 -> FY24(A) | D27: ='Avanse Financial'!I3 -> FY25(A) | E27: ='Avanse Financial'!J3 -> FY26(A) | F27: ='Auxilo Finserve '!H3 -> FY24(A) | G27: ='Auxilo Finserve '!I3 -> FY25(A) | H27: ='Auxilo Finserve '!J3 -> FY26(A) | I27: ='Hdfc Credila'!H3 -> FY24 (A) | J27: ='Hdfc Credila'!I3 -> FY25 (A) | K27: ='Hdfc Credila'!J3 -> FY26 (A) | L27: ='EdGro Finance'!H3 -> FY24 (A) | M27: ='EdGro Finance'!I3 -> FY25 (A) | N27: ='EdGro Finance'!J3 -> FY26 (A)
B28: Profitability
B29: Net Interest Margin | C29: ='Avanse Financial'!H5 -> 0.0487 | D29: ='Avanse Financial'!I5 -> 0.04987876 | E29: ='Avanse Financial'!J5 -> 0.049047354 | F29: ='Auxilo Finserve '!H5 -> 0.051150961 | G29: ='Auxilo Finserve '!I5 -> 0.05076908 | H29: ='Auxilo Finserve '!J5 -> 0.045824671 | I29: ='Hdfc Credila'!H5 -> 0.037 | J29: ='Hdfc Credila'!I5 -> 0.036400215 | K29: ='Hdfc Credila'!J5 -> 0.044412926 | L29: ='EdGro Finance'!H5 -> - | M29: ='EdGro Finance'!I5 -> 0.037037037 | N29: ='EdGro Finance'!J5 -> 0.090191657
B30: Capitalization
B31: Leverage (Debt/TNW) | C31: ='Avanse Financial'!H7 -> 2.8149424 | D31: ='Avanse Financial'!I7 -> 3.5605412 | E31: ='Avanse Financial'!J7 -> 3.0788746 | F31: ='Auxilo Finserve '!H7 -> 2.3867291 | G31: ='Auxilo Finserve '!I7 -> 2.4632793 | H31: ='Auxilo Finserve '!J7 -> 2.6122259 | I31: ='Hdfc Credila'!H7 -> 5.2261851 | J31: ='Hdfc Credila'!I7 -> 4.5093908 | K31: ='Hdfc Credila'!J7 -> 4.6220485 | L31: ='EdGro Finance'!H7 -> 1.4579439 | M31: ='EdGro Finance'!I7 -> 1.9557522 | N31: ='EdGro Finance'!J7 -> 1.2820513
B32: CAR | C32: ='Avanse Financial'!H8 -> 0.2752 | D32: ='Avanse Financial'!I8 -> 0.2244 | E32: ='Avanse Financial'!J8 -> 0.2673 | F32: ='Auxilo Finserve '!H8 -> 0.3149 | G32: ='Auxilo Finserve '!I8 -> 0.3 | H32: ='Auxilo Finserve '!J8 -> 0.321 | I32: ='Hdfc Credila'!H8 -> 0.2045 | J32: ='Hdfc Credila'!I8 -> 0.2181 | K32: ='Hdfc Credila'!J8 -> 0.1989 | L32: ='EdGro Finance'!H8 -> 0.4737 | M32: ='EdGro Finance'!I8 -> 0.3398 | N32: ='EdGro Finance'!J8 -> 0.4502
B33: TNW/Loan Book | C33: ='Avanse Financial'!H9 -> 0.28756379 | D33: ='Avanse Financial'!I9 -> 0.23335381 | E33: ='Avanse Financial'!J9 -> 0.29122594 | F33: ='Auxilo Finserve '!H9 -> 0.34363853 | G33: ='Auxilo Finserve '!I9 -> 0.32278702 | H33: ='Auxilo Finserve '!J9 -> 0.30485952 | I33: ='Hdfc Credila'!H9 -> 0.17671957 | J33: ='Hdfc Credila'!I9 -> 0.20665654 | K33: ='Hdfc Credila'!J9 -> 0.19590548 | L33: ='EdGro Finance'!H9 -> 0.69934641 | M33: ='EdGro Finance'!I9 -> 0.40501792 | N33: ='EdGro Finance'!J9 -> 0.57730263
B34: Operational Efficiency
B35: Cost to Income (on total operating income net-off interest expenses) | C35: ='Avanse Financial'!H11 -> 0.36848912 | D35: ='Avanse Financial'!I11 -> 0.49522613 | E35: ='Avanse Financial'!J11 -> 0.32403846 | F35: ='Auxilo Finserve '!H11 -> 0.44981413 | G35: ='Auxilo Finserve '!I11 -> 0.40056934 | H35: ='Auxilo Finserve '!J11 -> 0.46581931 | I35: ='Hdfc Credila'!H11 -> 0.27102363 | J35: ='Hdfc Credila'!I11 -> 0.19646833 | K35: ='Hdfc Credila'!J11 -> 0.20565613 | L35: ='EdGro Finance'!H11 -> 4 | M35: ='EdGro Finance'!I11 -> 0.875 | N35: ='EdGro Finance'!J11 -> 0.91525424
B36: Cost to Income (on total operating income) | C36: ='Avanse Financial'!H12 -> 0.18156538 | D36: ='Avanse Financial'!I12 -> 0.19582712 | E36: ='Avanse Financial'!J12 -> 0.15201249 | F36: ='Auxilo Finserve '!H12 -> 0.20353238 | G36: ='Auxilo Finserve '!I12 -> 0.1865177 | H36: ='Auxilo Finserve '!J12 -> 0.20065108 | I36: ='Hdfc Credila'!H12 -> 0.10171993 | J36: ='Hdfc Credila'!I12 -> 0.076182818 | K36: ='Hdfc Credila'!J12 -> 0.082179464 | L36: ='EdGro Finance'!H12 -> 1 | M36: ='EdGro Finance'!I12 -> 0.4375 | N36: ='EdGro Finance'!J12 -> 0.58064516
B37: Operating Expenses: Avg. Assets | C37: ='Avanse Financial'!H13 -> 0.026 | D37: ='Avanse Financial'!I13 -> 0.023747346 | E37: ='Avanse Financial'!J13 -> 0.019892749 | F37: ='Auxilo Finserve '!H13 -> 0.027262572 | G37: ='Auxilo Finserve '!I13 -> 0.02395865 | H37: ='Auxilo Finserve '!J13 -> 0.026207963 | I37: ='Hdfc Credila'!H13 -> 0.011767422 | J37: ='Hdfc Credila'!I13 -> 0.0090435715 | K37: ='Hdfc Credila'!J13 -> 0.0094528709 | L37: ='EdGro Finance'!H13 -> 0.026143791 | M37: ='EdGro Finance'!I13 -> 0.0672 | N37: ='EdGro Finance'!J13 -> 0.091216216
B38: Loan Book Performance
B39: Gross NPA % | C39: ='Avanse Financial'!H15 -> 0.0042409769 | D39: ='Avanse Financial'!I15 -> 0.0025545497 | E39: ='Avanse Financial'!J15 -> 0.0036406883 | F39: ='Auxilo Finserve '!H15 -> 0.008743093 | G39: ='Auxilo Finserve '!I15 -> 0.005257648 | H39: ='Auxilo Finserve '!J15 -> 0.0036461604 | I39: ='Hdfc Credila'!H15 -> 0.00076133848 | J39: ='Hdfc Credila'!I15 -> 0.0019151448 | K39: ='Hdfc Credila'!J15 -> 0.0026000147 | L39: ='EdGro Finance'!H15 -> - | M39: ='EdGro Finance'!I15 -> 0.0095 | N39: ='EdGro Finance'!J15 -> 0.0039
B40: Net NPA% | C40: ='Avanse Financial'!H16 -> 0.0012778838 | D40: ='Avanse Financial'!I16 -> 0.00039035815 | E40: ='Avanse Financial'!J16 -> 0.00059221864 | F40: ='Auxilo Finserve '!H16 -> 0.0050360215 | G40: ='Auxilo Finserve '!I16 -> 0.00081423752 | H40: ='Auxilo Finserve '!J16 -> 0.0010128223 | I40: ='Hdfc Credila'!H16 -> 0.00034732077 | J40: ='Hdfc Credila'!I16 -> 0.00067010888 | K40: ='Hdfc Credila'!J16 -> 0.00099992972 | L40: ='EdGro Finance'!H16 -> - | M40: ='EdGro Finance'!I16 -> 0.0039 | N40: ='EdGro Finance'!J16 -> 0.0029
B41: Provision coverage Ratio | C41: ='Avanse Financial'!H17 -> 0.69868173 | D41: ='Avanse Financial'!I17 -> 0.84719101 | E41: ='Avanse Financial'!J17 -> 0.83733333 | F41: ='Auxilo Finserve '!H17 -> 0.424 | G41: ='Auxilo Finserve '!I17 -> 0.84513274 | H41: ='Auxilo Finserve '!J17 -> 0.72222222 | I41: ='Hdfc Credila'!H17 -> 0.54380242 | J41: ='Hdfc Credila'!I17 -> 0.65010015 | K41: ='Hdfc Credila'!J17 -> 0.61541382 | L41: ='EdGro Finance'!H17 -> - | M41: ='EdGro Finance'!I17 -> 0.58947368 | N41: ='EdGro Finance'!J17 -> 0.25641026
B42: Credit Cost | C42: ='Avanse Financial'!H18 -> 0.0076 | D42: ='Avanse Financial'!I18 -> 0.0043218907 | E42: ='Avanse Financial'!J18 -> 0.0061177684 | F42: ='Auxilo Finserve '!H18 -> 0.0029713043 | G42: ='Auxilo Finserve '!I18 -> 0.0036044091 | H42: ='Auxilo Finserve '!J18 -> 0.0027503465 | I42: ='Hdfc Credila'!H18 -> 0.0022899745 | J42: ='Hdfc Credila'!I18 -> 0.0041930365 | K42: ='Hdfc Credila'!J18 -> 0.0037532264 | L42: ='EdGro Finance'!H18 -> 0.008 | M42: ='EdGro Finance'!I18 -> 0.0136 | N42: ='EdGro Finance'!J18 -> 0.018038331
B43: Return Indicators
B44: Pre Provisioning Operating Profit (PPOP)Margin | C44: ='Avanse Financial'!H20 -> 0.044793131 | D44: ='Avanse Financial'!I20 -> 0.044554888 | E44: ='Avanse Financial'!J20 -> 0.041810644 | F44: ='Auxilo Finserve '!H20 -> 0.03737469 | G44: ='Auxilo Finserve '!I20 -> 0.039622986 | H44: ='Auxilo Finserve '!J20 -> 0.032740626 | I44: ='Hdfc Credila'!H20 -> 0.031651013 | J44: ='Hdfc Credila'!I20 -> 0.036987112 | K44: ='Hdfc Credila'!J20 -> 0.03661671 | L44: ='EdGro Finance'!H20 -> -0.011070111 | M44: ='EdGro Finance'!I20 -> 0.0096 | N44: ='EdGro Finance'!J20 -> 0.0084459459
B45: RoA | C45: ='Avanse Financial'!H21 -> 0.028457487 | D45: ='Avanse Financial'!I21 -> 0.030373951 | E45: ='Avanse Financial'!J21 -> 0.027148767 | F45: ='Auxilo Finserve '!H21 -> 0.026005085 | G45: ='Auxilo Finserve '!I21 -> 0.027217999 | H45: ='Auxilo Finserve '!J21 -> 0.022593738 | I45: ='Hdfc Credila'!H21 -> 0.022077849 | J45: ='Hdfc Credila'!I21 -> 0.024866054 | K45: ='Hdfc Credila'!J21 -> 0.02497905 | L45: ='EdGro Finance'!H21 -> 0.0022 | M45: ='EdGro Finance'!I21 -> 0.0136 | N45: ='EdGro Finance'!J21 -> 0.0084459459
B46: RoE | C46: ='Avanse Financial'!H22 -> 0.1180145 | D46: ='Avanse Financial'!I22 -> 0.13155045 | E46: ='Avanse Financial'!J22 -> 0.11881483 | F46: ='Auxilo Finserve '!H22 -> 0.096016949 | G46: ='Auxilo Finserve '!I22 -> 0.094426396 | H46: ='Auxilo Finserve '!J22 -> 0.080829732 | I46: ='Hdfc Credila'!H22 -> 0.14344866 | J46: ='Hdfc Credila'!I22 -> 0.14557379 | K46: ='Hdfc Credila'!J22 -> 0.14197363 | L46: ='EdGro Finance'!H22 -> 0.0053 | M46: ='EdGro Finance'!I22 -> 0.0399 | N46: ='EdGro Finance'!J22 -> 0.021551724
B47: Spread
B48: Yields (A) | C48: ='Avanse Financial'!H24 -> 0.13212547 | D48: ='Avanse Financial'!I24 -> 0.13117306 | E48: ='Avanse Financial'!J24 -> 0.12953046 | F48: ='Auxilo Finserve '!H24 -> 0.13663242 | G48: ='Auxilo Finserve '!I24 -> 0.12961902 | H48: ='Auxilo Finserve '!J24 -> 0.12913635 | I48: ='Hdfc Credila'!H24 -> 0.11660749 | J48: ='Hdfc Credila'!I24 -> 0.11919194 | K48: ='Hdfc Credila'!J24 -> 0.1232179 | L48: ='EdGro Finance'!H24 -> 0.0354 | M48: ='EdGro Finance'!I24 -> 0.14814815 | N48: ='EdGro Finance'!J24 -> 0.16685457
B49: Avg. Cost of Borrowing(B) | C49: ='Avanse Financial'!H25 -> 0.1036883 | D49: ='Avanse Financial'!I25 -> 0.098907708 | E49: ='Avanse Financial'!J25 -> 0.092882076 | F49: ='Auxilo Finserve '!H25 -> 0.1026412 | G49: ='Auxilo Finserve '!I25 -> 0.097935103 | H49: ='Auxilo Finserve '!J25 -> 0.10469167 | I49: ='Hdfc Credila'!H25 -> 0.087231779 | J49: ='Hdfc Credila'!I25 -> 0.089163574 | K49: ='Hdfc Credila'!J25 -> 0.085899303 | L49: ='EdGro Finance'!H25 -> 0.0359 | M49: ='EdGro Finance'!I25 -> 0.12732095 | N49: ='EdGro Finance'!J25 -> 0.10134128
B50: Spread(A-B) | C50: ='Avanse Financial'!H26 -> 0.028437171 | D50: ='Avanse Financial'!I26 -> 0.032265348 | E50: ='Avanse Financial'!J26 -> 0.036648386 | F50: ='Auxilo Finserve '!H26 -> 0.033991216 | G50: ='Auxilo Finserve '!I26 -> 0.031683919 | H50: ='Auxilo Finserve '!J26 -> 0.024444681 | I50: ='Hdfc Credila'!H26 -> 0.029375711 | J50: ='Hdfc Credila'!I26 -> 0.030028367 | K50: ='Hdfc Credila'!J26 -> 0.037318602 | L50: ='EdGro Finance'!H26 -> -0.0005 | M50: ='EdGro Finance'!I26 -> 0.020827193 | N50: ='EdGro Finance'!J26 -> 0.065513284

Sheet NBFC-Gold Loan
C2: NBFC - Gold Loan
C3: Manappuram Finance | G3: Muthoot Finance | K3: Muthoot Fincorp | O3: Muthoot MCred (erstwhile Muthootu Mini Financiers) | S3: Kosamattam Finance
B4: Particulars | C4: ='Manappuram Finance'!H3 -> FY23 | D4: ='Manappuram Finance'!I3 -> FY24 | E4: ='Manappuram Finance'!J3 -> FY25 | F4: ='Manappuram Finance'!K3 -> FY26 | G4: FY 23 | H4: FY 24 | I4: FY 25 | J4: FY 26 | K4: FY 23 | L4: FY 24 | M4: FY 25 | N4: FY 26 | O4: FY 23 | P4: FY 24 | Q4: FY 25 | R4: FY 26 | S4: FY 23 | T4: FY 24 | U4: FY 25 | V4: FY 26
C5: ='Manappuram Finance'!H4 -> Aud | D5: ='Manappuram Finance'!I4 -> Aud | E5: ='Manappuram Finance'!J4 -> Aud | F5: ='Manappuram Finance'!K4 -> Aud | G5: Aud | H5: Aud | I5: Aud | J5: Aud | K5: Aud | L5: Aud | M5: Aud | N5: Aud | O5: Aud | P5: Aud | Q5: Aud | R5: Aud | S5: Aud | T5: Aud | U5: Aud | V5: Aud
C6: Rs in Crores | G6: Rs in Crores | K6: Rs in Crores | O6: Rs in Crores | S6: Rs in Crores
B7: Revenue from operations | C7: ='Manappuram Finance'!H6 -> 4827 | D7: ='Manappuram Finance'!I6 -> 5855 | E7: ='Manappuram Finance'!J6 -> 6914 | F7: ='Manappuram Finance'!K6 -> 7653 | G7: ='Muthoot Finance'!I6 -> 10514.849 | H7: ='Muthoot Finance'!J6 -> 12694 | I7: ='Muthoot Finance'!K6 -> 17156 | J7: ='Muthoot Finance'!L6 -> 27600 | K7: ='Muthoot Fincorp'!D6 -> 3469.8253 | L7: ='Muthoot Fincorp'!E6 -> 4011 | M7: ='Muthoot Fincorp'!F6 -> 5540 | N7: ='Muthoot Fincorp'!G6 -> 8364 | O7: ='Muthoot MCred'!D6 -> 544 | P7: ='Muthoot MCred'!E6 -> 672 | Q7: ='Muthoot MCred'!F6 -> 815 | R7: ='Muthoot MCred'!G6 -> 1113 | S7: ='Kosamattam Finance'!D6 -> 765 | T7: ='Kosamattam Finance'!E6 -> 859 | U7: ='Kosamattam Finance'!F6 -> 900 | V7: ='Kosamattam Finance'!G6 -> 1128
B8: Interest Income | C8: ='Manappuram Finance'!H7 -> 4666 | D8: ='Manappuram Finance'!I7 -> 5664 | E8: ='Manappuram Finance'!J7 -> 6694 | F8: ='Manappuram Finance'!K7 -> 7437 | G8: ='Muthoot Finance'!I7 -> 10148.791 | H8: ='Muthoot Finance'!J7 -> 12186 | I8: ='Muthoot Finance'!K7 -> 16525 | J8: ='Muthoot Finance'!L7 -> 27066 | K8: ='Muthoot Fincorp'!D7 -> 3304.8309 | L8: ='Muthoot Fincorp'!E7 -> 3715 | M8: ='Muthoot Fincorp'!F7 -> 4936 | N8: ='Muthoot Fincorp'!G7 -> 7728 | O8: ='Muthoot MCred'!D7 -> 519 | P8: ='Muthoot MCred'!E7 -> 627 | Q8: ='Muthoot MCred'!F7 -> 744 | R8: ='Muthoot MCred'!G7 -> 1046 | S8: ='Kosamattam Finance'!D7 -> 761 | T8: ='Kosamattam Finance'!E7 -> 854 | U8: ='Kosamattam Finance'!F7 -> 894 | V8: ='Kosamattam Finance'!G7 -> 1107
B9: Other Operation Income | C9: ='Manappuram Finance'!H9 -> 161 | D9: ='Manappuram Finance'!I9 -> 191 | E9: ='Manappuram Finance'!J9 -> 214 | F9: ='Manappuram Finance'!K9 -> 206 | G9: ='Muthoot Finance'!I9 -> 366.058 | H9: ='Muthoot Finance'!J9 -> 508 | I9: ='Muthoot Finance'!K9 -> 631 | J9: ='Muthoot Finance'!L9 -> 534 | K9: ='Muthoot Fincorp'!D9 -> 164.9944 | L9: ='Muthoot Fincorp'!E9 -> 177 | M9: ='Muthoot Fincorp'!F9 -> 273 | N9: ='Muthoot Fincorp'!G9 -> 462 | O9: ='Muthoot MCred'!D9 -> 24 | P9: ='Muthoot MCred'!E9 -> 42 | Q9: ='Muthoot MCred'!F9 -> 67 | R9: ='Muthoot MCred'!G9 -> 63 | S9: ='Kosamattam Finance'!D9 -> 4 | T9: ='Kosamattam Finance'!E9 -> 4 | U9: ='Kosamattam Finance'!F9 -> 6 | V9: ='Kosamattam Finance'!G9 -> 21
B10: Interest expended | C10: ='Manappuram Finance'!H10 -> 1498 | D10: ='Manappuram Finance'!I10 -> 1776 | E10: ='Manappuram Finance'!J10 -> 2327 | F10: ='Manappuram Finance'!K10 -> 2953 | G10: ='Muthoot Finance'!I10 -> 3699.14 | H10: ='Muthoot Finance'!J10 -> 4655 | I10: ='Muthoot Finance'!K10 -> 6429 | J10: ='Muthoot Finance'!L10 -> 9941 | K10: ='Muthoot Fincorp'!D10 -> 1571.3255 | L10: ='Muthoot Fincorp'!E10 -> 1805 | M10: ='Muthoot Fincorp'!F10 -> 2313 | N10: ='Muthoot Fincorp'!G10 -> 3069 | O10: ='Muthoot MCred'!D10 -> 283 | P10: ='Muthoot MCred'!E10 -> 345 | Q10: ='Muthoot MCred'!F10 -> 398 | R10: ='Muthoot MCred'!G10 -> 530 | S10: ='Kosamattam Finance'!D10 -> 433 | T10: ='Kosamattam Finance'!E10 -> 512 | U10: ='Kosamattam Finance'!F10 -> 539 | V10: ='Kosamattam Finance'!G10 -> 628
B11: Net Interest Income | C11: ='Manappuram Finance'!H11 -> 3168 | D11: ='Manappuram Finance'!I11 -> 3888 | E11: ='Manappuram Finance'!J11 -> 4367 | F11: ='Manappuram Finance'!K11 -> 4484 | G11: ='Muthoot Finance'!I11 -> 6449.651 | H11: ='Muthoot Finance'!J11 -> 7531 | I11: ='Muthoot Finance'!K11 -> 10097 | J11: ='Muthoot Finance'!L11 -> 17125 | K11: ='Muthoot Fincorp'!D11 -> 1733.5054 | L11: ='Muthoot Fincorp'!E11 -> 1910 | M11: ='Muthoot Fincorp'!F11 -> 2623 | N11: ='Muthoot Fincorp'!G11 -> 4659 | O11: ='Muthoot MCred'!D11 -> 236 | P11: ='Muthoot MCred'!E11 -> 282 | Q11: ='Muthoot MCred'!F11 -> 347 | R11: ='Muthoot MCred'!G11 -> 516 | S11: ='Kosamattam Finance'!D11 -> 328 | T11: ='Kosamattam Finance'!E11 -> 342 | U11: ='Kosamattam Finance'!F11 -> 355 | V11: ='Kosamattam Finance'!G11 -> 479
B12: Total Operating Income | C12: ='Manappuram Finance'!H12 -> 4827 | D12: ='Manappuram Finance'!I12 -> 5855 | E12: ='Manappuram Finance'!J12 -> 6908 | F12: ='Manappuram Finance'!K12 -> 7643 | G12: ='Muthoot Finance'!I12 -> 10514.849 | H12: ='Muthoot Finance'!J12 -> 12694 | I12: ='Muthoot Finance'!K12 -> 17156 | J12: ='Muthoot Finance'!L12 -> 27600 | K12: ='Muthoot Fincorp'!D12 -> 3469.8253 | L12: ='Muthoot Fincorp'!E12 -> 3892 | M12: ='Muthoot Fincorp'!F12 -> 5209 | N12: ='Muthoot Fincorp'!G12 -> 8190 | O12: ='Muthoot MCred'!D12 -> 543 | P12: ='Muthoot MCred'!E12 -> 669 | Q12: ='Muthoot MCred'!F12 -> 811 | R12: ='Muthoot MCred'!G12 -> 1109 | S12: ='Kosamattam Finance'!D12 -> 765 | T12: ='Kosamattam Finance'!E12 -> 858 | U12: ='Kosamattam Finance'!F12 -> 900 | V12: ='Kosamattam Finance'!G12 -> 1128
B13: Other income | C13: ='Manappuram Finance'!H13 -> 0 | D13: ='Manappuram Finance'!I13 -> 0 | E13: ='Manappuram Finance'!J13 -> 6 | F13: ='Manappuram Finance'!K13 -> 11 | G13: ='Muthoot Finance'!I13 -> 28.899 | H13: ='Muthoot Finance'!J13 -> 59 | I13: ='Muthoot Finance'!K13 -> 57 | J13: ='Muthoot Finance'!L13 -> 42 | K13: ='Muthoot Fincorp'!D13 -> 21.4383 | L13: ='Muthoot Fincorp'!E13 -> 119 | M13: ='Muthoot Fincorp'!F13 -> 331 | N13: ='Muthoot Fincorp'!G13 -> 174 | O13: ='Muthoot MCred'!D13 -> 1 | P13: ='Muthoot MCred'!E13 -> 2 | Q13: ='Muthoot MCred'!F13 -> 4 | R13: ='Muthoot MCred'!G13 -> 4 | S13: ='Kosamattam Finance'!D13 -> 0 | T13: ='Kosamattam Finance'!E13 -> 1 | U13: ='Kosamattam Finance'!F13 -> 0 | V13: ='Kosamattam Finance'!G13 -> 0
B14: Total Income | C14: ='Manappuram Finance'!H14 -> 4827 | D14: ='Manappuram Finance'!I14 -> 5855 | E14: ='Manappuram Finance'!J14 -> 6914 | F14: ='Manappuram Finance'!K14 -> 7654 | G14: ='Muthoot Finance'!I14 -> 10543.748 | H14: ='Muthoot Finance'!J14 -> 12753 | I14: ='Muthoot Finance'!K14 -> 17213 | J14: ='Muthoot Finance'!L14 -> 27642 | K14: ='Muthoot Fincorp'!D14 -> 3491.2636 | L14: ='Muthoot Fincorp'!E14 -> 4011 | M14: ='Muthoot Fincorp'!F14 -> 5540 | N14: ='Muthoot Fincorp'!G14 -> 8364 | O14: ='Muthoot MCred'!D14 -> 544 | P14: ='Muthoot MCred'!E14 -> 671 | Q14: ='Muthoot MCred'!F14 -> 815 | R14: ='Muthoot MCred'!G14 -> 1113 | S14: ='Kosamattam Finance'!D14 -> 765 | T14: ='Kosamattam Finance'!E14 -> 859 | U14: ='Kosamattam Finance'!F14 -> 900 | V14: ='Kosamattam Finance'!G14 -> 1128
B15: Operating expenses | C15: ='Manappuram Finance'!H15 -> 1577 | D15: ='Manappuram Finance'!I15 -> 1749 | E15: ='Manappuram Finance'!J15 -> 1949 | F15: ='Manappuram Finance'!K15 -> 2126 | G15: ='Muthoot Finance'!I15 -> 2117.655 | H15: ='Muthoot Finance'!J15 -> 2393 | I15: ='Muthoot Finance'!K15 -> 2890 | J15: ='Muthoot Finance'!L15 -> 3544 | K15: ='Muthoot Fincorp'!D15 -> 1227.437 | L15: ='Muthoot Fincorp'!E15 -> 1396 | M15: ='Muthoot Fincorp'!F15 -> 1971 | N15: ='Muthoot Fincorp'!G15 -> 2853 | O15: ='Muthoot MCred'!D15 -> 181 | P15: ='Muthoot MCred'!E15 -> 209 | Q15: ='Muthoot MCred'!F15 -> 274 | R15: ='Muthoot MCred'!G15 -> 333 | S15: ='Kosamattam Finance'!D15 -> 176 | T15: ='Kosamattam Finance'!E15 -> 183 | U15: ='Kosamattam Finance'!F15 -> 185 | V15: ='Kosamattam Finance'!G15 -> 239
B16: Operating profit | C16: ='Manappuram Finance'!H16 -> 3250 | D16: ='Manappuram Finance'!I16 -> 4106 | E16: ='Manappuram Finance'!J16 -> 4959 | F16: ='Manappuram Finance'!K16 -> 5517 | G16: ='Muthoot Finance'!I16 -> 8397.194 | H16: ='Muthoot Finance'!J16 -> 10301 | I16: ='Muthoot Finance'!K16 -> 14266 | J16: ='Muthoot Finance'!L16 -> 24056 | K16: ='Muthoot Fincorp'!D16 -> 2242.3883 | L16: ='Muthoot Fincorp'!E16 -> 2496 | M16: ='Muthoot Fincorp'!F16 -> 3238 | N16: ='Muthoot Fincorp'!G16 -> 5337 | O16: ='Muthoot MCred'!D16 -> 362 | P16: ='Muthoot MCred'!E16 -> 460 | Q16: ='Muthoot MCred'!F16 -> 537 | R16: ='Muthoot MCred'!G16 -> 776 | S16: ='Kosamattam Finance'!D16 -> 589 | T16: ='Kosamattam Finance'!E16 -> 675 | U16: ='Kosamattam Finance'!F16 -> 715 | V16: ='Kosamattam Finance'!G16 -> 889
B17: Pre-provisioning operating profit | C17: ='Manappuram Finance'!H17 -> 1752 | D17: ='Manappuram Finance'!I17 -> 2330 | E17: ='Manappuram Finance'!J17 -> 2638 | F17: ='Manappuram Finance'!K17 -> 2575 | G17: ='Muthoot Finance'!I17 -> 4726.953 | H17: ='Muthoot Finance'!J17 -> 5705 | I17: ='Muthoot Finance'!K17 -> 7894 | J17: ='Muthoot Finance'!L17 -> 14157 | K17: ='Muthoot Fincorp'!D17 -> 692.5011 | L17: ='Muthoot Fincorp'!E17 -> 810 | M17: ='Muthoot Fincorp'!F17 -> 1256 | N17: ='Muthoot Fincorp'!G17 -> 2442 | O17: ='Muthoot MCred'!D17 -> 80 | P17: ='Muthoot MCred'!E17 -> 117 | Q17: ='Muthoot MCred'!F17 -> 143 | R17: ='Muthoot MCred'!G17 -> 250 | S17: ='Kosamattam Finance'!D17 -> 156 | T17: ='Kosamattam Finance'!E17 -> 163 | U17: ='Kosamattam Finance'!F17 -> 176 | V17: ='Kosamattam Finance'!G17 -> 261
B18: Provisions | C18: ='Manappuram Finance'!H18 -> 45 | D18: ='Manappuram Finance'!I18 -> 108 | E18: ='Manappuram Finance'!J18 -> 263 | F18: ='Manappuram Finance'!K18 -> 535 | G18: ='Muthoot Finance'!I18 -> 60.527 | H18: ='Muthoot Finance'!J18 -> 198 | I18: ='Muthoot Finance'!K18 -> 767 | J18: ='Muthoot Finance'!L18 -> 470 | K18: ='Muthoot Fincorp'!D18 -> 67.1702 | L18: ='Muthoot Fincorp'!E18 -> 30 | M18: ='Muthoot Fincorp'!F18 -> 111 | N18: ='Muthoot Fincorp'!G18 -> 259 | O18: ='Muthoot MCred'!D18 -> -2 | P18: ='Muthoot MCred'!E18 -> 7 | Q18: ='Muthoot MCred'!F18 -> 14 | R18: ='Muthoot MCred'!G18 -> 11 | S18: ='Kosamattam Finance'!D18 -> 28 | T18: ='Kosamattam Finance'!E18 -> 10 | U18: ='Kosamattam Finance'!F18 -> 6 | V18: ='Kosamattam Finance'!G18 -> 11
B19: PAT | C19: ='Manappuram Finance'!H19 -> 1266 | D19: ='Manappuram Finance'!I19 -> 1658 | E19: ='Manappuram Finance'!J19 -> 1783 | F19: ='Manappuram Finance'!K19 -> 1525 | G19: ='Muthoot Finance'!I19 -> 3473.531 | H19: ='Muthoot Finance'!J19 -> 4050 | I19: ='Muthoot Finance'!K19 -> 5201 | J19: ='Muthoot Finance'!L19 -> 10134 | K19: ='Muthoot Fincorp'!D19 -> 459.8108 | L19: ='Muthoot Fincorp'!E19 -> 563 | M19: ='Muthoot Fincorp'!F19 -> 787 | N19: ='Muthoot Fincorp'!G19 -> 1640 | O19: ='Muthoot MCred'!D19 -> 67 | P19: ='Muthoot MCred'!E19 -> 78 | Q19: ='Muthoot MCred'!F19 -> 94 | R19: ='Muthoot MCred'!G19 -> 177 | S19: ='Kosamattam Finance'!D19 -> 107 | T19: ='Kosamattam Finance'!E19 -> 114 | U19: ='Kosamattam Finance'!F19 -> 127 | V19: ='Kosamattam Finance'!G19 -> 185
B20: TNW | C20: ='Manappuram Finance'!H20 -> 8885 | D20: ='Manappuram Finance'!I20 -> 10246 | E20: ='Manappuram Finance'!J20 -> 11682 | F20: ='Manappuram Finance'!K20 -> 15832 | G20: ='Muthoot Finance'!I20 -> 21061.928 | H20: ='Muthoot Finance'!J20 -> 24253 | I20: ='Muthoot Finance'!K20 -> 26724 | J20: ='Muthoot Finance'!L20 -> 34081 | K20: ='Muthoot Fincorp'!D20 -> 3893.0345 | L20: ='Muthoot Fincorp'!E20 -> 4305 | M20: ='Muthoot Fincorp'!F20 -> 4810 | N20: ='Muthoot Fincorp'!G20 -> 6679 | O20: ='Muthoot MCred'!D20 -> 622 | P20: ='Muthoot MCred'!E20 -> 701 | Q20: ='Muthoot MCred'!F20 -> 797 | R20: ='Muthoot MCred'!G20 -> 1159 | S20: ='Kosamattam Finance'!D20 -> 761 | T20: ='Kosamattam Finance'!E20 -> 912 | U20: ='Kosamattam Finance'!F20 -> 1047 | V20: ='Kosamattam Finance'!G20 -> 1067
B21: Total Debt | C21: ='Manappuram Finance'!H22 -> 19229 | D21: ='Manappuram Finance'!I22 -> 22467 | E21: ='Manappuram Finance'!J22 -> 27046 | F21: ='Manappuram Finance'!K22 -> 50611 | G21: ='Muthoot Finance'!I22 -> 49734.307 | H21: ='Muthoot Finance'!J22 -> 58783 | I21: ='Muthoot Finance'!K22 -> 89820 | J21: ='Muthoot Finance'!L22 -> 138443 | K21: ='Muthoot Fincorp'!D22 -> 17823.175 | L21: ='Muthoot Fincorp'!E22 -> 20596 | M21: ='Muthoot Fincorp'!F22 -> 25855 | N21: ='Muthoot Fincorp'!G22 -> 43609 | O21: ='Muthoot MCred'!D22 -> 3207 | P21: ='Muthoot MCred'!E22 -> 3581 | Q21: ='Muthoot MCred'!F22 -> 4119 | R21: ='Muthoot MCred'!G22 -> 6261 | S21: ='Kosamattam Finance'!D22 -> 4659 | T21: ='Kosamattam Finance'!E22 -> 5001 | U21: ='Kosamattam Finance'!F22 -> 5281 | V21: ='Kosamattam Finance'!G22 -> 6925
B22: Total Assets | C22: ='Manappuram Finance'!H23 -> 29338 | D22: ='Manappuram Finance'!I23 -> 33893 | E22: ='Manappuram Finance'!J23 -> 39836 | F22: ='Manappuram Finance'!K23 -> 67554 | G22: ='Muthoot Finance'!I23 -> 72619.814 | H22: ='Muthoot Finance'!J23 -> 85028 | I22: ='Muthoot Finance'!K23 -> 121249 | J22: ='Muthoot Finance'!L23 -> 179945 | K22: ='Muthoot Fincorp'!D23 -> 23699.001 | L22: ='Muthoot Fincorp'!E23 -> 26611 | M22: ='Muthoot Fincorp'!F23 -> 32811 | N22: ='Muthoot Fincorp'!G23 -> 52671 | O22: ='Muthoot MCred'!D23 -> 3858 | P22: ='Muthoot MCred'!E23 -> 4316 | Q22: ='Muthoot MCred'!F23 -> 4960 | R22: ='Muthoot MCred'!G23 -> 7493 | S22: ='Kosamattam Finance'!D23 -> 5444 | T22: ='Kosamattam Finance'!E23 -> 5986 | U22: ='Kosamattam Finance'!F23 -> 6406 | V22: ='Kosamattam Finance'!G23 -> 8285
B23: Loans & Advances (Gross) | C23: ='Manappuram Finance'!H24 -> 24735 | D23: ='Manappuram Finance'!I24 -> 29271 | E23: ='Manappuram Finance'!J24 -> 33690 | F23: ='Manappuram Finance'!K24 -> 56228 | G23: ='Muthoot Finance'!I24 -> 65030.642 | H23: ='Muthoot Finance'!J24 -> 77936 | I23: ='Muthoot Finance'!K24 -> 110254 | J23: ='Muthoot Finance'!L24 -> 163400 | K23: ='Muthoot Fincorp'!D24 -> 17585.782 | L23: ='Muthoot Fincorp'!E24 -> 21415 | M23: ='Muthoot Fincorp'!F24 -> 25752 | N23: ='Muthoot Fincorp'!G24 -> 46193 | O23: ='Muthoot MCred'!D24 -> 3263 | P23: ='Muthoot MCred'!E24 -> 3523 | Q23: ='Muthoot MCred'!F24 -> 4142 | R23: ='Muthoot MCred'!G24 -> 6625 | S23: ='Kosamattam Finance'!D24 -> 4910 | T23: ='Kosamattam Finance'!E24 -> 5383 | U23: ='Kosamattam Finance'!F24 -> 5766 | V23: ='Kosamattam Finance'!G24 -> 7786
B24: Gross NPAs | C24: ='Manappuram Finance'!H25 -> 321 | D24: ='Manappuram Finance'!I25 -> 547 | E24: ='Manappuram Finance'!J25 -> 891 | F24: ='Manappuram Finance'!K25 -> 991 | G24: ='Muthoot Finance'!I25 -> 2398.596 | H24: ='Muthoot Finance'!J25 -> 2485 | I24: ='Muthoot Finance'!K25 -> 3700 | J24: ='Muthoot Finance'!L25 -> 3824 | K24: ='Muthoot Fincorp'!D25 -> 371.6113 | L24: ='Muthoot Fincorp'!E25 -> 351 | M24: ='Muthoot Fincorp'!F25 -> 516 | N24: ='Muthoot Fincorp'!G25 -> 476 | O24: ='Muthoot MCred'!D25 -> 14 | P24: ='Muthoot MCred'!E25 -> 31 | Q24: ='Muthoot MCred'!F25 -> 35 | R24: ='Muthoot MCred'!G25 -> 41 | S24: ='Kosamattam Finance'!D25 -> 78 | T24: ='Kosamattam Finance'!E25 -> 78 | U24: ='Kosamattam Finance'!F25 -> 79 | V24: ='Kosamattam Finance'!G25 -> 94
B25: Net NPAs | C25: ='Manappuram Finance'!H26 -> 255 | D25: ='Manappuram Finance'!I26 -> 456 | E25: ='Manappuram Finance'!J26 -> 753 | F25: ='Manappuram Finance'!K26 -> 842 | G25: ='Muthoot Finance'!I26 -> 2152.124 | H25: ='Muthoot Finance'!J26 -> 2197 | I25: ='Muthoot Finance'!K26 -> 3037 | J25: ='Muthoot Finance'!L26 -> 3324 | K25: ='Muthoot Fincorp'!D26 -> 102.2142 | L25: ='Muthoot Fincorp'!E26 -> 139 | M25: ='Muthoot Fincorp'!F26 -> 332 | N25: ='Muthoot Fincorp'!G26 -> 263 | O25: ='Muthoot MCred'!D26 -> 12 | P25: ='Muthoot MCred'!E26 -> 25 | Q25: ='Muthoot MCred'!F26 -> 21 | R25: ='Muthoot MCred'!G26 -> 17 | S25: ='Kosamattam Finance'!D26 -> 33 | T25: ='Kosamattam Finance'!E26 -> 28 | U25: ='Kosamattam Finance'!F26 -> 27 | V25: ='Kosamattam Finance'!G26 -> 38
C27: ='Manappuram Finance'!N2 -> FY23 (A) | D27: ='Manappuram Finance'!O2 -> FY24 (A) | E27: ='Manappuram Finance'!P2 -> FY25 (A) | F27: ='Manappuram Finance'!Q2 -> FY26 (A) | G27: ='Muthoot Finance'!P3 -> FY23 (A) | H27: ='Muthoot Finance'!Q3 -> FY24 (A) | I27: ='Muthoot Finance'!R3 -> FY25 (A) | J27: ='Muthoot Finance'!S3 -> FY26 (A) | K27: ='Muthoot Fincorp'!K3 -> FY23 (A) | L27: ='Muthoot Fincorp'!L3 -> FY24 (A) | M27: ='Muthoot Fincorp'!M3 -> FY25 (A) | N27: ='Muthoot Fincorp'!N3 -> FY26 (A) | O27: ='Muthoot MCred'!K3 -> FY23 (A) | P27: ='Muthoot MCred'!L3 -> FY24 (A) | Q27: ='Muthoot MCred'!M3 -> FY25 (A) | R27: ='Muthoot MCred'!N3 -> FY26 (A) | S27: ='Kosamattam Finance'!K3 -> FY23 (A) | T27: ='Kosamattam Finance'!L3 -> FY24 (A) | U27: ='Kosamattam Finance'!M3 -> FY25 (A) | V27: ='Kosamattam Finance'!N3 -> FY26 (A)
B28: Profitability
B29: Net Interest Margin | C29: ='Manappuram Finance'!N4 -> 0.13312949 | D29: ='Manappuram Finance'!O4 -> 0.14114777 | E29: ='Manappuram Finance'!P4 -> 0.1387208 | F29: ='Manappuram Finance'!Q4 -> 0.099735314 | G29: ='Muthoot Finance'!P5 -> 0.10303727 | H29: ='Muthoot Finance'!Q5 -> 0.10535325 | I29: ='Muthoot Finance'!R5 -> 0.10730645 | J29: ='Muthoot Finance'!S5 -> 0.12515805 | K29: ='Muthoot Fincorp'!K4 -> 0.09931591 | L29: ='Muthoot Fincorp'!L4 -> 0.097946754 | M29: ='Muthoot Fincorp'!M4 -> 0.11122183 | N29: ='Muthoot Fincorp'!N4 -> 0.1295156 | O29: ='Muthoot MCred'!K4 -> 0.081921623 | P29: ='Muthoot MCred'!L4 -> 0.08311229 | Q29: ='Muthoot MCred'!M4 -> 0.090541422 | R29: ='Muthoot MCred'!N4 -> 0.095848426 | S29: ='Kosamattam Finance'!J4 -> 0.058619837 | T29: ='Kosamattam Finance'!K4 -> 0.073271529 | U29: ='Kosamattam Finance'!L4 -> 0.066452929 | V29: ='Kosamattam Finance'!M4 -> 0.063682842
B30: Capitalization
B31: Leverage (Debt/TNW) | C31: ='Manappuram Finance'!N6 -> 2.1413702 | D31: ='Manappuram Finance'!O6 -> 2.1928272 | E31: ='Manappuram Finance'!P6 -> 2.3852192 | F31: ='Manappuram Finance'!Q6 -> 3.1967534 | G31: ='Muthoot Finance'!P7 -> 2.3613369 | H31: ='Muthoot Finance'!Q7 -> 2.4237414 | I31: ='Muthoot Finance'!R7 -> 3.3610238 | J31: ='Muthoot Finance'!S7 -> 4.0621754 | K31: ='Muthoot Fincorp'!K6 -> 4.5782216 | L31: ='Muthoot Fincorp'!L6 -> 4.7842044 | M31: ='Muthoot Fincorp'!M6 -> 5.3752599 | N31: ='Muthoot Fincorp'!N6 -> 6.5292708 | O31: ='Muthoot MCred'!K6 -> 5.1559486 | P31: ='Muthoot MCred'!L6 -> 5.1084165 | Q31: ='Muthoot MCred'!M6 -> 5.1681305 | R31: ='Muthoot MCred'!N6 -> 5.4020708 | S31: ='Kosamattam Finance'!J6 -> 6.0372093 | T31: ='Kosamattam Finance'!K6 -> 6.1222076 | U31: ='Kosamattam Finance'!L6 -> 5.4835526 | V31: ='Kosamattam Finance'!M6 -> 5.0439351
B32: CAR | C32: ='Manappuram Finance'!N7 -> 0.317 | D32: ='Manappuram Finance'!O7 -> 0.3058 | E32: ='Manappuram Finance'!P7 -> 0.3091 | F32: ='Manappuram Finance'!Q7 -> 0.213 | G32: ='Muthoot Finance'!P8 -> 0.3177 | H32: ='Muthoot Finance'!Q8 -> 0 | I32: ='Muthoot Finance'!R8 -> 0 | J32: ='Muthoot Finance'!S8 -> 0 | K32: ='Muthoot Fincorp'!K7 -> 0.2134 | L32: 0.2001 | M32: 0.195 | N32: 0.18 | O32: ='Muthoot MCred'!K7 -> 0.2282 | P32: ='Muthoot MCred'!L7 -> 0.2386 | Q32: ='Muthoot MCred'!M7 -> 0.2138 | R32: ='Muthoot MCred'!N7 -> 0.1812 | S32: ='Kosamattam Finance'!J7 -> 0.1865 | T32: ='Kosamattam Finance'!K7 -> 0.1771 | U32: ='Kosamattam Finance'!L7 -> 0.1842 | V32: ='Kosamattam Finance'!M7 -> 0.1878
B33: TNW/Loan Book | C33: ='Manappuram Finance'!N8 -> 0.36305093 | D33: ='Manappuram Finance'!O8 -> 0.34907521 | E33: ='Manappuram Finance'!P8 -> 0.33656871 | F33: ='Manappuram Finance'!Q8 -> 0.2815679 | G33: ='Muthoot Finance'!P9 -> 0.32387698 | H33: ='Muthoot Finance'!Q9 -> 0.31119123 | I33: ='Muthoot Finance'!R9 -> 0.24238576 | J33: ='Muthoot Finance'!S9 -> 0.20857405 | K33: ='Muthoot Fincorp'!K8 -> 0.22137398 | L33: ='Muthoot Fincorp'!L8 -> 0.20102732 | M33: ='Muthoot Fincorp'!M8 -> 0.18678161 | N33: ='Muthoot Fincorp'!N8 -> 0.14458901 | O33: ='Muthoot MCred'!K8 -> 0.19062213 | P33: ='Muthoot MCred'!L8 -> 0.19897814 | Q33: ='Muthoot MCred'!M8 -> 0.19241912 | R33: ='Muthoot MCred'!N8 -> 0.1749434 | S33: ='Kosamattam Finance'!J8 -> 0.159535 | T33: ='Kosamattam Finance'!K8 -> 0.15498982 | U33: ='Kosamattam Finance'!L8 -> 0.16942226 | V33: ='Kosamattam Finance'!M8 -> 0.18158169
B34: Operational Efficiency
B35: Cost to Income (on total operating income net-off interest expenses) | C35: ='Manappuram Finance'!N10 -> 0.47740883 | D35: ='Manappuram Finance'!O10 -> 0.42393529 | E35: ='Manappuram Finance'!P10 -> 0.42545296 | F35: ='Manappuram Finance'!Q10 -> 0.4533049 | G35: ='Muthoot Finance'!P11 -> 0.31070209 | H35: ='Muthoot Finance'!Q11 -> 0.29767384 | I35: ='Muthoot Finance'!R11 -> 0.26941363 | J35: ='Muthoot Finance'!S11 -> 0.20069087 | K35: ='Muthoot Fincorp'!K10 -> 0.64652996 | L35: ='Muthoot Fincorp'!L10 -> 0.66890273 | M35: ='Muthoot Fincorp'!M10 -> 0.68059392 | N35: ='Muthoot Fincorp'!N10 -> 0.55711775 | O35: ='Muthoot MCred'!K10 -> 0.69615385 | P35: ='Muthoot MCred'!L10 -> 0.64506173 | Q35: ='Muthoot MCred'!M10 -> 0.66343826 | R35: ='Muthoot MCred'!N10 -> 0.57512953 | S35: ='Kosamattam Finance'!J10 -> 0.59583333 | T35: ='Kosamattam Finance'!K10 -> 0.53012048 | U35: ='Kosamattam Finance'!L10 -> 0.52890173 | V35: ='Kosamattam Finance'!M10 -> 0.51246537
B36: Cost to Income (on total operating income) | C36: ='Manappuram Finance'!N11 -> 0.32843182 | D36: ='Manappuram Finance'!O11 -> 0.29099935 | E36: ='Manappuram Finance'!P11 -> 0.28213665 | F36: ='Manappuram Finance'!Q11 -> 0.27816302 | G36: ='Muthoot Finance'!P12 -> 0.20139662 | H36: ='Muthoot Finance'!Q12 -> 0.18851426 | I36: ='Muthoot Finance'!R12 -> 0.16845419 | J36: ='Muthoot Finance'!S12 -> 0.1284058 | K36: ='Muthoot Fincorp'!K11 -> 0.35374605 | L36: ='Muthoot Fincorp'!L11 -> 0.35868448 | M36: ='Muthoot Fincorp'!M11 -> 0.37838357 | N36: ='Muthoot Fincorp'!N11 -> 0.34835165 | O36: ='Muthoot MCred'!K11 -> 0.33333333 | P36: ='Muthoot MCred'!L11 -> 0.31240658 | Q36: ='Muthoot MCred'!M11 -> 0.3378545 | R36: ='Muthoot MCred'!N11 -> 0.30027051 | S36: ='Kosamattam Finance'!J11 -> 0.23481117 | T36: ='Kosamattam Finance'!K11 -> 0.23006536 | U36: ='Kosamattam Finance'!L11 -> 0.21328671 | V36: ='Kosamattam Finance'!M11 -> 0.20555556
B37: Operating Expenses: Avg. Assets | C37: ='Manappuram Finance'!N12 -> 0.056015316 | D37: ='Manappuram Finance'!O12 -> 0.053593322 | E37: ='Manappuram Finance'!P12 -> 0.052869292 | F37: ='Manappuram Finance'!Q12 -> 0.039594003 | G37: ='Muthoot Finance'!P13 -> 0.02958139 | H37: ='Muthoot Finance'!Q13 -> 0.03035881 | I37: ='Muthoot Finance'!R13 -> 0.028020574 | J37: ='Muthoot Finance'!S13 -> 0.023533005 | K37: ='Muthoot Fincorp'!K12 -> 0.052676566 | L37: ='Muthoot Fincorp'!L12 -> 0.055495924 | M37: ='Muthoot Fincorp'!M12 -> 0.066339066 | N37: ='Muthoot Fincorp'!N12 -> 0.066750895 | O37: ='Muthoot MCred'!K12 -> 0.051066453 | P37: ='Muthoot MCred'!L12 -> 0.051137754 | Q37: ='Muthoot MCred'!M12 -> 0.059077188 | R37: ='Muthoot MCred'!N12 -> 0.053481089 | S37: ='Kosamattam Finance'!J12 -> 0.035369775 | T37: ='Kosamattam Finance'!K12 -> 0.037103405 | U37: ='Kosamattam Finance'!L12 -> 0.032020997 | V37: ='Kosamattam Finance'!M12 -> 0.029857973
B38: Loan Book Performance
B39: Gross NPA % | C39: ='Manappuram Finance'!N14 -> 0.012981549 | D39: ='Manappuram Finance'!O14 -> 0.018625044 | E39: ='Manappuram Finance'!P14 -> 0.026447017 | F39: ='Manappuram Finance'!Q14 -> 0.017624671 | G39: ='Muthoot Finance'!P15 -> 0.036884089 | H39: ='Muthoot Finance'!Q15 -> 0.031885137 | I39: ='Muthoot Finance'!R15 -> 0.033558873 | J39: ='Muthoot Finance'!S15 -> 0.023402693 | K39: ='Muthoot Fincorp'!K14 -> 0.021131349 | L39: ='Muthoot Fincorp'!L14 -> 0.016390381 | M39: ='Muthoot Fincorp'!M14 -> 0.020037279 | N39: ='Muthoot Fincorp'!N14 -> 0.010304592 | O39: ='Muthoot MCred'!K14 -> 0.0042905302 | P39: ='Muthoot MCred'!L14 -> 0.0087993188 | Q39: ='Muthoot MCred'!M14 -> 0.0084500241 | R39: ='Muthoot MCred'!N14 -> 0.0061886792 | S39: ='Kosamattam Finance'!J14 -> 0.014098442 | T39: ='Kosamattam Finance'!K14 -> 0.015885947 | U39: ='Kosamattam Finance'!L14 -> 0.014490061 | V39: ='Kosamattam Finance'!M14 -> 0.013701006
B40: Net NPA% | C40: ='Manappuram Finance'!N15 -> 0.010327086 | D40: ='Manappuram Finance'!O15 -> 0.015513057 | E40: ='Manappuram Finance'!P15 -> 0.022350846 | F40: ='Manappuram Finance'!Q15 -> 0.014974746 | G40: ='Muthoot Finance'!P16 -> 0.033093999 | H40: ='Muthoot Finance'!Q16 -> 0.028189797 | I40: ='Muthoot Finance'!R16 -> 0.027545486 | J40: ='Muthoot Finance'!S16 -> 0.020342717 | K40: ='Muthoot Fincorp'!K15 -> 0.0058123205 | L40: ='Muthoot Fincorp'!L15 -> 0.0064907775 | M40: ='Muthoot Fincorp'!M15 -> 0.012892203 | N40: ='Muthoot Fincorp'!N15 -> 0.0056935033 | O40: ='Muthoot MCred'!K15 -> 0.0036775973 | P40: ='Muthoot MCred'!L15 -> 0.0070962248 | Q40: ='Muthoot MCred'!M15 -> 0.0050700145 | R40: ='Muthoot MCred'!N15 -> 0.0025660377 | S40: ='Kosamattam Finance'!J15 -> 0.0086569379 | T40: ='Kosamattam Finance'!K15 -> 0.0067209776 | U40: ='Kosamattam Finance'!L15 -> 0.0052015605 | V40: ='Kosamattam Finance'!M15 -> 0.0046826223
B41: Provision coverage Ratio | C41: ='Manappuram Finance'!N16 -> 0.2044797 | D41: ='Manappuram Finance'!O16 -> 0.16708619 | E41: ='Manappuram Finance'!P16 -> 0.15488215 | F41: ='Manappuram Finance'!Q16 -> 0.15035318 | G41: ='Muthoot Finance'!P17 -> 0.10275678 | H41: ='Muthoot Finance'!Q17 -> 0.11589537 | I41: ='Muthoot Finance'!R17 -> 0.17918919 | J41: ='Muthoot Finance'!S17 -> 0.13075314 | K41: ='Muthoot Fincorp'!K16 -> 0.72494324 | L41: ='Muthoot Fincorp'!L16 -> 0.6039886 | M41: ='Muthoot Fincorp'!M16 -> 0.35658915 | N41: ='Muthoot Fincorp'!N16 -> 0.44747899 | O41: ='Muthoot MCred'!K16 -> 0.14285714 | P41: ='Muthoot MCred'!L16 -> 0.19354839 | Q41: ='Muthoot MCred'!M16 -> 0.4 | R41: ='Muthoot MCred'!N16 -> 0.58536585 | S41: ='Kosamattam Finance'!J16 -> 0.38596491 | T41: ='Kosamattam Finance'!K16 -> 0.57692308 | U41: ='Kosamattam Finance'!L16 -> 0.64102564 | V41: ='Kosamattam Finance'!M16 -> 0.65822785
B42: Credit Cost | C42: ='Manappuram Finance'!N17 -> 0.0018935467 | D42: ='Manappuram Finance'!O17 -> 0.0040084856 | E42: ='Manappuram Finance'!P17 -> 0.0083543781 | F42: ='Manappuram Finance'!Q17 -> 0.011899731 | G42: ='Muthoot Finance'!P18 -> 0.00096695726 | H42: ='Muthoot Finance'!Q18 -> 0.0027698769 | I42: ='Muthoot Finance'!R18 -> 0.0081513364 | J42: ='Muthoot Finance'!S18 -> 0.0034349946 | K42: ='Muthoot Fincorp'!K17 -> 0.0038483119 | L42: ='Muthoot Fincorp'!L17 -> 0.0015384307 | M42: ='Muthoot Fincorp'!M17 -> 0.0047066805 | N42: ='Muthoot Fincorp'!N17 -> 0.0071999444 | O42: ='Muthoot MCred'!K17 -> -0.00069425104 | P42: ='Muthoot MCred'!L17 -> 0.002063071 | Q42: ='Muthoot MCred'!M17 -> 0.003652968 | R42: ='Muthoot MCred'!N17 -> 0.0020432804 | S42: ='Kosamattam Finance'!J17 -> 0.0014840465 | T42: ='Kosamattam Finance'!K17 -> 0.0062548866 | U42: ='Kosamattam Finance'!L17 -> 0.0019430681 | V42: ='Kosamattam Finance'!M17 -> 0.0010763297
B43: Return Indicators
B44: Pre Provisioning operating profit (PPOP)margin | C44: ='Manappuram Finance'!N19 -> 0.06220732 | D44: ='Manappuram Finance'!O19 -> 0.073606551 | E44: ='Manappuram Finance'!P19 -> 0.071559359 | F44: ='Manappuram Finance'!Q19 -> 0.047956048 | G44: ='Muthoot Finance'!P21 -> 0.06603051 | H44: ='Muthoot Finance'!Q21 -> 0.072376519 | I44: ='Muthoot Finance'!R21 -> 0.076537859 | J44: ='Muthoot Finance'!S21 -> 0.094005857 | K44: ='Muthoot Fincorp'!K20 -> 0.029719309 | L44: ='Muthoot Fincorp'!L20 -> 0.032200357 | M44: ='Muthoot Fincorp'!M20 -> 0.042273905 | N44: ='Muthoot Fincorp'!N20 -> 0.057134835 | O44: ='Muthoot MCred'!K19 -> 0.022570808 | P44: ='Muthoot MCred'!L19 -> 0.028627355 | Q44: ='Muthoot MCred'!M19 -> 0.030832255 | R44: ='Muthoot MCred'!N19 -> 0.040150968 | S44: ='Kosamattam Finance'!J19 -> 0.023992085 | T44: ='Kosamattam Finance'!K19 -> 0.032887109 | U44: ='Kosamattam Finance'!L19 -> 0.028521435 | V44: ='Kosamattam Finance'!M19 -> 0.028405423
B45: RoA | C45: ='Manappuram Finance'!N20 -> 0.044976229 | D45: ='Manappuram Finance'!O20 -> 0.052369822 | E45: ='Manappuram Finance'!P20 -> 0.048366314 | F45: ='Manappuram Finance'!Q20 -> 0.028401155 | G45: ='Muthoot Finance'!P22 -> 0.048521537 | H45: ='Muthoot Finance'!Q22 -> 0.051380351 | I45: ='Muthoot Finance'!R22 -> 0.050427338 | J45: ='Muthoot Finance'!S22 -> 0.067292177 | K45: ='Muthoot Fincorp'!K21 -> 0.019733195 | L45: ='Muthoot Fincorp'!L21 -> 0.022381236 | M45: ='Muthoot Fincorp'!M21 -> 0.026488506 | N45: ='Muthoot Fincorp'!N21 -> 0.038370651 | O45: ='Muthoot MCred'!K20 -> 0.018903052 | P45: ='Muthoot MCred'!L20 -> 0.019084903 | Q45: ='Muthoot MCred'!M20 -> 0.020267357 | R45: ='Muthoot MCred'!N20 -> 0.028426885 | S45: ='Kosamattam Finance'!J20 -> 0.019787287 | T45: ='Kosamattam Finance'!K20 -> 0.022557184 | U45: ='Kosamattam Finance'!L20 -> 0.019947507 | V45: ='Kosamattam Finance'!M20 -> 0.020497095
B46: RoE | C46: ='Manappuram Finance'!N21 -> 0.14965184 | D46: ='Manappuram Finance'!O21 -> 0.17245526 | E46: ='Manappuram Finance'!P21 -> 0.16262313 | F46: ='Manappuram Finance'!Q21 -> 0.11085266 | G46: ='Muthoot Finance'!P23 -> 0.17628143 | H46: ='Muthoot Finance'!Q23 -> 0.17874904 | I46: ='Muthoot Finance'!R23 -> 0.20405281 | J46: ='Muthoot Finance'!S23 -> 0.33332785 | K46: ='Muthoot Fincorp'!K22 -> 0.12524591 | L46: ='Muthoot Fincorp'!L22 -> 0.13735 | M46: ='Muthoot Fincorp'!M22 -> 0.17268239 | N46: ='Muthoot Fincorp'!N22 -> 0.28549047 | O46: ='Muthoot MCred'!K21 -> 0.11358806 | P46: ='Muthoot MCred'!L21 -> 0.11791383 | Q46: ='Muthoot MCred'!M21 -> 0.12550067 | R46: ='Muthoot MCred'!N21 -> 0.1809816 | S46: ='Kosamattam Finance'!J21 -> 0.12403101 | T46: ='Kosamattam Finance'!K21 -> 0.15220484 | U46: ='Kosamattam Finance'!L21 -> 0.13628213 | V46: ='Kosamattam Finance'!M21 -> 0.12965799
B47: Spread
B48: Yields (A) | C48: ='Manappuram Finance'!N23 -> 0.19609693 | D48: ='Manappuram Finance'!O23 -> 0.20874917 | E48: ='Manappuram Finance'!P23 -> 0.21263957 | F48: ='Manappuram Finance'!Q23 -> 0.16541738 | G48: ='Muthoot Finance'!P25 -> 0.16213338 | H48: ='Muthoot Finance'!Q25 -> 0.17047333 | I48: ='Muthoot Finance'!R25 -> 0.17562038 | J48: ='Muthoot Finance'!S25 -> 0.19781184 | K48: ='Muthoot Fincorp'!K24 -> 0.18934022 | L48: ='Muthoot Fincorp'!L24 -> 0.190509 | M48: ='Muthoot Fincorp'!M24 -> 0.20929887 | N48: ='Muthoot Fincorp'!N24 -> 0.21483077 | O48: ='Muthoot MCred'!K23 -> 0.18015815 | P48: ='Muthoot MCred'!L23 -> 0.18479222 | Q48: ='Muthoot MCred'!M23 -> 0.19412916 | R48: ='Muthoot MCred'!N23 -> 0.19429739 | S48: ='Kosamattam Finance'!J23 -> 0.1498887 | T48: ='Kosamattam Finance'!K23 -> 0.16999888 | U48: ='Kosamattam Finance'!L23 -> 0.16593802 | V48: ='Kosamattam Finance'!M23 -> 0.16037313
B49: Avg. Cost of Borrowing(B) | C49: ='Manappuram Finance'!N24 -> 0.080656757 | D49: ='Manappuram Finance'!O24 -> 0.08768774 | E49: ='Manappuram Finance'!P24 -> 0.093995516 | F49: ='Manappuram Finance'!Q24 -> 0.076052384 | G49: ='Muthoot Finance'!P26 -> 0.074320731 | H49: ='Muthoot Finance'!Q26 -> 0.085792767 | I49: ='Muthoot Finance'!R26 -> 0.086525844 | J49: ='Muthoot Finance'!S26 -> 0.087101282 | K49: ='Muthoot Fincorp'!K25 -> 0.088430967 | L49: ='Muthoot Fincorp'!L25 -> 0.093963497 | M49: ='Muthoot Fincorp'!M25 -> 0.099588814 | N49: ='Muthoot Fincorp'!N25 -> 0.088362317 | O49: ='Muthoot MCred'!K24 -> 0.096624742 | P49: ='Muthoot MCred'!L24 -> 0.10164997 | Q49: ='Muthoot MCred'!M24 -> 0.10337662 | R49: ='Muthoot MCred'!N24 -> 0.10211946 | S49: ='Kosamattam Finance'!J24 -> 0.094761171 | T49: ='Kosamattam Finance'!K24 -> 0.10125102 | U49: ='Kosamattam Finance'!L24 -> 0.10600414 | V49: ='Kosamattam Finance'!M24 -> 0.10484342
B50: Spread(A-B) | C50: ='Manappuram Finance'!N25 -> 0.11544017 | D50: ='Manappuram Finance'!O25 -> 0.12106143 | E50: ='Manappuram Finance'!P25 -> 0.11864405 | F50: ='Manappuram Finance'!Q25 -> 0.089364996 | G50: ='Muthoot Finance'!P27 -> 0.087812649 | H50: ='Muthoot Finance'!Q27 -> 0.084680567 | I50: ='Muthoot Finance'!R27 -> 0.08909454 | J50: ='Muthoot Finance'!S27 -> 0.11071055 | K50: ='Muthoot Fincorp'!K26 -> 0.10090925 | L50: ='Muthoot Fincorp'!L26 -> 0.096545505 | M50: ='Muthoot Fincorp'!M26 -> 0.10971006 | N50: ='Muthoot Fincorp'!N26 -> 0.12646846 | O50: ='Muthoot MCred'!K25 -> 0.083533403 | P50: ='Muthoot MCred'!L25 -> 0.083142249 | Q50: ='Muthoot MCred'!M25 -> 0.090752535 | R50: ='Muthoot MCred'!N25 -> 0.09217793 | S50: ='Kosamattam Finance'!J25 -> 0.055127525 | T50: ='Kosamattam Finance'!K25 -> 0.06874786 | U50: ='Kosamattam Finance'!L25 -> 0.059933875 | V50: ='Kosamattam Finance'!M25 -> 0.055529712

Sheet NBFC-LC
B1: Ambit Finvest | D1: Northern Arc Capital | F1: Aptus Finance | H1: Arka Fincap | J1: Profectus Capital | L1: Indostar Capital Finance | N1: Avendus Finance Pvt. | P1: Incred Financial | R1: Dhani Loans | T1: Capsave | V1: IFFCO Kisan | X1: Finova | Z1: Five star | AB1: Shriram City Union | AD1: Home Credit | AF1: Vivirti | AH1: Veritas | AJ1: Vistaar | AL1: Ugro Capital | AN1: Oxyzo | AP1: Tata Capital Financial | AR1: SBFC | AT1: Indiabulls Commercial Credit
A2: Particulars | B2: FY 21 | C2: FY 22 | D2: FY 21 | F2: FY 21 | G2: FY 22 | H2: FY 21 | I2: FY 22 | J2: FY 21 | K2: FY 22 | L2: FY 21 | M2: FY 22 | N2: FY 21 | O2: FY 22 | P2: FY 21 | Q2: FY 22 | R2: FY 21 | S2: FY 22 | T2: FY 21 | U2: FY 22 | V2: FY 21 | W2: FY 22 | X2: FY 21 | Y2: FY 22 | Z2: FY 21 | AA2: FY 22 | AB2: FY 21 | AC2: FY 22 | AD2: FY 21 | AE2: FY 22 | AF2: FY 21 | AG2: FY 22 | AH2: FY 21 | AI2: FY 22 | AJ2: FY 21 | AK2: FY 22 | AL2: FY 21 | AM2: FY 22 | AN2: FY 21 | AO2: FY 22 | AP2: FY 21 | AQ2: FY 22 | AR2: FY 21 | AT2: FY 21 | AU2: FY 22
B3: Aud | C3: Aud | D3: Aud | F3: Aud | G3: Aud | H3: Aud | I3: Aud | J3: Aud | K3: Aud | L3: Aud | M3: Aud | N3: Aud | O3: Aud | P3: Aud | Q3: Aud | R3: Aud | S3: Aud | T3: Aud | U3: Aud | V3: Aud | W3: Aud | X3: Aud | Y3: Aud | Z3: Aud | AA3: Aud | AB3: Aud | AC3: Aud | AD3: Aud | AE3: Aud | AF3: Aud | AG3: Aud | AH3: Aud | AI3: Aud | AJ3: Aud | AK3: Aud | AL3: Aud | AM3: Aud | AN3: Aud | AO3: Aud | AP3: Aud | AQ3: Aud | AR3: Aud | AT3: Aud | AU3: Aud
B4: Rs in Lakh | D4: Rs in Lakh | F4: Rs in Lakh | H4: Rs in Lakh | J4: Rs in Lakh | L4: Rs in Lakh | N4: Rs in Lakh | P4: Rs in Lakh | R4: Rs in Lakh | T4: Rs in Lakh | V4: Rs in Lakh | X4: Rs in Lakh | Z4: Rs in Lakh | AB4: Rs in Lakh | AD4: Rs in Lakh | AF4: Rs in Lakh | AH4: Rs in Lakh | AJ4: Rs in Lakh | AL4: Rs in Lakh | AN4: Rs in Lakh | AP4: Rs in Lakh | AR4: Rs in Lakh | AT4: Rs in Crore
A5: Revenue from operations | B5: 14312.84 | C5: 20302.22 | D5: 65128.56 | E5: 86711.4 | F5: 10996.64 | G5: 14129.6 | H5: 10188.51 | I5: 20172.74 | J5: 9886 | K5: 16147 | L5: 118780.16 | M5: 104218.4 | N5: 16646.3 | O5: 19919.37 | P5: 38537.82 | Q5: 48791.66 | R5: 101518.07 | S5: 81229.38 | T5: 12011 | U5: 16209 | V5: 8671.13 | W5: 12394.73 | X5: 12296.13 | Y5: 18329.07 | Z5: 104974.22 | AA5: 125406.36 | AB5: 573069.65 | AC5: 652675.6 | AD5: =232655.41+23129.49 -> 255784.9 | AE5: =155339.26+25609.26 -> 180948.52 | AF5: 21938.19 | AG5: 34487.19 | AH5: 36009.78 | AI5: 44208.42 | AJ5: 39069 | AK5: 43329 | AL5: 14981.07 | AM5: 30727.46 | AN5: =19757.17-4.2 -> 19752.97 | AO5: =31323.76-26.55 -> 31297.21 | AP5: 592205 | AQ5: 620622 | AR5: 50727.39 | AT5: 1619.41 | AU5: 1833.08
A6: Interest Income | B6: 13171.35 | C6: 16745.92 | D6: 46569.42 | E6: 75550.32 | F6: 10763.96 | G6: 13757.5 | H6: 6777.54 | I6: 18155.9 | J6: 8342 | K6: 13602 | L6: 108201.77 | M6: 93823.06 | N6: 15503.71 | O6: 18470.47 | P6: 35496.52 | Q6: 45746.66 | R6: 80080.85 | S6: 41386.63 | T6: 6262 | U6: 11595 | V6: 8402.54 | W6: 11870.77 | X6: 10752.21 | Y6: 16199.49 | Z6: 99550.11 | AA6: 117051.64 | AB6: 542044.23 | AC6: 599044.94 | AD6: 232665.41 | AE6: 155339.26 | AF6: 17192.4 | AG6: 28634.13 | AH6: 32771.41 | AI6: 40930.01 | AJ6: 34692 | AK6: 39044 | AL6: 13214 | AM6: 26137.36 | AN6: 18884.87 | AO6: 28663.85 | AP6: 522593 | AQ6: 557178 | AR6: 27756.75 | AT6: 1589.98 | AU6: 1577
A7: Other Operation Income | B7: =B5-B6 -> 1141.49 | C7: =C5-C6 -> 3556.3 | D7: =D5-D6 -> 18559.14 | E7: =E5-E6 -> 11161.08 | F7: =F5-F6 -> 232.68 | G7: =G5-G6 -> 372.1 | H7: =H5-H6 -> 3410.97 | I7: =I5-I6 -> 2016.84 | ... AR7: =AR5-AR6 -> 22970.64 | AT7: =AT5-AT6 -> 29.43 | AU7: =AU5-AU6 -> 256.08
A8: Interest expended | B8: 4015.55 | C8: 6626.25 | D8: 32296.76 | E8: 41026.93 | F8: 2957.42 | G8: 3505.66 | H8: 3768.91 | I8: 9173.74 | J8: 1948 | K8: 5686 | L8: 69224.61 | M8: 51430.77 | N8: 194.6 | O8: 363.35 | P8: 15271.4 | Q8: 21951.92 | R8: 43590.94 | S8: 22606.32 | T8: 2115 | U8: 4275 | V8: 2668.22 | W8: 4139.49 | X8: 4756.58 | Y8: 5883.18 | Z8: 32519.12 | AA8: 30060 | AB8: 213388.43 | AC8: 253252.52 | AD8: 64077.81 | AE8: 45128.04 | AF8: 9435.22 | AG8: 19905.55 | AH8: 12164.59 | AI8: 12893.81 | AJ8: 14237 | AK8: 15650 | AL8: 4456.24 | AM8: 13738.92 | AN8: 9021.93 | AO8: 14296.86 | AP8: 289885 | AQ8: 283300 | AR8: 23845.54 | AT8: 997.29 | AU8: 941.48
A9: Net Interest Income | B9: =B6-B8 -> 9155.8 | C9: =C6-C8 -> 10119.67 | D9: =D6-D8 -> 14272.66 | E9: =E6-E8 -> 34523.39 | F9: =F6-F8 -> 7806.54 | G9: =G6-G8 -> 10251.84 | H9: =H6-H8 -> 3008.63 | I9: =I6-I8 -> 8982.16 | ... AR9: =AR6-AR8 -> 3911.21 | AT9: =AT6-AT8 -> 592.69 | AU9: =AU6-AU8 -> 635.52
A10: Total Operating Income | B10: =SUM(B6:B7) -> 14312.84 | C10: =SUM(C6:C7) -> 20302.22 | D10: =SUM(D6:D7) -> 65128.56 | E10: =SUM(E6:E7) -> 86711.4 | F10: =SUM(F6:F7) -> 10996.64 | G10: =SUM(G6:G7) -> 14129.6 | H10: =SUM(H6:H7) -> 10188.51 | I10: =SUM(I6:I7) -> 20172.74 | ... AR10: =SUM(AR6:AR7) -> 50727.39 | AT10: =SUM(AT6:AT7) -> 1619.41 | AU10: =SUM(AU6:AU7) -> 1833.08
A11: Other income | B11: 199.06 | C11: 136.88 | D11: 291.63 | E11: 700.53 | F11: 220.55 | G11: 224.13 | H11: 104.03 | I11: 136.66 | J11: 7 | K11: 20 | L11: 546.56 | M11: 1135.87 | N11: 194.6 | O11: 363.35 | P11: 647.09 | Q11: 3330.04 | R11: 4768.69 | S11: 3181.5 | T11: 69 | U11: 238 | V11: 1.57 | W11: 562.05 | X11: 5.44 | Y11: 1.45 | Z11: 151.25 | AA11: 210.56 | AB11: 773.82 | AC11: 363.63 | AD11: 426.73 | AE11: 699.58 | AF11: 574.05 | AG11: 679.72 | AH11: 157.51 | AI11: 156.14 | AJ11: 7 | AK11: 30 | AL11: 352.77 | AM11: 614.13 | AN11: 4.2 | AO11: 26.55 | AP11: 7252 | AQ11: 8098 | AR11: 390.73 | AT11: 13.53 | AU11: 8.8
A12: Total Income | B12: =B10+B11 -> 14511.9 | C12: =C10+C11 -> 20439.1 | D12: =D10+D11 -> 65420.19 | E12: =E10+E11 -> 87411.93 | F12: =F10+F11 -> 11217.19 | G12: =G10+G11 -> 14353.73 | H12: =H10+H11 -> 10292.54 | I12: =I10+I11 -> 20309.4 | ... AR12: =AR10+AR11 -> 51118.12 | AT12: =AT10+AT11 -> 1632.94 | AU12: =AU10+AU11 -> 1841.88
A13: Operating expenses | B13: =3758.43+476.36+1484.47 -> 5719.26 | C13: =6558.85+726.06+2337.84 -> 9622.75 | D13: =2852.19+5679.95+673.83+2681.56 -> 11887.53 | E13: =5273.22+8771.65+911.82+5034.73 -> 19991.42 | F13: =1.3+41.61+1465.69 -> 1508.6 | G13: =69.21+513.67+1848.52 -> 2431.4 | H13: =3050.32+315.27+609.23 -> 3974.82 | I13: =4676.27+365.34+1127.82 -> 6169.43 | J13: =4355+348+1968 -> 6671 | K13: 8718 | L13: =15563.01+3149.38+11859.72 -> 30572.11 | M13: =17627.03+3381.93+11923.3 -> 32932.26 | N13: =1714.43+15.57+1420.08 -> 3150.08 | O13: =2699.11+13.98+1547.89 -> 4260.98 | P13: =9159.37+841.79+3805.92 -> 13807.08 | Q13: =13687.26+1070.98+5196.83 -> 19955.07 | R13: =30348.36+5707.22+18226.83 -> 54282.41 | S13: =486.01+28082.14+6004.97+25576.61 -> 60149.73 | T13: =948+781+2028+931 -> 4688 | U13: =1447+1784+996 -> 4227 | V13: =1708.48+89.08+1390.76 -> 3188.32 | W13: =2572.65+91.68+2462.31 -> 5126.64 | X13: =3803.52+172.94+578.9 -> 4555.36 | Y13: =5824.99+222.86+969.85 -> 7017.7 | Z13: =266.83+16371.78+1138.39+3667.7 -> 21444.7 | AA13: =23611.52+1224.47+5748.21 -> 30584.2 | AB13: =10384.64+84799.87+76366.07+7984.14+6254.89+13010.25+22263.67 -> 221063.53 | AC13: =10373.41+85253.45+97236.64+7835.49+7076.06+12664.85+29710.31 -> 250150.21 | AD13: =56166.72+12150.26+34229.95 -> 102546.93 | AE13: =37076.68+13603.76+38958.84 -> 89639.28 | AF13: =3668.93+680.38+1671.45 -> 6020.76 | AG13: =2309.07+487.07+1938.79 -> 4734.93 | AH13: =8421.28+1332.59+2000.1 -> 11753.97 | AI13: =10984.31+1425.4+2989.14 -> 15398.85 | AJ13: =297+8813+637+1464 -> 11211 | AK13: =507+10848+566+2143 -> 14064 | AL13: =4532.67+1173.91+1996.4 -> 7702.98 | AM13: =7289.06+1233.26+4121.03 -> 12643.35 | AN13: =2995.48+26.44+755.17 -> 3777.09 | AO13: =4577.66+31+1539.8 -> 6148.46 | AP13: =43811+31974+49989 -> 125774 | AQ13: =55064+25982+67403 -> 148449 | AR13: =8418.27+930.06+3693.23 -> 13041.56 | AT13: =20.6+4.54+15.72 -> 40.86 | AU13: =24.15+1.64+13.15 -> 38.94
A14: Operating profit | B14: =B10-B13 -> 8593.58 | C14: =C10-C13 -> 10679.47 | D14: =D10-D13 -> 53241.03 | E14: =E10-E13 -> 66719.98 | F14: =F10-F13 -> 9488.04 | G14: =G10-G13 -> 11698.2 | H14: =H10-H13 -> 6213.69 | I14: =I10-I13 -> 14003.31 | ... AR14: =AR10-AR13 -> 37685.83 | AT14: =AT10-AT13 -> 1578.55 | AU14: =AU10-AU13 -> 1794.14
A15: Pre-provisioning operating profit | B15: =B12-B13-B8 -> 4777.09 | C15: =C12-C13-C8 -> 4190.1 | D15: =D12-D13-D8 -> 21235.9 | E15: =E12-E13-E8 -> 26393.58 | F15: =F12-F13-F8 -> 6751.17 | G15: =G12-G13-G8 -> 8416.67 | H15: =H12-H13-H8 -> 2548.81 | I15: =I12-I13-I8 -> 4966.23 | ... AR15: =AR12-AR13-AR8 -> 14231.02 | AT15: =AT12-AT13-AT8 -> 594.79 | AU15: =AU12-AU13-AU8 -> 861.46
A16: Provisions | B16: 2294.44 | C16: 750.99 | D16: 13602.68 | E16: 3684.74 | F16: 88.18 | G16: 513.67 | H16: 3050.32 | I16: 4676.27 | J16: 415 | K16: 614 | L16: 45240.8 | M16: 115076.93 | N16: 4482.21 | O16: 4338.35 | P16: 8865.37 | Q16: 4351.64 | R16: 15393.44 | S16: 26512.62 | T16: 175 | U16: 659 | V16: 1518.48 | W16: 977.38 | X16: 782.37 | Y16: 1567.18 | Z16: 3517.57 | AA16: 4551.81 | AB16: 285.73 | AC16: 3512.13 | AD16: 252335.27 | AE16: 53964.47 | AF16: 2989.74 | AG16: 1462.38 | AH16: 4044.59 | AI16: 5935.56 | AJ16: 5027 | AK16: 3603 | AL16: 1961.71 | AM16: 2941.54 | AN16: 1576.47 | AO16: 1367.45 | AP16: 101294 | AQ16: 88950 | AR16: 2817.91 | AT16: 426.88 | AU16: 248.92
A17: PAT | B17: 2123.57 | C17: 2578.22 | D17: 5604.99 | E17: 16372.93 | F17: 4947.26 | G17: 6244.67 | H17: 1688.34 | I17: 3251.67 | J17: 680 | K17: 783 | L17: -24146.8 | M17: -76919.79 | N17: 2015.91 | O17: 2505.17 | P17: 1023.44 | Q17: 3611.77 | R17: -5409.77 | S17: -18427.65 | T17: 3660 | U17: 5414 | V17: 942.72 | W17: 2007.03 | X17: 1650.15 | Y17: 2900.59 | Z17: 35899.44 | AA17: 45354.45 | AB17: 101094.42 | AC17: 108619.5 | AD17: -122130.81 | AE17: -5535.28 | AF17: 3000.51 | AG17: 6736.98 | AH17: 6202.02 | AI17: 7540.39 | AJ17: 6476 | AK17: 7419 | AL17: 2872.75 | AM17: 1455.06 | AN17: 3993.69 | AO17: 6933.7 | AP17: 67699 | AQ17: 81719 | AR17: 8514.88 | AT17: 139.04 | AU17: 508.22
A18: TNW | B18: 64132.3 | C18: 66802 | D18: 155886.02 | E18: 170991.44 | F18: 23948.68 | G18: 30193.35 | H18: 67335.16 | I18: 83682.5 | J18: 65812 | K18: 76691 | L18: 367896.44 | M18: 287801.66 | N18: 69511.55 | O18: 72013.59 | P18: =38624.42+65950.36 -> 104574.78 | Q18: 111231.44 | R18: 417567.87 | S18: 401265.95 | T18: 26192 | U18: 36564 | V18: 25016.41 | W18: 27132.99 | X18: 44190.01 | Y18: 91846.54 | Z18: 231817.22 | AA18: 371035.1 | AB18: 811852.59 | AC18: 897247.64 | AD18: 189671.39 | AE18: 184216.46 | AF18: 79714.17 | AG18: 119614.66 | AH18: 88801.8 | AI18: 140804.82 | AJ18: 70346 | AK18: 78488 | AL18: 95243.82 | AM18: 96656.32 | AN18: 44961.65 | AO18: 139228.74 | AP18: 673534 | AQ18: 776274 | AR18: 120540.64 | AT18: =4305.4+247.8 -> 4553.2 | AU18: =4817.04+247.8 -> 5064.84
A19: Total Debt | B19: =12587.98+38022.4+1231.24 -> 51841.62 | C19: =17024.54+89100.8+1704.43 -> 107829.77 | D19: =163956.78+229247.09 -> 393203.87 | E19: =134359.68+459942.62+3993.47 -> 598295.77 | F19: =4874.26+30985.29 -> 35859.55 | G19: =2813.37+35857.33 -> 38670.7 | H19: =22203.94+44364.85 -> 66568.79 | I19: =56577.25+116773.31 -> 173350.56 | J19: 44316 | K19: 84889 | L19: =201276.18+374790.64 -> 576066.82 | M19: =197793.62+350504.82 -> 548298.44 | N19: =52391.41+23060.15 -> 75451.56 | O19: =68932.27+28566.37 -> 97498.64 | P19: =73827.02+93422.08 -> 167249.1 | Q19: =106523.77+175065.49 -> 281589.26 | R19: =77060.33+238793.37 -> 315853.7 | S19: =54506.33+111746.19 -> 166252.52 | T19: =8504+8378+12310 -> 29192 | U19: =12965+45091+11399 -> 69455 | V19: 35321.7 | W19: 59078.91 | X19: =8451.29+43908.02+305.39 -> 52664.7 | Y19: =6465.33+57962.43+285.2 -> 64712.96 | Z19: =130378.55+212141.12 -> 342519.67 | AA19: =100853.38+155029.75 -> 255883.13 | AB19: =426363+1577279.14+552888.78 -> 2556530.9 | AC19: =651514.1+1728828.82+682838.64 -> 3063181.6 | AD19: =5000+378891.34 -> 383891.34 | AE19: =6000+271025.49 -> 277025.49 | AF19: =39953.41+96864.64 -> 136818.05 | AG19: =107051.35+247962.03 -> 355013.38 | AH19: =53074.52+72340.01 -> 125414.53 | AI19: =95357.96+24207.26 -> 119565.22 | AJ19: =17733+129709 -> 147442 | AK19: =17150+174197 -> 191347 | AL19: =31557.55+45011.94 -> 76569.49 | AM19: =70376.77+109807.09 -> 180183.86 | AN19: =32468.1+84369.47 -> 116837.57 | AO19: =39131.54+162347.19 -> 201478.73 | AP19: =2005053+1463342+355532 -> 3823927 | AQ19: =2290671+2185506+432060 -> 4908237 | AR19: =15000+262775.8 -> 277775.8 | AT19: =2192.77+5280.88+349.4 -> 7823.05 | AU19: =2159.42+5053.79+350 -> 7563.21
A20: Total Assets | B20: 119424.43 | C20: 181353.2 | D20: 557419.24 | E20: 783520.78 | F20: 60082.89 | G20: 69170.88 | H20: 136614.38 | I20: 262699.72 | J20: 114818 | K20: 170220 | L20: 978730.05 | M20: 882426.89 | N20: 146336.29 | O20: 171444.38 | P20: 279140.5 | Q20: 402389.25 | R20: 795604.64 | S20: 619053.86 | T20: 70511 | U20: 130808 | V20: 61571.33 | W20: 88055.24 | X20: 98432.1 | Y20: 159194.56 | Z20: 579361.14 | AA20: 634306.56 | AB20: 3421003.5 | AC20: 4006764.4 | AD20: 615802.01 | AE20: 492519.63 | AF20: 219515.59 | AG20: 478284.35 | AH20: 217486.17 | AI20: 264247.23 | AJ20: 228189 | AK20: 278789 | AL20: 175478.58 | AM20: 285422.56 | AN20: 164512.93 | AO20: 343919.74 | AP20: 4741557 | AQ20: 5946384 | AR20: 426588.07 | AT20: 15873.26 | AU20: 13143.65
A21: Loans & Advances (Gross) | B21: 99375.04 | C21: 133266.39 | D21: 383639.88 | E21: 522265.41 | F21: 57768.29 | G21: 67917.46 | H21: 90939.79 | I21: 230606.09 | J21: 88819 | K21: 152155 | L21: 737756.39 | M21: 760755.41 | N21: 123885.95 | O21: 133856.77 | P21: 264464.73 | Q21: 382323.85 | R21: 372117.35 | S21: 334454.23 | T21: 51576 | U21: 105750 | V21: 62090.01 | W21: 88445.68 | X21: 58592.07 | Y21: 94829.41 | Z21: 444538.09 | AA21: 520529.65 | AB21: 2946518.9 | AC21: 3310360.7 | AD21: 440258.62 | AE21: 361388.53 | AF21: 163692.1 | AG21: 298931.64 | AH21: 156275 | AI21: 218735.37 | AJ21: 199470 | AK21: 232081 | AL21: 130831.61 | AM21: 249112.74 | AN21: 138408.49 | AO21: 257853 | AP21: 4472364 | AQ21: 5604150 | AR21: 217232.83 | AT21: 12640.72 | AU21: 10950.3
A22: Gross NPAs | B22: 2650.9 | C22: 3784.71 | D22: 11727.78 | F22: 293.9 | G22: 1118.13 | J22: 193 | K22: 1182 | L22: 32486.91 | M22: 118091.93 | O22: 5505.26 | P22: 9036.67 | Q22: 10811.36 | U22: 138.47 | V22: 2315.99 | W22: 3188.43 | X22: 396.75 | Y22: 1716.86 | Z22: 4519.37 | AA22: 5304.99 | AB22: 187598.74 | AC22: 208869.2 | AF22: 592.52 | AG22: 1091.69 | AH22: 4216.93 | AI22: 8614.19 | AJ22: 6324 | AK22: 6085 | AL22: 3647.41 | AM22: 5641.15 | AN22: 1672.3 | AO22: 2609.84 | AP22: 132917 | AQ22: 124904 | AR22: 6665.46 | AT22: 620.2 | AU22: 260.73
A23: Net NPAs | B23: 1666.23 | C23: 2331.96 | D23: 4482.58 | F23: 227.99 | G23: 837.1 | J23: 170 | K23: 978 | L23: 14211.9 | M23: 50534.98 | O23: 304.91 | P23: 4424.54 | Q23: 5404.46 | U23: 124.62 | V23: 802.96 | W23: 1459.53 | X23: 236.74 | Y23: 1009.72 | Z23: 3707.53 | AA23: 3454.04 | AB23: 87728.16 | AC23: 105934.01 | AG23: 249.59 | AH23: 2107.36 | AI23: 5041.99 | AJ23: 4241 | AK23: 4284 | AL23: 2297.45 | AM23: 4152.32 | AN23: 684.27 | AO23: 1100.96 | AP23: 38840 | AQ23: 26511 | AR23: 4115.87 | AT23: 404.8 | AU23: 195.54
A25: Profitability | B25: FY21 (A) | C25: FY22 (A) | D25: FY21 (A) | E25: FY22 (A) | F25: FY21 (A) | G25: FY22 (A) | H25: FY21 (A) | I25: FY22 (A) | J25: FY21 (A) | K25: FY22 (A) | L25: FY21 (A) | M25: FY22 (A) | N25: FY21 (A) | O25: FY22 (A) | P25: FY21 (A) | Q25: FY22 (A) | R25: FY21 (A) | S25: FY22 (A) | T25: FY21 (A) | U25: FY22 (A) | V25: FY21 (A) | W25: FY22 (A) | X25: FY21 (A) | Y25: FY22 (A) | Z25: FY21 (A) | AA25: FY22 (A) | AB25: FY21 (A) | AC25: FY22 (A) | AD25: FY21 (A) | AE25: FY22 (A) | AF25: FY21 (A) | AG25: FY22 (A) | AH25: FY21 (A) | AI25: FY22 (A) | AJ25: FY21 (A) | AK25: FY22 (A) | AL25: FY21 (A) | AM25: FY22 (A) | AN25: FY21 (A) | AO25: FY22 (A) | AP25: FY21 (A) | AQ25: FY22 (A) | AR25: FY21 (A) | AT25: FY21 (A) | AU25: FY22 (A)
A26: Net Interest Margin | B26: 0.10126173 | C26: 0.086998004 | D26: 0.041787438 | E26: 0.076218542 | F26: 0.15528462 | G26: 0.16313448 | H26: 0.055206069 | I26: 0.055868606 | J26: 0.071989101 | K26: 0.065700034 | L26: 0.050179204 | M26: 0.056579187 | N26: 0.12357422 | O26: 0.14050538 | P26: 0.085220658 | Q26: 0.073578108 | R26: 0.098060222 | S26: 0.053158974 | T26: 0.12012318 | U26: 0.093055185 | V26: 0.12397648 | W26: 0.1027169 | X26: 0.10232835 | Y26: 0.13448325 | Z26: 0.16079187 | AA26: 0.1802809 | AB26: 0.11309226 | AC26: 0.11053191 | AD26: 0.38292856 | AE26: 0.27496192 | AF26: 0.062841687 | AG26: 0.037735115 | AH26: 0.14393132 | AI26: 0.14952227 | AJ26: 0.10673018 | AK26: 0.10841824 | AL26: 0.081422998 | AM26: 0.065264505 | AN26: 0.085910628 | AO26: 0.072512673 | AP26: 0.052285567 | AQ26: 0.054359672 | AR26: 0.020813568 | AT26: 0.048156854 | AU26: 0.053878128
A27: Capitalization
A28: Leverage (Debt/TNW) | B28: 0.80835429 | C28: 1.6141698 | D28: 2.5223806 | E28: 3.4989808 | F28: 1.4973497 | G28: 1.2807688 | H28: 0.98861858 | I28: 2.071527 | J28: 0.67337264 | K28: 1.1068965 | L28: 1.5658396 | M28: 1.9051261 | N28: 1.0854536 | O28: 1.3538922 | P28: 1.5993254 | Q28: 2.5315618 | R28: 0.75641284 | S28: 0.41432003 | T28: 1.1145388 | U28: 1.899546 | V28: 1.4119412 | W28: 2.177383 | X28: 1.1917784 | Y28: 0.704577 | Z28: 1.477542 | AA28: 0.68964669 | AB28: 3.1490088 | AC28: 3.4139756 | AD28: 2.0239813 | AE28: 1.5038042 | AF28: 1.716358 | AG28: 2.9679755 | AH28: 1.4122972 | AI28: 0.84915573 | AJ28: 2.0959543 | AK28: 2.4379141 | AL28: 0.80393132 | AM28: 1.8641705 | AN28: 2.598605 | AO28: 1.4471059 | AP28: 5.6774075 | AQ28: 6.3228151 | AR28: 2.3044162 | AT28: 1.7181433 | AU28: 1.4932772
A29: CAR | B29: 0.5692 | C29: 0.3845 | D29: 0.287 | E29: 0.2279 | F29: 0.4444 | G29: 0.4792 | I29: 0.5785 | J29: 0.6317 | K29: 0.4823 | L29: 0.346 | M29: 0.258 | N29: 0.5162 | O29: 0.4189 | P29: 0.372 | Q29: 0.2805 | S29: 0.6391 | T29: 0.3764 | U29: 0.2842 | V29: 0.4037 | W29: 0.3089 | Y29: 0.7845 | Z29: 0.5886 | AA29: 0.752 | AB29: 0.2864 | AC29: 0.2678 | AD29: 0.211 | AE29: 0.2239 | AF29: 0.4031 | AG29: 0.2957 | AH29: 0.5065 | AI29: 0.6443 | AJ29: 0.365 | AK29: 0.3 | AL29: 0.6555 | AM29: 0.3437 | AN29: 0.3232 | AO29: 0.4838 | AP29: 0.2029 | AQ29: 0.1725 | AR29: 0.2625 | AT29: 0.3448 | AU29: 0.4773
A30: TNW/Loan Book | B30: 0.64535622 | C30: 0.50126667 | D30: 0.40633424 | E30: 0.32740334 | F30: 0.41456446 | G30: 0.44455947 | H30: 0.74043672 | I30: 0.3628807 | J30: 0.74096759 | K30: 0.50403207 | L30: 0.49866927 | M30: 0.37831037 | N30: 0.56109309 | O30: 0.5379899 | P30: 0.39542052 | Q30: 0.29093513 | R30: 1.1221403 | S30: 1.1997634 | T30: 0.5078331 | U30: 0.34575887 | V30: 0.40290556 | W30: 0.30677575 | X30: 0.7541978 | Y30: 0.96854488 | Z30: 0.52147887 | AA30: 0.71280301 | AB30: 0.2755294 | AC30: 0.27104226 | AD30: 0.43081812 | AE30: 0.50974628 | AF30: 0.48697628 | AG30: 0.40014051 | AH30: 0.5682406 | AI30: 0.64372223 | AJ30: 0.35266456 | AK30: 0.33819227 | AL30: 0.72798783 | AM30: 0.38800232 | AN30: 0.32484749 | AO30: 0.53995393 | AP30: 0.1505991 | AQ30: 0.13851771 | AR30: 0.55489145 | AT30: 0.360201 | AU30: 0.46252979
A31: Operational Efficiency
A32: Cost to Income (on total operating income net-off interest expenses) | B32: 0.55541409 | C32: 0.70362468 | D32: 0.36207366 | E32: 0.43759772 | F32: 0.18765502 | G32: 0.22886048 | H32: 0.61916942 | I32: 0.56090826 | J32: 0.84038801 | K32: 0.83338113 | L32: 0.61692606 | M32: 0.6238632 | N32: 0.19147444 | O32: 0.21788585 | P32: 0.5934338 | Q32: 0.74348969 | R32: 0.93708095 | S32: 1.0260421 | T32: 0.47372676 | U32: 0.35419809 | V32: 0.53112907 | W32: 0.62101647 | X32: 0.60419521 | Y32: 0.56385682 | Z32: 0.29597226 | AA32: 0.32076946 | AB32: 0.6146096 | AC32: 0.62627881 | AD32: 0.53491465 | AE32: 0.65998353 | AF32: 0.48154638 | AG32: 0.32471862 | AH32: 0.49292834 | AI32: 0.4917465 | AJ32: 0.4514739 | AK32: 0.50811084 | AL32: 0.73188641 | AM32: 0.74422817 | AN32: 0.351978 | AO32: 0.36166667 | AP32: 0.41602937 | AQ32: 0.44008099 | AR32: 0.48514369 | AT32: 0.065678647 | AU32: 0.043674293
A33: Cost to Income (on total operating income) | B33: 0.39958946 | C33: 0.47397526 | D33: 0.18252407 | E33: 0.23055123 | F33: 0.13718736 | G33: 0.17207847 | H33: 0.3901277 | I33: 0.30583005 | J33: 0.67479264 | K33: 0.53991454 | L33: 0.25738398 | M33: 0.31599276 | N33: 0.18923605 | O33: 0.21391138 | P33: 0.35827351 | Q33: 0.40898527 | R33: 0.53470688 | S33: 0.74049229 | T33: 0.39030888 | U33: 0.26078105 | V33: 0.36769371 | W33: 0.4136145 | X33: 0.37047103 | Y33: 0.38287267 | Z33: 0.2042854 | AA33: 0.24388077 | AB33: 0.38575334 | AC33: 0.38326882 | AD33: 0.4009108 | AE33: 0.49538554 | AF33: 0.27444197 | AG33: 0.13729533 | AH33: 0.32641049 | AI33: 0.34832392 | AJ33: 0.28695385 | AK33: 0.3245863 | AL33: 0.5141809 | AM33: 0.41146746 | AN33: 0.19121631 | AO33: 0.19645393 | AP33: 0.21238254 | AQ33: 0.23919391 | AR33: 0.25709109 | AT33: 0.025231411 | AU33: 0.021242935
A34: Operating Expenses: Avg. Assets | B34: 0.05042252 | C34: 0.063985809 | D34: 0.023639365 | E34: 0.029817023 | F34: 0.029163632 | G34: 0.037622113 | H34: 0.04013006 | I34: 0.030900136 | J34: 0.058100646 | K34: 0.061170791 | L34: 0.031583707 | M34: 0.03538902 | N34: 0.021526308 | O34: 0.026817113 | P34: 0.055275396 | Q34: 0.058559645 | R34: 0.06822787 | S34: 0.085037809 | T34: 0.08449154 | U34: 0.041993056 | V34: 0.057312085 | W34: 0.068525797 | X34: 0.046279212 | Y34: 0.05447961 | Z34: 0.042269037 | AA34: 0.050399628 | AB34: 0.067827247 | AC34: 0.067355419 | AD34: 0.16652581 | AE34: 0.1617568 | AF34: 0.032866292 | AG34: 0.013571024 | AH34: 0.05828262 | AI34: 0.063931004 | AJ34: 0.052442989 | AK34: 0.055481697 | AL34: 0.051920023 | AM34: 0.054863609 | AN34: 0.029002544 | AO34: 0.024185936 | AP34: 0.026697204 | AQ34: 0.027778784 | AR34: 0.030780486 | AT34: 0.002533124 | AU34: 0.0026839522
A35: Loan Book Performance
A36: Gross NPA % | B36: 0.026675713 | C36: 0.028399584 | D36: 0.030569762 | E36: 0 | F36: 0.0050875662 | G36: 0.016463071 | H36: 0 | I36: 0 | J36: 0.0021729585 | K36: 0.0077683941 | L36: 0.044034739 | M36: 0.15522983 | N36: 0 | O36: 0.041127991 | P36: 0.03416966 | Q36: 0.028278016 | R36: 0 | S36: 0 | T36: 0 | U36: 0 | V36: 0.037300525 | W36: 0.036049584 | X36: 0.0067713941 | Y36: 0.018104721 | Z36: 0.01016644 | AA36: 0.010191523 | AB36: 0.063667923 | AC36: 0.063095602 | AD36: 0 | AE36: 0 | AF36: 0.0036197226 | AG36: 0.0036519721 | AH36: 0.026984035 | AI36: 0.039381788 | AJ36: 0.031704016 | AK36: 0.026219294 | AL36: 0.02787866 | AM36: 0.022644968 | AN36: 0.012082351 | AO36: 0.010121426 | AP36: 0.029719629 | AQ36: 0.022287769 | AR36: 0.030683484 | AT36: 0.049063661 | AU36: 0.023810307
A37: Net NPA% | B37: 0.016767088 | C37: 0.017498486 | D37: 0.011684343 | E37: 0 | F37: 0.0039466289 | G37: 0.012325255 | H37: 0 | I37: 0 | J37: 0.0019140049 | K37: 0.006427656 | L37: 0.019263676 | M37: 0.066427369 | N37: 0 | O37: 0.0022778825 | P37: 0.01673017 | Q37: 0.014135817 | R37: 0 | S37: 0 | T37: 0 | U37: 0 | V37: 0.012932193 | W37: 0.016501993 | X37: 0.0040404785 | Y37: 0.010647752 | Z37: 0.0083401852 | AA37: 0.0066356258 | AB37: 0.029773493 | AC37: 0.032000746 | AD37: 0 | AE37: 0 | AF37: 0 | AG37: 0.00083494006 | AH37: 0.013484946 | AI37: 0.023050639 | AJ37: 0.021261343 | AK37: 0.018459072 | AL37: 0.017560359 | AM37: 0.016668437 | AN37: 0.0049438441 | AO37: 0.0042697196 | AP37: 0.0086844452 | AQ37: 0.0047306014 | AR37: 0.018946814 | AT37: 0.032023492 | AU37: 0.017857045
A38: Provision coverage Ratio | B38: 0.37144743 | C38: 0.38384711 | D38: 0.61778103 | E38: #DIV/0! | F38: 0.22425995 | G38: 0.25133929 | H38: #DIV/0! | I38: #DIV/0! | J38: 0.11917098 | K38: 0.17258883 | L38: 0.56253457 | M38: 0.57207084 | N38: #DIV/0! | O38: 0.94461479 | P38: 0.51037938 | Q38: 0.50011284 | R38: #DIV/0! | S38: #DIV/0! | T38: #DIV/0! | U38: #DIV/0! | V38: 0.65329729 | W38: 0.54224179 | X38: 0.40330183 | Y38: 0.41187983 | Z38: 0.17963566 | AA38: 0.34890735 | AB38: 0.53236274 | AC38: 0.4928213 | AD38: #DIV/0! | AE38: #DIV/0! | AF38: 1 | AG38: 0.77137283 | AH38: 0.50026204 | AI38: 0.41468786 | AJ38: 0.32938014 | AK38: 0.29597371 | AL38: 0.37011468 | AM38: 0.26392314 | AN38: 0.59082102 | AO38: 0.57815038 | AP38: 0.70778757 | AQ38: 0.78774899 | AR38: 0.38250773 | AT38: 0.34730732 | AU38: 0.25002877
A39: Credit Cost | B39: 0.025376152 | C39: 0.0064562017 | D39: 0.039825873 | E39: 0.0081349343 | F39: 0.0017540419 | G39: 0.0081738781 | H39: 0.055971049 | I39: 0.029086176 | J39: 0.0046724237 | K39: 0.0050959855 | L39: 0.058243015 | M39: 0.15358829 | N39: 0.036180132 | O39: 0.03366419 | P39: 0.037355163 | Q39: 0.013456144 | R39: 0.041367165 | S39: 0.075045815 | T39: 0.0050690998 | U39: 0.0083775091 | V39: 0.032829665 | W39: 0.012985359 | X39: 0.013352831 | Y39: 0.020429734 | Z39: 0.0084378383 | AA39: 0.0094331409 | AB39: 9.8321256e-05 | AC39: 0.0011226459 | AD39: 0.57315237 | AE39: 0.13463397 | AF39: 0.024220181 | AG39: 0.0063221139 | AH39: 0.028250025 | AI39: 0.031655445 | AJ39: 0.026229902 | AK39: 0.016697911 | AL39: 0.018238489 | AM39: 0.015484057 | AN39: 0.01373176 | AO39: 0.0069017557 | AP39: 0.022759055 | AQ39: 0.017654915 | AR39: 0.014995554 | AT39: 0.03468457 | AU39: 0.021102945
A41: Return Indicators
A42: Pre Provisioning operating profit (PPOP)margin | B42: 0.042116098 | C42: 0.027861779 | D42: 0.042229395 | E42: 0.039365788 | F42: 0.13051083 | G42: 0.13023481 | H42: 0.025732963 | I42: 0.024873802 | J42: 0.011095821 | K42: 0.01237028 | L42: 0.020176226 | M42: 0.022557195 | N42: 0.09222743 | O42: 0.098548411 | P42: 0.040460178 | Q42: 0.02997583 | R42: 0.010574863 | S42: 0.002339547 | T42: 0.095107051 | U42: 0.07892946 | V42: 0.050622272 | W42: 0.049331479 | X42: 0.030372511 | Y42: 0.042151228 | Z42: 0.10084327 | AA42: 0.10706838 | AB42: 0.04276844 | AC42: 0.040291108 | AD42: 0.14548002 | AE42: 0.084597789 | AF42: 0.038518909 | AG42: 0.030170338 | AH42: 0.060735911 | AI42: 0.066725288 | AJ42: 0.063749269 | AK42: 0.053828766 | AL42: 0.021397737 | AM42: 0.021520103 | AN42: 0.053428446 | AO42: 0.042792057 | AP42: 0.03901357 | AQ42: 0.036858549 | AR42: 0.033587831 | AT42: 0.036874127 | AU42: 0.059376412
A43: RoA | B43: 0.018721959 | C43: 0.017143695 | D43: 0.011146 | E43: 0.024420078 | F43: 0.095638388 | G43: 0.096626505 | H43: 0.017045598 | I43: 0.016286277 | J43: 0.0059224163 | K43: 0.0054940043 | L43: -0.02494579 | M43: -0.082658037 | N43: 0.013775872 | O43: 0.015766661 | P43: 0.0040972495 | Q43: 0.010599009 | R43: -0.0067995707 | S43: -0.026052436 | T43: 0.065963958 | U43: 0.053785286 | V43: 0.016945993 | W43: 0.026827187 | X43: 0.016764348 | Y43: 0.022517778 | Z43: 0.070760363 | AA43: 0.074739486 | AB43: 0.031018034 | AC43: 0.029246875 | AD43: -0.19832805 | AE43: -0.0099885806 | AF43: 0.016379268 | AG43: 0.019309202 | AH43: 0.030753012 | AI43: 0.031305241 | AJ43: 0.030293533 | AK43: 0.029267542 | AL43: 0.019363058 | AM43: 0.0063139787 | AN43: 0.030665716 | AO43: 0.027274801 | AP43: 0.014370013 | AQ43: 0.015291813 | AR43: 0.020096687 | AT43: 0.0086198132 | AU43: 0.03502923
A44: RoE | B44: 0.031668586 | C44: 0.039381888 | D44: 0.036733811 | E44: 0.10017779 | F44: 0.23037246 | G44: 0.23067735 | H44: 0.028039213 | I44: 0.04306344 | J44: 0.010332462 | K44: 0.010989242 | L44: -0.075842479 | M44: -0.23461953 | N44: 0.02900108 | O44: 0.035402473 | P44: 0.0098881964 | Q44: 0.033472344 | R44: -0.012955427 | S44: -0.045009499 | T44: 0.15836231 | U44: 0.17254127 | V44: 0.038261961 | W44: 0.076972314 | X44: 0.03734215 | Y44: 0.042644275 | Z44: 0.16843313 | AA44: 0.1504662 | AB44: 0.13192124 | AC44: 0.12710723 | AD44: -0.64390739 | AE44: -0.029609307 | AF44: 0.041085936 | AG44: 0.067596644 | AH44: 0.072546451 | AI44: 0.065680946 | AJ44: 0.09639702 | AK44: 0.099694962 | AL44: 0.030659643 | AM44: 0.015164762 | AN44: 0.10396661 | AO44: 0.075288401 | AP44: 0.10456494 | AQ44: 0.11273079 | AR44: 0.076783662 | AT44: 0.031035195 | AU44: 0.10568058
A45: Spread
A46: Yields (A) | B46: 0.1456731 | C46: 0.14396335 | D46: 0.13634577 | E46: 0.16679518 | F46: 0.21411246 | G46: 0.21891901 | H46: 0.1243627 | I46: 0.11292883 | J46: 0.093921346 | K46: 0.11289185 | L46: 0.13929898 | M46: 0.12522165 | N46: 0.12514502 | O46: 0.14332486 | P46: 0.1495683 | Q46: 0.14145785 | R46: 0.21520321 | S46: 0.11714773 | T46: 0.18138687 | U46: 0.14740094 | V46: 0.18166362 | W46: 0.1577137 | X46: 0.18350965 | Y46: 0.2111763 | Z46: 0.23879773 | AA46: 0.24257704 | AB46: 0.18652039 | AC46: 0.19148361 | AD46: 0.5284744 | AE46: 0.38755021 | AF46: 0.13927734 | AG46: 0.12379015 | AH46: 0.22889666 | AI46: 0.21828735 | AJ46: 0.18101606 | AK46: 0.18094733 | AL46: 0.12285373 | AM46: 0.1375852 | AN46: 0.16449568 | AO46: 0.14467139 | AP46: 0.11741784 | AQ46: 0.11058944 | AR46: 0.147708 | AT46: 0.129188 | AU46: 0.13369494
A47: Avg. Cost of Borrowing(B) | B47: 0.084008025 | C47: 0.082998589 | D47: 0.094254183 | E47: 0.082757327 | F47: 0.098349349 | G47: 0.09407348 | H47: 0.1049561 | I47: 0.076473532 | J47: 0.043957036 | K47: 0.08801517 | L47: 0.11177852 | M47: 0.091484097 | N47: 0.0025791382 | O47: 0.0042017876 | P47: 0.1092078 | Q47: 0.097816595 | R47: 0.13800991 | S47: 0.093781491 | T47: 0.072451357 | U47: 0.086672681 | V47: 0.09693825 | W47: 0.087700493 | X47: 0.090318183 | Y47: 0.10024361 | Z47: 0.11235011 | AA47: 0.10046744 | AB47: 0.087577838 | AC47: 0.090130063 | AD47: 0.16691653 | AE47: 0.13656193 | AF47: 0.087981151 | AG47: 0.080944603 | AH47: 0.11139906 | AI47: 0.10526429 | AJ47: 0.10242888 | AK47: 0.092387887 | AL47: 0.087357248 | AM47: 0.10702038 | AN47: 0.10075464 | AO47: 0.089828011 | AP47: 0.075859356 | AQ47: 0.06488655 | AR47: 0.081684045 | AT47: 0.11942799 | AU47: 0.12237932
A48: Spread(A-B) | B48: 0.061665073 | C48: 0.060964763 | D48: 0.042091583 | E48: 0.084037857 | F48: 0.11576311 | G48: 0.12484553 | H48: 0.019406598 | I48: 0.036455298 | J48: 0.04996431 | K48: 0.024876678 | L48: 0.027520465 | M48: 0.033737553 | N48: 0.12256588 | O48: 0.13912308 | P48: 0.040360501 | Q48: 0.043641252 | R48: 0.077193307 | S48: 0.023366244 | T48: 0.10893552 | U48: 0.060728257 | V48: 0.084725368 | W48: 0.070013203 | X48: 0.093191463 | Y48: 0.11093269 | Z48: 0.12644762 | AA48: 0.1421096 | AB48: 0.098942548 | AC48: 0.10135355 | AD48: 0.36155787 | AE48: 0.25098828 | AF48: 0.051296192 | AG48: 0.042845542 | AH48: 0.1174976 | AI48: 0.11302306 | AJ48: 0.078587181 | AK48: 0.08855944 | AL48: 0.035496484 | AM48: 0.030564826 | AN48: 0.063741038 | AO48: 0.054843378 | AP48: 0.041558486 | AQ48: 0.045702886 | AR48: 0.066023957 | AT48: 0.0097600084 | AU48: 0.011315622

Sheet NBFC-Wholesale
B1: NBFC-WHOLESALE
B2: Tata Cleantech | D2: PHL Finvest | F2: Shapoorji pallonji | H2: JM Credit Solutions
A3: Particulars | B3: FY 21 | C3: FY 22 | D3: FY 21 | F3: FY 21 | H3: FY 21 | I3: FY 22
B4: Aud | C4: Aud | D4: Aud | F4: Aud | H4: Aud | I4: Aud
B5: Rs in Lakh | D5: Rs in Lakh | F5: Rs in Lakh | H5: Rs in Crore
A6: Revenue from operations | B6: 66823 | C6: 70408 | D6: 200792 | F6: 15036.38 | G6: 14265.74 | H6: 1167.49 | I6: 1122.4
A7: Interest Income | B7: 57614 | C7: 63596 | D7: 135056 | F7: 14805.58 | G7: 13504.43 | H7: 1131.18 | I7: 1026.78
A8: Other Operation Income | B8: =B6-B7 -> 9209 | C8: =C6-C7 -> 6812 | D8: =D6-D7 -> 65736 | F8: =F6-F7 -> 230.8 | G8: =G6-G7 -> 761.31 | H8: =H6-H7 -> 36.31 | I8: =I6-I7 -> 95.62
A9: Interest expended | B9: 37822 | C9: 35243 | D9: 106228 | F9: 6561.97 | G9: 3657.99 | H9: 449.13 | I9: 455.43
A10: Net Interest Income | B10: =B7-B9 -> 19792 | C10: =C7-C9 -> 28353 | D10: =D7-D9 -> 28828 | F10: =F7-F9 -> 8243.61 | G10: =G7-G9 -> 9846.44 | H10: =H7-H9 -> 682.05 | I10: =I7-I9 -> 571.35
A11: Total Operating Income | B11: =SUM(B7:B8) -> 66823 | C11: =SUM(C7:C8) -> 70408 | D11: =SUM(D7:D8) -> 200792 | F11: =SUM(F7:F8) -> 15036.38 | G11: =SUM(G7:G8) -> 14265.74 | H11: =SUM(H7:H8) -> 1167.49 | I11: =SUM(I7:I8) -> 1122.4
A12: Other income | B12: 45 | C12: 10 | D12: 0 | F12: 0 | G12: 10.12 | I12: 13.7
A13: Total Income | B13: =B11+B12 -> 66868 | C13: =C11+C12 -> 70418 | D13: =D11+D12 -> 200792 | F13: =F11+F12 -> 15036.38 | G13: =G11+G12 -> 14275.86 | H13: =H11+H12 -> 1167.49 | I13: =I11+I12 -> 1136.1
A14: Operating expenses | B14: =2210+102+1868 -> 4180 | C14: =3065+108+2357 -> 5530 | D14: =6816+2912+241+6897 -> 16866 | F14: =1570.03+239.36+630.24 -> 2439.63 | G14: =2201.81+241.75+937 -> 3380.56 | H14: =27.79+2.19+24.63 -> 54.61 | I14: =35.64+3.13+24.63 -> 63.4
A15: Operating profit | B15: =B11-B14 -> 62643 | C15: =C11-C14 -> 64878 | D15: =D11-D14 -> 183926 | F15: =F11-F14 -> 12596.75 | G15: =G11-G14 -> 10885.18 | H15: =H11-H14 -> 1112.88 | I15: =I11-I14 -> 1059
A16: Pre-provisioning operating profit | B16: =B13-B14-B9 -> 24866 | C16: =C13-C14-C9 -> 29645 | D16: =D13-D14-D9 -> 77698 | F16: =F13-F14-F9 -> 6034.78 | G16: =G13-G14-G9 -> 7237.31 | H16: =H13-H14-H9 -> 663.75 | I16: =I13-I14-I9 -> 617.27
A17: Provisions | B17: 2797 | C17: 2780 | D17: 8831 | F17: 4189.23 | G17: 1234.79 | H17: 185.02 | I17: 224.56
A18: PAT | B18: 16773 | C18: 20381 | D18: 49067 | F18: 1344.1 | G18: 4057.7 | H18: 358.98 | I18: 289.06
A19: TNW | B19: 116245 | C19: 167682 | D19: =62868+457693 -> 520561 | F19: 41585.23 | G19: 45651.57 | H19: 3649.86 | I19: 3942.16
A20: Total Debt | B20: =154972+322207+53036 -> 530215 | C20: =242555+378070+52807 -> 673432 | D20: =283743+490139 -> 773882 | F20: =7612.95+45896.81 -> 53509.76 | G20: 26082.61 | H20: =3507.66+1999.45 -> 5507.11 | I20: =3826.93+1275.64 -> 5102.57
A21: Total Assets | B21: 650789 | C21: 848688 | D21: 1300128 | F21: 96434.11 | G21: 73346.97 | H21: 9220.18 | I21: 9113.19
A22: Loans & Advances (Gross) | B22: 628102 | C22: 784023 | D22: 906997 | F22: 75659.25 | G22: 51736.11 | H22: 7220.07 | I22: 7823.31
A23: Gross NPAs | B23: 6030 | C23: 5922 | D23: 50419 | F23: 2019.98 | H23: 288.93 | I23: 416.01
A24: Net NPAs | B24: 3837 | C24: 3768 | D24: 24055 | F24: 1262.98 | H24: 164.9 | I24: 284.53
A26: Profitability | B26: FY21 (A) | C26: FY22 (A) | D26: FY21 (A) | F26: FY21 (A) | G26: FY22 (A) | H26: FY21 (A) | I26: FY22 (A)
A27: Net Interest Margin | B27: 0.033998198 | C27: 0.040156502 | D27: 0.029767891 | F27: 0.093132824 | G27: 0.15458083 | H27: 0.093425428 | I27: 0.075960323
A28: Capitalization
A29: Leverage (Debt/TNW) | B29: 4.5611854 | C29: 4.0161258 | D29: 1.4866308 | F29: 1.2867492 | G29: 0.57134092 | H29: 1.5088551 | I29: 1.2943589
A30: CAR | B30: 0.2484 | C30: 0.2324 | D30: 0.391 | F30: 0.4101 | G30: 0.4727 | H30: 0.4009 | I30: 0.4528
A31: TNW/Loan Book | B31: 0.18507344 | C31: 0.21387383 | D31: 0.57393905 | F31: 0.54963841 | G31: 0.88239278 | H31: 0.50551587 | I31: 0.50389924
A32: Operational Efficiency
A33: Cost to Income (on total operating income net-off interest expenses) | B33: 0.14413296 | C33: 0.15725864 | D33: 0.1783554 | F33: 0.28788199 | G33: 0.31868775 | H33: 0.07602038 | I33: 0.095056749
A34: Cost to Income (on total operating income) | B34: 0.062553312 | C34: 0.078542211 | D34: 0.08399737 | F34: 0.16224849 | G34: 0.23697053 | H34: 0.046775561 | I34: 0.056486101
A35: Operating Expenses: Avg. Assets | B35: 0.0065678813 | C35: 0.0073759051 | D35: 0.011868852 | F35: 0.024710151 | G35: 0.039822576 | H35: 0.0062698552 | I35: 0.0069163498
A36: Loan Book Performance
A37: Gross NPA % | B37: 0.0096003515 | C37: 0.0075533498 | D37: 0.055588938 | F37: 0.026698388 | G37: 0 | H37: 0.040017618 | I37: 0.053175702
A38: Net NPA% | B38: 0.0061088804 | C38: 0.0048059815 | D38: 0.026521587 | F38: 0.016693002 | G38: 0 | H38: 0.022839114 | I38: 0.036369516
A39: Provision coverage Ratio | B39: 0.36368159 | C39: 0.36372847 | D39: 0.52289811 | F39: 0.37475619 | G39: #DIV/0! | H39: 0.42927353 | I39: 0.31605009
A40: Credit Cost | B40: 0.004804616 | C40: 0.0039373285 | D40: 0.0091189208 | F40: 0.047328151 | G40: 0.019385164 | H40: 0.025343556 | I40: 0.029854993
A42: Return Indicators
A43: Pre Provisioning operating profit (PPOP)margin | B43: 0.039071038 | C43: 0.039540453 | D43: 0.054677222 | F43: 0.061124156 | G43: 0.085254611 | H43: 0.076206123 | I43: 0.067338411
A44: RoA | B44: 0.026354802 | C44: 0.027184145 | D44: 0.034529167 | F44: 0.013613914 | G44: 0.047799201 | H44: 0.041215027 | I44: 0.031533755
A45: RoE | B45: 0.15602791 | C45: 0.14356507 | D45: 0.098914933 | F45: 0.032851595 | G45: 0.093027255 | H45: 0.10343561 | I45: 0.076148377
A46: Spread
A47: Yields (A) | B47: 0.098967875 | C47: 0.090071346 | D47: 0.13945929 | F47: 0.16726719 | G47: 0.21200819 | H47: 0.15494608 | I47: 0.13650922
A48: Avg. Cost of Borrowing(B) | B48: 0.072421046 | C48: 0.058560359 | D48: 0.11560388 | F48: 0.11619204 | G48: 0.091918107 | H48: 0.086703796 | I48: 0.085851788
A49: Spread(A-B) | B49: 0.026546829 | C49: 0.031510988 | D49: 0.023855408 | F49: 0.051075147 | G49: 0.12009009 | H49: 0.068242286 | I49: 0.050657427

Sheet NBFC-AFC
B1: NBFC-ASSET FINANCE COMPANIES
B2: IREDA | D2: KKR Asset Finance
A3: Particulars | B3: FY 21 | C3: FY 22 | D3: FY 21 | E3: FY 22
B4: Aud | C4: Aud | D4: Aud | E4: Aud
B5: Rs in Lakh | D5: Rs in Million
A6: Revenue from operations | B6: 265481.14 | C6: 285989.94 | D6: 4683.78 | E6: 4507.57
A7: Interest Income | B7: 249499.78 | C7: 264480.5 | D7: 4525.55 | E7: 3797.96
A8: Other Operation Income | B8: =B6-B7 -> 15981.36 | C8: =C6-C7 -> 21509.44 | D8: =D6-D7 -> 158.23 | E8: =E6-E7 -> 709.61
A9: Interest expended | B9: 157026.19 | C9: 158725.13 | D9: 1881.22 | E9: 2164.96
A10: Net Interest Income | B10: =B7-B9 -> 92473.59 | C10: =C7-C9 -> 105755.37 | D10: =D7-D9 -> 2644.33 | E10: =E7-E9 -> 1633
A11: Total Operating Income | B11: =SUM(B7:B8) -> 265481.14 | C11: =SUM(C7:C8) -> 285989.94 | D11: =SUM(D7:D8) -> 4683.78 | E11: =SUM(E7:E8) -> 4507.57
A12: Other income | B12: 293.21 | C12: 1425.54 | D12: 10.18 | E12: 5.21
A13: Total Income | B13: =B11+B12 -> 265774.35 | C13: =C11+C12 -> 287415.48 | D13: =D11+D12 -> 4693.96 | E13: =E11+E12 -> 4512.78
A14: Operating expenses | B14: =4735.95+2267.4+2002.33+1641.6 -> 10647.28 | C14: =5881.83+2324.31+13570.9+950.6 -> 22727.64 | D14: =314.73+24.05+265.39 -> 604.17 | E14: =364.39+24.53+356.12 -> 745.04
A15: Operating profit | B15: =B11-B14 -> 254833.86 | C15: =C11-C14 -> 263262.3 | D15: =D11-D14 -> 4079.61 | E15: =E11-E14 -> 3762.53
A16: Pre-provisioning operating profit | B16: =B13-B14-B9 -> 98100.88 | C16: =C13-C14-C9 -> 105962.71 | D16: =D13-D14-D9 -> 2208.57 | E16: =E13-E14-E9 -> 1602.78
A17: Provisions | B17: 34164.5 | C17: 17989.84 | D17: 598.71 | E17: -952.17
A18: PAT | B18: 34640.72 | C18: 63352.65 | D18: 452.1 | E18: 507.42
A19: TNW | B19: 299518.5 | C19: 526811.31 | D19: 21266.87 | E19: 21773
A20: Total Debt | B20: =912026.16+1423055.09+64919.2 -> 2400000.5 | C20: =922913.87+1773467.47+64925.97 -> 2761307.3 | D20: =21579.37 -> 21579.37 | E20: =4661.75+17345.53 -> 22007.28
A21: Total Assets | B21: 3029297.6 | C21: 3670840.4 | D21: 43045.25 | E21: 43971.47
A22: Loans & Advances (Gross) | B22: 2784035.9 | C22: 3391335.1 | D22: 33084.58 | E22: 29096.28
A23: Gross NPAs | B23: 244155.27 | C23: 176825.45 | D23: 2391.5 | E23: 907.45
A24: Net NPAs | B24: 151022.39 | C24: 103539.01 | D24: 1546.51 | E24: 547.88
A26: Profitability | B26: FY21 (A) | C26: FY22 (A) | D26: FY21 (A) | E26: FY22 (A)
A27: Net Interest Margin | B27: 0.035873963 | C27: 0.034250694 | D27: 0.079926358 | E27: 0.052524201
A28: Capitalization
A29: Leverage (Debt/TNW) | B29: 8.0128621 | C29: 5.241549 | D29: 1.0146942 | E29: 1.0107601
A30: CAR | D30: 0.566 | E30: 0.6348
A31: TNW/Loan Book | B31: 0.10758428 | C31: 0.15534039 | D31: 0.64280308 | E31: 0.74830872
A32: Operational Efficiency
A33: Cost to Income (on total operating income net-off interest expenses) | B33: 0.098172375 | C33: 0.17858542 | D33: 0.2155779 | E33: 0.31803843
A34: Cost to Income (on total operating income) | B34: 0.040105598 | C34: 0.079470068 | D34: 0.12899197 | E34: 0.1652864
A35: Operating Expenses: Avg. Assets | B35: 0.0036749672 | C35: 0.0067842304 | D35: 0.014035695 | E35: 0.017124065
A36: Loan Book Performance
A37: Gross NPA % | B37: 0.08769832 | C37: 0.052140366 | D37: 0.07228443 | E37: 0.031187836
A38: Net NPA% | B38: 0.054245849 | C38: 0.030530457 | D38: 0.046744133 | E38: 0.018829899
A39: Provision coverage Ratio | B39: 0.38144939 | C39: 0.4144564 | D39: 0.35333055 | E39: 0.39624222
A40: Credit Cost | B40: 0.013253687 | C40: 0.0058263188 | D40: 0.018096346 | E40: -0.030625823
A42: Return Indicators
A43: Pre Provisioning operating profit (PPOP)margin | B43: 0.033860058 | C43: 0.031630008 | D43: 0.0513081 | E43: 0.036838437
A44: RoA | B44: 0.011956435 | C44: 0.018910849 | D44: 0.010502901 | E44: 0.011662586
A45: RoE | B45: 0.12558941 | C45: 0.15333502 | D45: 0.021258417 | E45: 0.023579068
A46: Spread
A47: Yields (A) | B47: 0.096790293 | C47: 0.085656555 | D47: 0.13678729 | E47: 0.12215849
A48: Avg. Cost of Borrowing(B) | B48: 0.068490309 | C48: 0.06150578 | D48: 0.08717678 | E48: 0.099340509
A49: Spread(A-B) | B49: 0.028299984 | C49: 0.024150775 | D49: 0.049610508 | E49: 0.022817981

Sheet NBFC-IFC
B1: NBFC-INFRASTRUCTURE FINANCE COMPANIES
B2: PTC India Financial Services | D2: IIFCL | F2: Assem Infra | H2: Power Finance Corporation | J2: REC | L2: IRFC
A3: Particulars | B3: FY 21 | D3: FY 21 | F3: FY 21 | G3: FY 22 | H3: FY 21 | I3: FY 22 | J3: FY 21 | K3: FY 22 | L3: FY 21 | M3: FY 22
B4: Aud | D4: Aud | F4: Aud | G4: Aud | H4: Aud | I4: Aud | J4: Aud | K4: Aud | L4: Aud | M4: Aud
B5: Rs in Lakh | D5: Rs in Lakh | F5: Rs in Lakh | H5: Rs in Crore | J5: Rs in Crore | L5: Rs in Millions
A6: Revenue from operations | B6: =113945.03-888.25 -> 113056.78 | D6: 334556.28 | F6: =4701.11+37.72 -> 4738.83 | G6: =31124.3+217.45 -> 31341.75 | H6: 37744.87 | I6: 38545.4 | J6: 35387.99 | K6: 39132.49 | L6: 157704.72 | M6: 202992.64
A7: Interest Income | B7: 106024.52 | D7: 330269.23 | F7: 1774.92 | G7: 23777.82 | H7: =36058.44-331.27 -> 35727.17 | I7: =36780.13-386.71 -> 36393.42 | J7: 34229.92 | K7: 37810.84 | L7: 157512.7 | M7: 202801.61
A8: Other Operation Income | B8: =B6-B7 -> 7032.26 | D8: =D6-D7 -> 4287.05 | F8: =F6-F7 -> 2963.91 | G8: =G6-G7 -> 7563.93 | H8: =H6-H7 -> 2017.7 | I8: =I6-I7 -> 2151.98 | J8: =J6-J7 -> 1158.07 | K8: =K6-K7 -> 1321.65 | L8: =L6-L7 -> 192.02 | M8: =M6-M7 -> 191.03
A9: Interest expended | B9: 75150.23 | D9: 222918.68 | F9: 185.73 | G9: 14275.62 | H9: 23194.49 | I9: 22671.3 | J9: 21489.08 | K9: 22052.91 | L9: 112370.53 | M9: 140747.82
A10: Net Interest Income | B10: =B7-B9 -> 30874.29 | D10: =D7-D9 -> 107350.55 | F10: =F7-F9 -> 1589.19 | G10: =G7-G9 -> 9502.2 | H10: =H7-H9 -> 12532.68 | I10: =I7-I9 -> 13722.12 | J10: =J7-J9 -> 12740.84 | K10: =K7-K9 -> 15757.93 | L10: =L7-L9 -> 45142.17 | M10: =M7-M9 -> 62053.79
A11: Total Operating Income | B11: =SUM(B7:B8) -> 113056.78 | D11: =SUM(D7:D8) -> 334556.28 | F11: =SUM(F7:F8) -> 4738.83 | G11: =SUM(G7:G8) -> 31341.75 | H11: =SUM(H7:H8) -> 37744.87 | I11: =SUM(I7:I8) -> 38545.4 | J11: =SUM(J7:J8) -> 35387.99 | K11: =SUM(K7:K8) -> 39132.49 | L11: =SUM(L7:L8) -> 157704.72 | M11: =SUM(M7:M8) -> 202992.64
A12: Other income | B12: 888.25 | D12: 66770.9 | G12: 52.65 | H12: 21.7 | I12: 45.77 | J12: 22.55 | K12: 97.96 | L12: 3.9 | M12: 23.33
A13: Total Income | B13: =B11+B12 -> 113945.03 | D13: =D11+D12 -> 401327.18 | F13: =F11+F12 -> 4738.83 | G13: =G11+G12 -> 31394.4 | H13: =H11+H12 -> 37766.57 | I13: =I11+I12 -> 38591.17 | J13: =J11+J12 -> 35410.54 | K13: =K11+K12 -> 39230.45 | L13: =L11+L12 -> 157708.62 | M13: =M11+M12 -> 203015.97
A14: Operating expenses | B14: =148.02+595.82+1674.33+595.43+3492.87 -> 6506.47 | D14: =179639.16+1449.42+3140.16+2537.32+4934.5 -> 191700.56 | F14: =599.25+2.76+447.43 -> 1049.44 | G14: =1090.24+20.15+959.1 -> 2069.49 | H14: =70.8+222.61+11.17+194.62+518.95+14.28-164.06 -> 868.37 | I14: =10.18+213.11+13.2+214.72+122.71+905.58 -> 1479.5 | J14: =330.26+9.95+144.84+9.53+144.32+106.71 -> 745.61 | K14: =799.05+16.73+158.86+17.96+170.67+116.06 -> 1279.33 | L14: =78.47+44.32+1026.84 -> 1149.63 | M14: =107.48+140.25+1114.26 -> 1361.99
A15: Operating profit | B15: =B11-B14 -> 106550.31 | D15: =D11-D14 -> 142855.72 | F15: =F11-F14 -> 3689.39 | G15: =G11-G14 -> 29272.26 | H15: =H11-H14 -> 36876.5 | I15: =I11-I14 -> 37065.9 | J15: =J11-J14 -> 34642.38 | K15: =K11-K14 -> 37853.16 | L15: =L11-L14 -> 156555.09 | M15: =M11-M14 -> 201630.65
A16: Pre-provisioning operating profit | B16: =B13-B14-B9 -> 32288.33 | D16: =D13-D14-D9 -> -13292.06 | F16: =F13-F14-F9 -> 3503.66 | G16: =G13-G14-G9 -> 15049.29 | H16: =H13-H14-H9 -> 13703.71 | I16: =I13-I14-I9 -> 14440.37 | J16: =J13-J14-J9 -> 13175.85 | K16: =K13-K14-K9 -> 15898.21 | L16: =L13-L14-L9 -> 44188.46 | M16: =M13-M14-M9 -> 60906.16
A17: Provisions | B17: 22946.97 | D17: -44834.61 | F17: 854.97 | G17: 4239.51 | H17: 3496.4 | I17: 2222.14 | J17: 2419.62 | K17: 3473.31 | L17: 27.15 | M17: 4.61
A18: PAT | B18: 2560.31 | D18: 28527.45 | F18: 2080.03 | G18: 8523.37 | H18: 8444.01 | I18: 10021.9 | J18: 8361.78 | K18: 10045.92 | L18: 44161.31 | M18: 60898.36
A19: TNW | B19: 211950.43 | D19: 1065447.1 | F19: 225275.48 | G19: 265402.73 | H19: 52393.12 | I19: 59350.28 | J19: 43426.37 | K19: 50985.6 | L19: 359133.82 | M19: 409963.4
A20: Total Debt | B20: =63608.8+853810.92 -> 917419.72 | D20: =1848997.24+2121065.96 -> 3970063.2 | F20: 44182.49 | G20: 472748.4 | H20: =242811.54+80837.6+9310.2 -> 332959.34 | I20: =230156.95+87965.42+9311.27 -> 327433.64 | J20: =237328.06+85507.36+6946.89 -> 329782.31 | K20: =219633.57+106651.59+6816.47 -> 333101.63 | L20: =1785747.89+1445358.9 -> 3231106.8 | M20: =1941749.53+1942416.65 -> 3884166.2
A21: Total Assets | B21: 1153207.6 | D21: 5552458.6 | F21: 270460.33 | G21: 847219.57 | H21: 392084.07 | I21: 394410.01 | J21: 400233.19 | K21: 410412.61 | L21: 3804815.2 | M21: 4499802.2
A22: Loans & Advances (Gross) | B22: 1058977.1 | D22: 3670260 | F22: 158832.28 | G22: 699194.28 | H22: 376665.52 | I22: 378201.04 | J22: 378467.6 | K22: 386635.2 | L22: 69978.06 | M22: 68522.14
A23: Gross NPAs | B23: 82410.63 | D23: 510043.88 | H23: 21150.16 | I23: 20915.28 | J23: 18256.93 | K23: 17159.89
A24: Net NPAs | B24: 31305.84 | D24: 197718.2 | H24: 7733.8 | I24: 6570.9 | J24: 6465.62 | K24: 5594.16
A26: Profitability | B26: FY21 (A) | D26: FY21 (A) | F26: FY21 (A) | G26: FY22 (A) | H26: FY21 (A) | I26: FY22 (A) | J26: FY21 (A) | K26: FY22 (A) | L26: FY21 (A) | M26: FY22 (A)
A27: Net Interest Margin | B27: 0.028804281 | D27: 0.030523407 | F27: 0.01000546 | G27: 0.022148965 | H27: 0.034498599 | I27: 0.036356412 | J27: 0.03627042 | K27: 0.041191667 | L27: 0.67141009 | M27: 0.89608232
A28: Capitalization
A29: Leverage (Debt/TNW) | B29: 4.3284636 | D29: 3.7261946 | F29: 0.19612649 | G29: 1.7812492 | H29: 6.3550203 | I29: 5.5169687 | J29: 7.5940566 | K29: 6.5332492 | L29: 8.9969438 | M29: 9.4744218
A30: CAR | B30: 0.241 | D30: 0.3086 | F30: 1.5087 | G30: 0.352 | H30: 0.1883 | I30: 0.2348 | J30: 0.1972 | K30: 0.2361 | L30: 4.2046 | M30: 4.3973
A31: TNW/Loan Book | B31: 0.20014637 | D31: 0.290292 | F31: 1.418323 | G31: 0.37958367 | H31: 0.1390972 | I31: 0.15692786 | J31: 0.11474264 | K31: 0.13187004 | L31: 5.1320917 | M31: 5.9829334
A32: Operational Efficiency
A33: Cost to Income (on total operating income net-off interest expenses) | B33: 0.17164501 | D33: 1.7171684 | F33: 0.23048912 | G33: 0.12126299 | H33: 0.059680228 | I33: 0.093202134 | J33: 0.053645214 | K33: 0.074904067 | L33: 0.025359006 | M33: 0.021881178
A34: Cost to Income (on total operating income) | B34: 0.057550463 | D34: 0.57299944 | F34: 0.22145551 | G34: 0.066029816 | H34: 0.023006305 | I34: 0.038383309 | J34: 0.021069578 | K34: 0.032692272 | L34: 0.0072897628 | M34: 0.0067095536
A35: Operating Expenses: Avg. Assets | B35: 0.0056153399 | D35: 0.035608329 | F35: 0.0038801994 | G35: 0.0037031891 | H35: 0.0023037618 | I35: 0.0037622661 | J35: 0.0019970249 | K35: 0.003156323 | L35: 0.00035050462 | M35: 0.00032800788
A36: Loan Book Performance
A37: Gross NPA % | B37: 0.077820973 | D37: 0.13896669 | F37: 0 | G37: 0 | H37: 0.056151038 | I37: 0.055302016 | J37: 0.048239083 | K37: 0.044382638 | L37: 0 | M37: 0
A38: Net NPA% | B38: 0.029562338 | D38: 0.053870353 | F38: 0 | G38: 0 | H38: 0.020532275 | I38: 0.017374093 | J38: 0.017083682 | K38: 0.014468833 | L38: 0 | M38: 0
A39: Provision coverage Ratio | B39: 0.62012376 | D39: 0.61235061 | F39: #DIV/0! | G39: #DIV/0! | H39: 0.63433846 | I39: 0.68583256 | J39: 0.64585393 | K39: 0.67399791 | L39: #DIV/0! | M39: #DIV/0!
A40: Credit Cost | B40: 0.021408459 | D40: -0.012748002 | F40: 0.0053828479 | G40: 0.0098820018 | H40: 0.0096245098 | I40: 0.0058875041 | J40: 0.0068881356 | K40: 0.0090793289 | L40: 0.00040380832 | M40: 6.6570301e-05
A42: Return Indicators
A43: Pre Provisioning operating profit (PPOP)margin | B43: 0.027866101 | D43: -0.0024689967 | F43: 0.012954432 | G43: 0.026929517 | H43: 0.036355567 | I43: 0.036720861 | J43: 0.035289898 | K43: 0.039223567 | L43: 0.013472386 | M43: 0.014668023
A44: RoA | B44: 0.0022096484 | D44: 0.0052989664 | F44: 0.0076907027 | G44: 0.015251898 | H44: 0.022401727 | I44: 0.025484998 | J44: 0.022396002 | K44: 0.02478498 | L44: 0.013464109 | M44: 0.014666145
A45: RoE | B45: 0.01209312 | D45: 0.027220524 | F45: 0.009233273 | G45: 0.03474118 | H45: 0.17310882 | I45: 0.17937346 | J45: 0.21303103 | K45: 0.2128103 | L45: 0.13339139 | M45: 0.15836323
A46: Spread
A47: Yields (A) | B47: 0.098915962 | D47: 0.093906757 | F47: 0.011174807 | G47: 0.055424438 | H47: 0.098345869 | I47: 0.096423453 | J47: 0.097445191 | K47: 0.098838587 | L47: 2.3427234 | M47: 2.9285389
A48: Avg. Cost of Borrowing(B) | B48: 0.081467568 | D48: 0.058525543 | F48: 0.0042037015 | G48: 0.055232219 | H48: 0.072118356 | I48: 0.068660027 | J48: 0.069755836 | K48: 0.066536263 | L48: 0.040313209 | M48: 0.03956217
A49: Spread(A-B) | B49: 0.017448394 | D49: 0.035381214 | F49: 0.006971105 | G49: 0.00019221938 | H49: 0.026227513 | I49: 0.027763425 | J49: 0.027689355 | K49: 0.032302325 | L49: 2.3024101 | M49: 2.8889767

Sheet NBFC-HFC
B1: NBFC- HOUSING FINANCE COMPANIES
B2: Aavas Financiers | D2: Aptus Value Housing | F2: Motilal Oswal Home Loans | H2: Vastu Housing Finance | J2: Sundaram Home Finance | L2: Svatantra Microfinance | N2: IKF Home Finance | P2: India Shelter | R2: Shubham Housing Development | T2: Indostar Home Finance | V2: LIC Housing | X2: HDFC Ltd | Z2: Repco Home finance | AB2: Bajaj Housing Finance | AD2: PNB Housing
A3: Particulars | B3: FY 21 | C3: FY 22 | D3: FY 21 | E3: FY 22 | F3: FY 21 | G3: FY 22 | H3: FY 21 | I3: FY 22 | J3: FY 21 | K3: FY 22 | L3: FY 21 | M3: FY 22 | N3: FY 21 | P3: FY 21 | Q3: FY 22 | R3: FY 21 | S3: FY 22 | T3: FY 21 | V3: FY 21 | W3: FY 22 | X3: FY 21 | Y3: FY 22 | Z3: FY 21 | AA3: FY 22 | AB3: FY 21 | AC3: FY 22 | AD3: FY 21 | AE3: FY 22
B4: Aud | C4: Aud | D4: Aud | E4: Aud | F4: Aud | G4: Aud | H4: Aud | I4: Aud | J4: Aud | K4: Aud | L4: Aud | M4: Aud | N4: Aud | P4: Aud | Q4: Aud | R4: Aud | S4: Aud | T4: Aud | V4: Aud | W4: Aud | X4: Aud | Y4: Aud | Z4: Aud | AA4: Aud | AB4: Aud | AC4: Aud | AD4: Aud | AE4: Aud
B5: Rs in Lakhs | D5: Rs in Lakhs | F5: Rs in Lakhs | H5: Rs in Lakhs | J5: Rs in Lakhs | L5: Rs in Lakhs | N5: Rs in Lakhs | P5: Rs in Lakhs | R5: Rs in Lakhs | T5: Rs in Lakhs | V5: Rs in crore | X5: Rs in Crore | Z5: Rs in Crore | AB5: Rs in Crore | AD5: Rs in Crore
A6: Revenue from operations | B6: 110317.46 | C6: 130435.89 | D6: 53466.16 | E6: 67896.83 | F6: 53919 | G6: 52170 | H6: 35195.04 | I6: 48216.23 | J6: 103911.35 | K6: 95659.17 | L6: 9114.49 | M6: 11186.13 | N6: 3980.37 | P6: 31670.61 | Q6: 44797.7 | R6: 33655.15 | S6: 34686.92 | T6: 13217.82 | V6: 19847.15 | W6: 19919.07 | X6: 48149.74 | Y6: 47957.07 | Z6: 1373.46 | AA6: 1290.19 | AB6: 3154.7 | AC6: 3766.66 | AD6: 7565.2 | AE6: 6141.09
A7: Interest Income | B7: 89939.42 | C7: 106452.48 | D7: 52408.4 | E7: 65934.21 | F7: 52809 | G7: 49773 | H7: 28290.66 | I7: 35951.36 | J7: 96920.26 | K7: 89052.81 | L7: 8779.21 | M7: 10666.12 | N7: 2925.27 | P7: 25719.71 | Q7: 35663.21 | R7: 29040.36 | S7: 32108.9 | T7: 10835.88 | V7: 19514.31 | W7: 19460.2 | X7: 41453.15 | Y7: 41044.17 | Z7: 1351.82 | AA7: 1258.17 | AB7: 2832.81 | AC7: 3463.64 | AD7: 6987.32 | AE7: 5535.98
A8: Other Operation Income | B8: =B6-B7 -> 20378.04 | C8: =C6-C7 -> 23983.41 | D8: =D6-D7 -> 1057.76 | E8: =E6-E7 -> 1962.62 | F8: =F6-F7 -> 1110 | G8: =G6-G7 -> 2397 | H8: =H6-H7 -> 6904.38 | I8: =I6-I7 -> 12264.87 | ... N8: =N6-N7 -> 1055.1 | P8: =P6-P7 -> 5950.9 | Q8: =Q6-Q7 -> 9134.49 | R8: =R6-R7 -> 4614.79 | S8: =S6-S7 -> 2578.02 | T8: =T6-T7 -> 2381.94 | V8: =V6-V7 -> 332.84 | W8: =W6-W7 -> 458.87 | X8: =X6-X7 -> 6696.59 | Y8: =Y6-Y7 -> 6912.9 | Z8: =Z6-Z7 -> 21.64 | AA8: =AA6-AA7 -> 32.02 | AB8: =AB6-AB7 -> 321.89 | AC8: =AC6-AC7 -> 303.02 | ... AE8: =AE6-AE7 -> 605.11
A9: Interest expended | B9: 45824.27 | C9: 47750.33 | D9: 18208.21 | E9: 17919.56 | F9: 28890 | G9: 22903 | H9: 12800.13 | I9: 12557.83 | J9: 62537.2 | K9: 53242.96 | L9: 6162.39 | M9: 7452.17 | N9: 1572.39 | P9: 10534.81 | Q9: 14833.86 | R9: 14017.95 | S9: 15789.36 | T9: 5658.05 | V9: 14452.58 | W9: 14153.65 | X9: 28614.76 | Y9: 26739.21 | Z9: 807.24 | AA9: 689.93 | AB9: 1965.87 | AC9: 2155.31 | AD9: 5100.4 | AE9: 4065.63
A10: Net Interest Income | B10: =B7-B9 -> 44115.15 | C10: =C7-C9 -> 58702.15 | D10: =D7-D9 -> 34200.19 | E10: =E7-E9 -> 48014.65 | F10: =F7-F9 -> 23919 | G10: =G7-G9 -> 26870 | H10: =H7-H9 -> 15490.53 | I10: =I7-I9 -> 23393.53 | ... N10: =N7-N9 -> 1352.88 | P10: =P7-P9 -> 15184.9 | Q10: =Q7-Q9 -> 20829.35 | R10: =R7-R9 -> 15022.41 | S10: =S7-S9 -> 16319.54 | T10: =T7-T9 -> 5177.83 | V10: =V7-V9 -> 5061.73 | W10: =W7-W9 -> 5306.55 | X10: =X7-X9 -> 12838.39 | Y10: =Y7-Y9 -> 14304.96 | Z10: =Z7-Z9 -> 544.58 | AA10: =AA7-AA9 -> 568.24 | AB10: =AB7-AB9 -> 866.94 | AC10: =AC7-AC9 -> 1308.33 | ... AE10: =AE7-AE9 -> 1470.35
A11: Total Operating Income | B11: =SUM(B7:B8) -> 110317.46 | C11: =SUM(C7:C8) -> 130435.89 | D11: =SUM(D7:D8) -> 53466.16 | E11: =SUM(E7:E8) -> 67896.83 | F11: =SUM(F7:F8) -> 53919 | G11: =SUM(G7:G8) -> 52170 | H11: =SUM(H7:H8) -> 35195.04 | I11: =SUM(I7:I8) -> 48216.23 | ... N11: =SUM(N7:N8) -> 3980.37 | P11: =SUM(P7:P8) -> 31670.61 | Q11: =SUM(Q7:Q8) -> 44797.7 | R11: =SUM(R7:R8) -> 33655.15 | S11: =SUM(S7:S8) -> 34686.92 | T11: =SUM(T7:T8) -> 13217.82 | V11: =SUM(V7:V8) -> 19847.15 | W11: =SUM(W7:W8) -> 19919.07 | X11: =SUM(X7:X8) -> 48149.74 | Y11: =SUM(Y7:Y8) -> 47957.07 | Z11: =SUM(Z7:Z8) -> 1373.46 | AA11: =SUM(AA7:AA8) -> 1290.19 | AB11: =SUM(AB7:AB8) -> 3154.7 | AC11: =SUM(AC7:AC8) -> 3766.66 | ... AE11: =SUM(AE7:AE8) -> 6141.09
A12: Other income | B12: 216.05 | C12: 119.91 | D12: 1688.07 | E12: 2391.27 | F12: 633 | G12: 450 | H12: 118.22 | I12: 243.29 | J12: 4.57 | K12: 39.54 | L12: 115.69 | M12: 177.13 | N12: 41.03 | P12: 609.22 | Q12: 1182.8 | R12: 422.84 | S12: 285.36 | T12: 188.93 | V12: 0.54 | W12: 33.95 | X12: 26.12 | Y12: 33.13 | Z12: 18.77 | AA12: 16.38 | AB12: 0.58 | AC12: 0.47 | AD12: 18.78 | AE12: 4.83
A13: Total Income | B13: =B11+B12 -> 110533.51 | C13: =C11+C12 -> 130555.8 | D13: =D11+D12 -> 55154.23 | E13: =E11+E12 -> 70288.1 | F13: =F11+F12 -> 54552 | G13: =G11+G12 -> 52620 | H13: =H11+H12 -> 35313.26 | I13: =I11+I12 -> 48459.52 | ... N13: =N11+N12 -> 4021.4 | P13: =P11+P12 -> 32279.83 | Q13: =Q11+Q12 -> 45980.5 | R13: =R11+R12 -> 34077.99 | S13: =S11+S12 -> 34972.28 | T13: =T11+T12 -> 13406.75 | V13: =V11+V12 -> 19847.69 | W13: =W11+W12 -> 19953.02 | X13: =X11+X12 -> 48175.86 | Y13: =Y11+Y12 -> 47990.2 | Z13: =Z11+Z12 -> 1392.23 | AA13: =AA11+AA12 -> 1306.57 | AB13: =AB11+AB12 -> 3155.28 | AC13: =AC11+AC12 -> 3767.13 | ... AE13: =AE11+AE12 -> 6145.92
A14: Operating expenses | B14: =618.46+17213.61+2060.37+5770 -> 25662.44 | C14: =571.23+23223.53+2375.76+8888.7 -> 35059.22 | D14: =6540.66+567.08+1460.25 -> 8567.99 | E14: =7405.57+661.19+1729.73 -> 9796.49 | F14: =5765+647+2170 -> 8582 | G14: =7584+469+2514 -> 10567 | H14: =6156.86+336+1615.46 -> 8108.32 | I14: =9128.84+432.55+1754.28 -> 11315.67 | J14: =6628.21+1293.55+3098.91 -> 11020.67 | K14: =7270.91+1155.79+4663.39 -> 13090.09 | L14: =1383.7+78.41+479.23 -> 1941.34 | M14: =1954.88+104.69+697.21 -> 2756.78 | N14: =816.76+49.03+272.23 -> 1138.02 | P14: =6168.58+509.84+1786.18 -> 8464.6 | Q14: =10140.62+653.9+2473.14 -> 13267.66 | R14: =8585.04+533.38+2176.53 -> 11294.95 | S14: =10115.9+541.58+2828.14 -> 13485.62 | T14: =1808.4+200.82+917.15 -> 2926.37 | V14: =109.15+293.18+49.44+249.74 -> 701.51 | W14: =135.54+563.32+52.44+248.09 -> 999.39 | X14: =914.11+158.78+725.12 -> 1798.01 | Y14: =1060.79+172.29+839.6 -> 2072.68 | Z14: =71.35+12.98+30.11 -> 114.44 | AA14: =78.63+12.88+32.56 -> 124.07 | AB14: =1.33+245.76+21.77+60.16 -> 329.02 | AC14: =4.68+348.8+25.76+91.65 -> 470.89 | AD14: =176.37+6.68+58.78+193.2 -> 435.03 | AE14: =180.05+9+53.18+198.91 -> 441.14
A15: Operating profit | B15: =B11-B14 -> 84655.02 | C15: =C11-C14 -> 95376.67 | D15: =D11-D14 -> 44898.17 | E15: =E11-E14 -> 58100.34 | F15: =F11-F14 -> 45337 | G15: =G11-G14 -> 41603 | H15: =H11-H14 -> 27086.72 | I15: =I11-I14 -> 36900.56 | ... N15: =N11-N14 -> 2842.35 | P15: =P11-P14 -> 23206.01 | Q15: =Q11-Q14 -> 31530.04 | R15: =R11-R14 -> 22360.2 | S15: =S11-S14 -> 21201.3 | T15: =T11-T14 -> 10291.45 | V15: =V11-V14 -> 19145.64 | W15: =W11-W14 -> 18919.68 | X15: =X11-X14 -> 46351.73 | Y15: =Y11-Y14 -> 45884.39 | Z15: =Z11-Z14 -> 1259.02 | AA15: =AA11-AA14 -> 1166.12 | AB15: =AB11-AB14 -> 2825.68 | AC15: =AC11-AC14 -> 3295.77 | ... AE15: =AE11-AE14 -> 5699.95
A16: Pre-provisioning operating profit | B16: =B13-B14-B9 -> 39046.8 | C16: =C13-C14-C9 -> 47746.25 | D16: =D13-D14-D9 -> 28378.03 | E16: =E13-E14-E9 -> 42572.05 | F16: =F13-F14-F9 -> 17080 | G16: =G13-G14-G9 -> 19150 | H16: =H13-H14-H9 -> 14404.81 | I16: =I13-I14-I9 -> 24586.02 | ... N16: =N13-N14-N9 -> 1310.99 | P16: =P13-P14-P9 -> 13280.42 | Q16: =Q13-Q14-Q9 -> 17878.98 | R16: =R13-R14-R9 -> 8765.09 | S16: =S13-S14-S9 -> 5697.3 | T16: =T13-T14-T9 -> 4822.33 | V16: =V13-V14-V9 -> 4693.6 | W16: =W13-W14-W9 -> 4799.98 | X16: =X13-X14-X9 -> 17763.09 | Y16: =Y13-Y14-Y9 -> 19178.31 | Z16: =Z13-Z14-Z9 -> 470.55 | AA16: =AA13-AA14-AA9 -> 492.57 | AB16: =AB13-AB14-AB9 -> 860.39 | AC16: =AC13-AC14-AC9 -> 1140.93 | ... AE16: =AE13-AE14-AE9 -> 1639.15
A17: Provisions | B17: 3713.86 | C17: 2260.52 | D17: 493.62 | E17: 2933.61 | F17: 8035 | G17: 7319 | H17: 1081.86 | I17: 1875.25 | J17: 5227.97 | K17: 8093.92 | L17: 357.18 | M17: 74.83 | N17: 114.48 | P17: 1984.73 | Q17: 1188.87 | R17: 954.51 | S17: 2603.04 | T17: 955.1 | V17: 1317.61 | W17: 1988.24 | X17: 2948 | Y17: 1932 | Z17: 80.76 | AA17: 233.06 | AB17: 247.21 | AC17: 181.07 | AD17: 861.83 | AE17: 576.38
A18: PAT | B18: 28949.52 | C18: 35679.92 | D18: 21785.48 | E18: 30822.86 | F18: 4023 | G18: 9489 | H18: 10026.53 | I18: 17628.16 | J18: 19164.34 | K18: 16769.65 | L18: 577.6 | M18: 869.78 | N18: 905.33 | P18: 8738.86 | Q18: 12844.71 | R18: 6076.99 | S18: 2491.11 | T18: 2795.13 | V18: 2734.34 | W18: 2287.28 | X18: 12027.3 | Y18: 13742.18 | Z18: 287.6 | AA18: 191.54 | AB18: 453.19 | AC18: 709.62 | AD18: 925.22 | AE18: 821.92
A19: TNW | B19: 240140.48 | C19: 280864.34 | D19: 189109.61 | E19: 276589.56 | F19: 90953 | G19: 100697 | H19: 99479.94 | I19: 210640.57 | J19: =10125.44+145744.96 -> 155870.4 | K19: =10125.44+155372.19 -> 165497.63 | L19: 16749.87 | M19: 19625.25 | N19: 5883.04 | P19: 93726.96 | Q19: 107612.64 | R19: 52481.92 | S19: 54985.26 | T19: 21529.3 | V19: 20521.31 | W19: 24671.84 | X19: 108782.65 | Y19: 120251 | Z19: 2059.29 | AA19: 2235.6 | AB19: 6032.22 | AC19: 6741.36 | AD19: 8867.18 | AE19: 9800.54
A20: Total Debt | B20: =146466.15+478102.49+9973.65+3229.82 -> 637772.11 | C20: =170946.09+616321.15+9982.5+3948.24 -> 801197.98 | D20: =38144.13+178592.76+709.05 -> 217445.94 | E20: =38211.45+195680.54+780.13 -> 234672.12 | F20: =114924+170321 -> 285245 | G20: =74619+186027 -> 260646 | H20: =33277.38+119516.32 -> 152793.7 | I20: =17970.83+113846 -> 131816.83 | J20: =257188.02+365432.58+184588.41+13265.58 -> 820474.59 | K20: =321230.62+317984.63+200042.21+13286.7 -> 852544.16 | L20: =9222.09+66581.35 -> 75803.44 | M20: =11754.39+92914.62+2000 -> 106669.01 | N20: =6392.8+9522.81 -> 15915.61 | P20: =8222.38+140906.65 -> 149129.03 | Q20: =18659.85+188341.12 -> 207000.97 | R20: =11278.35+148867.47 -> 160145.82 | S20: =12736.2+167329.48 -> 180065.68 | T20: 63984.46 | V20: 207861.49 | W20: =127341.99+76447.22+18073.5+1795.44 -> 223658.15 | X20: =182054.73+105179.18+150131.13+4000 -> 441365.04 | Y20: =195929.63+139851.75+160899.76+3000 -> 499681.14 | Z20: 10197.39 | AA20: 9691.99 | AB20: =11332.08+20268.52 -> 31600.6 | AC20: =16489.15+24493.17+510 -> 41492.32 | AD20: =11461.48+29746.34+16747.42+1438.58 -> 59393.82 | AE20: =6201.97+27715.84+17648.97+1438.18 -> 53004.96
A21: Total Assets | B21: 896004.7 | C21: 1102038.3 | D21: 408924.54 | E21: 515052.73 | F21: 389758 | G21: 376302 | H21: 276670.67 | I21: 380238.8 | J21: 982966.54 | K21: 1024913.2 | L21: 93317.65 | M21: 127211.27 | N21: 22984.41 | P21: 246264.17 | Q21: 322122.11 | R21: 237370.75 | S21: 254077.45 | T21: 89034.54 | V21: 235633.32 | W21: 254567.46 | X21: 567598.58 | Y21: 640862.46 | Z21: 12364.52 | AA21: 11997.39 | AB21: 37858.38 | AC21: 48527.08 | AD21: 71332.52 | AE21: 65649.3
A22: Loans & Advances (Gross) | B22: 757286.55 | C22: 911773.88 | D22: 344428.15 | E22: 4445334.6 | F22: 347429 | G22: 343455 | H22: 217701.45 | I22: 283516.6 | J22: 906908.77 | K22: 943998.56 | L22: 81488.13 | M22: 113056.61 | N22: 19273.98 | P22: 201217.29 | Q22: 265687.27 | R22: 195979.34 | S22: 228883.42 | T22: 85355.75 | V22: 232013.8 | W22: 251135.45 | X22: 498298.03 | Y22: 568363.29 | Z22: 12124.22 | AA22: 11763.43 | AB22: 33774.66 | AC22: 46949.66 | AD22: 63231.48 | AE22: 57939.68
A23: Gross NPAs | B23: 7391.35 | C23: 9035.93 | D23: 2468.06 | E23: 5065.53 | F23: 7662 | G23: 5725 | H23: 1056.6 | I23: 3628.4 | J23: 40660 | K23: 28323 | L23: 1442.69 | M23: 1872.84 | N23: 182.24 | P23: 3618.7 | Q23: 5703.9 | R23: 4247 | S23: 8141 | T23: 1550.9 | V23: 9659.13 | W23: 11616.4 | X23: 11615.77 | Y23: 12875.04 | Z23: 503.66 | AA23: 881.99 | AB23: 119.13 | AC23: 146.36 | AD23: 2998.41 | AE23: 4706.17
A24: Net NPAs | B24: 5377.55 | C24: 6952.57 | D24: 1774.94 | E24: 3781.63 | F24: 5248 | G24: 3150 | H24: 766.04 | I24: 2648.75 | J24: 9582 | K24: 14571 | L24: 1417.82 | M24: 1554.56 | N24: 126.33 | P24: 2469.46 | Q24: 4253.35 | R24: 2769 | S24: 5579 | T24: 1200.22 | V24: 5913.93 | W24: 6596.72 | X24: 5558.77 | Y24: 5883.98 | Z24: 325.06 | AA24: 620.86 | AB24: 73.93 | AC24: 66.89 | AD24: 1749.15 | AE24: 2930.96
A26: Profitability | B26: FY21 (A) | C26: FY22 (A) | D26: FY21 (A) | E26: FY22 (A) | F26: FY21 (A) | G26: FY22 (A) | H26: FY21 (A) | I26: FY22 (A) | J26: FY21 (A) | K26: FY22 (A) | L26: FY21 (A) | M26: FY22 (A) | N26: FY21 (A) | P26: FY21 (A) | Q26: FY22 (A) | R26: FY21 (A) | S26: FY22 (A) | T26: FY21 (A) | V26: FY21 (A) | W26: FY22 (A) | X26: FY21 (A) | Y26: FY22 (A) | Z26: FY21 (A) | AA26: FY22 (A) | AB26: FY21 (A) | AC26: FY22 (A) | AD26: FY21 (A) | AE26: FY22 (A)
A27: Net Interest Margin | B27: 0.06405228 | C27: 0.070341551 | D27: 0.11044958 | E27: 0.020048864 | F27: 0.067360094 | G27: 0.077784404 | H27: 0.07981339 | I27: 0.093346718 | J27: 0.03705768 | K27: 0.038694374 | L27: 0.034738658 | M27: 0.033040729 | N27: 0.080684273 | P27: 0.086683745 | Q27: 0.089223159 | R27: 0.083177663 | S27: 0.076822643 | T27: 0.06446223 | V27: 0.022871972 | W27: 0.021966504 | X27: 0.027050947 | Y27: 0.026821934 | Z27: 0.045522274 | AA27: 0.047576049 | AB27: 0.028024255 | AC27: 0.032414767 | AD27: 0.028662269 | AE27: 0.024268976
A28: Capitalization
A29: Leverage (Debt/TNW) | B29: 2.6558292 | C29: 2.8526155 | D29: 1.1498408 | E29: 0.84844894 | F29: 3.1361802 | G29: 2.5884187 | H29: 1.5359247 | I29: 0.62579032 | J29: 5.2638255 | K29: 5.151398 | L29: 4.5256136 | M29: 5.4352943 | N29: 2.7053377 | P29: 1.5911007 | Q29: 1.9235749 | R29: 3.0514474 | S29: 3.2747991 | T29: 2.9719712 | V29: 10.129056 | W29: 9.065321 | X29: 4.057311 | Y29: 4.155318 | Z29: 4.951896 | AA29: 4.335297 | AB29: 5.2386352 | AC29: 6.1548886 | AD29: 6.6981633 | AE29: 5.4083714
A30: CAR | B30: 0.5438 | C30: 0.5193 | D30: 0.7363 | E30: 0.8561 | F30: 0.5003 | G30: 0.5157 | H30: 0.5701 | I30: 0.998 | K30: 0.257 | L30: 0.3654 | M30: 0.3566 | N30: 0.4808 | P30: 0.7151 | Q30: 0.5587 | R30: 0.4124 | S30: 0.3685 | T30: 0.492 | V30: 0.1528 | W30: 0.1808 | X30: 0.222 | Y30: 0.228 | Z30: 0.3072 | AA30: 0.3333 | AB30: 0.2133 | AC30: 0.1971 | AD30: 0.1873 | AE30: 0.234
A31: TNW/Loan Book | B31: 0.31710649 | C31: 0.30804166 | D31: 0.54905387 | E31: 0.062220189 | F31: 0.26178874 | G31: 0.29318834 | H31: 0.4569558 | I31: 0.74295674 | J31: 0.17186999 | K31: 0.17531555 | L31: 0.20554981 | M31: 0.17358782 | N31: 0.30523224 | P31: 0.46579973 | Q31: 0.40503499 | R31: 0.26779313 | S31: 0.2402326 | T31: 0.25223022 | V31: 0.088448661 | W31: 0.098241168 | X31: 0.21830841 | Y31: 0.21157419 | Z31: 0.16984928 | AA31: 0.19004661 | AB31: 0.17860195 | AC31: 0.14358698 | AD31: 0.14023363 | AE31: 0.16915074
A32: Operational Efficiency
A33: Cost to Income (on total operating income net-off interest expenses) | B33: 0.3979093 | C33: 0.42400656 | D33: 0.24300874 | E33: 0.19601891 | F33: 0.34288226 | G33: 0.36105511 | H33: 0.36206084 | I33: 0.31733533 | J33: 0.26636608 | K33: 0.30861055 | L33: 0.65761322 | M33: 0.73829929 | N33: 0.47260359 | P33: 0.40048638 | Q33: 0.44278904 | R33: 0.57518129 | S33: 0.713617 | T33: 0.38709776 | V33: 0.13004002 | W33: 0.1733421 | X33: 0.092040534 | Y33: 0.097685629 | Z33: 0.20211225 | AA33: 0.20669377 | AB33: 0.2767595 | AC33: 0.29223322 | AD33: 0.17649708 | AE33: 0.21255047
A34: Cost to Income (on total operating income) | B34: 0.23262356 | C34: 0.26878507 | D34: 0.16025071 | E34: 0.14428494 | F34: 0.15916467 | G34: 0.20254936 | H34: 0.23038246 | I34: 0.23468591 | J34: 0.10605839 | K34: 0.13684093 | L34: 0.21299491 | M34: 0.24644627 | N34: 0.28590809 | P34: 0.26726988 | Q34: 0.29616833 | R34: 0.33560837 | S34: 0.38878113 | T34: 0.22139581 | V34: 0.035345629 | W34: 0.050172523 | X34: 0.03734205 | Y34: 0.043219488 | Z34: 0.083322412 | AA34: 0.096164131 | AB34: 0.10429518 | AC34: 0.12501527 | AD34: 0.057504098 | AE34: 0.071834153
A35: Operating Expenses: Avg. Assets | B35: 0.030884953 | C35: 0.035093559 | D35: 0.022533689 | E35: 0.021205045 | F35: 0.022047604 | G35: 0.027587917 | H35: 0.032216203 | I35: 0.034451231 | J35: 0.011082195 | K35: 0.013038719 | L35: 0.023414232 | M35: 0.025001528 | N35: 0.058733227 | P35: 0.039724678 | Q35: 0.046685363 | R35: 0.052641275 | S35: 0.054881145 | T35: 0.034758074 | V35: 0.0031010153 | W35: 0.0040774721 | X35: 0.0032939873 | Y35: 0.0034302802 | Z35: 0.0093963286 | AA35: 0.010185572 | AB35: 0.009505018 | AC35: 0.010902066 | AD35: 0.005792418 | AE35: 0.0064408547
A36: Loan Book Performance
A37: Gross NPA % | B37: 0.009760308 | C37: 0.0099102751 | D37: 0.0071656745 | E37: 0.001139516 | F37: 0.022053427 | G37: 0.01666885 | H37: 0.0048534357 | I37: 0.01279784 | J37: 0.044833617 | K37: 0.030003224 | L37: 0.017704296 | M37: 0.016565506 | N37: 0.0094552345 | P37: 0.017984041 | Q37: 0.021468473 | R37: 0.021670652 | S37: 0.035568326 | T37: 0.018169836 | V37: 0.041631705 | W37: 0.046255517 | X37: 0.023310889 | Y37: 0.022652835 | Z37: 0.041541641 | AA37: 0.074977281 | AB37: 0.0035272006 | AC37: 0.0031173815 | AD37: 0.047419576 | AE37: 0.081225336
A38: Net NPA% | B38: 0.0071010769 | C38: 0.0076253226 | D38: 0.0051532954 | E38: 0.00085069637 | F38: 0.015105245 | G38: 0.0091715072 | H38: 0.0035187639 | I38: 0.0093424865 | J38: 0.010565561 | K38: 0.015435405 | L38: 0.017399098 | M38: 0.01375028 | N38: 0.0065544325 | P38: 0.012272603 | Q38: 0.016008859 | R38: 0.01412904 | S38: 0.024374854 | T38: 0.014061384 | V38: 0.025489561 | W38: 0.026267578 | X38: 0.011155513 | Y38: 0.010352498 | Z38: 0.026810797 | AA38: 0.052778824 | AB38: 0.0021889191 | AC38: 0.0014247175 | AD38: 0.027662645 | AE38: 0.050586403
A39: Provision coverage Ratio | B39: 0.27245361 | C39: 0.23056398 | D39: 0.28083596 | E39: 0.25345818 | F39: 0.31506134 | G39: 0.44978166 | H39: 0.27499527 | I39: 0.26999504 | J39: 0.76433842 | K39: 0.48554179 | L39: 0.017238631 | M39: 0.16994511 | N39: 0.30679324 | P39: 0.31758366 | Q39: 0.25430846 | R39: 0.34801036 | S39: 0.31470335 | T39: 0.22611387 | V39: 0.38773678 | W39: 0.43212011 | X39: 0.52144628 | Y39: 0.54299326 | Z39: 0.3546043 | AA39: 0.29606912 | AB39: 0.37941744 | AC39: 0.54297622 | AD39: 0.41664082 | AE39: 0.37720907
A40: Credit Cost | B40: 0.0053922791 | C40: 0.0027087336 | D40: 0.0015941467 | E40: 0.00122495 | F40: 0.022627968 | G40: 0.021187348 | H40: 0.0055741743 | I40: 0.0074827712 | J40: 0.005634648 | K40: 0.0087458944 | L40: 0.0047416153 | M40: 0.0007692832 | N40: 0.0068274611 | P40: 0.011329928 | Q40: 0.0050925611 | R40: 0.0052850316 | S40: 0.012253557 | T40: 0.011890672 | V40: 0.0059537626 | W40: 0.0082303346 | X40: 0.0062115414 | Y40: 0.0036225182 | Z40: 0.0067508517 | AA40: 0.019513012 | AB40: 0.0079911829 | AC40: 0.0044861326 | AD40: 0.013091177 | AE40: 0.0095134849
A42: Return Indicators
A43: Pre Provisioning operating profit (PPOP)margin | B43: 0.046993139 | C43: 0.047793015 | D43: 0.074633807 | E43: 0.092149561 | F43: 0.043879408 | G43: 0.049996084 | H43: 0.057233592 | I43: 0.074853602 | J43: 0.030527531 | K43: 0.029250418 | L43: 0.013585957 | M43: 0.010468559 | N43: 0.067660211 | P43: 0.062325498 | Q43: 0.062911371 | R43: 0.040850603 | S43: 0.02318576 | T43: 0.057277413 | V43: 0.020747994 | W43: 0.019583731 | X43: 0.032542306 | Y43: 0.031740055 | Z43: 0.038635463 | AA43: 0.040437716 | AB43: 0.0248557 | AC43: 0.026414862 | AD43: 0.027276413 | AE43: 0.023932373
A44: RoA | B44: 0.034840981 | C44: 0.035714867 | D44: 0.057295496 | E44: 0.066717788 | F44: 0.010335296 | G44: 0.024773516 | H44: 0.039837688 | I44: 0.053669983 | J44: 0.019271329 | K44: 0.016703839 | L44: 0.0069663533 | M44: 0.0078881264 | N44: 0.046724093 | P44: 0.041011791 | Q44: 0.045197115 | R44: 0.028322437 | S44: 0.010137833 | T44: 0.033199266 | V44: 0.012087112 | W44: 0.0093320129 | X44: 0.022034234 | Y44: 0.022743274 | Z44: 0.023613982 | AA44: 0.015724547 | AB44: 0.01309215 | AC44: 0.016429154 | AD44: 0.012319291 | AE44: 0.012000425
A45: RoE | B45: 0.12868345 | C45: 0.1369658 | D45: 0.12236142 | E45: 0.13237241 | F45: 0.045280718 | G45: 0.099024263 | H45: 0.10656744 | I45: 0.11368587 | J45: 0.12862959 | K45: 0.10436415 | L45: 0.036777675 | M45: 0.047822798 | N45: 0.16674771 | P45: 0.097884056 | Q45: 0.12759249 | R45: 0.12323632 | S45: 0.046360386 | T45: 0.13914555 | V45: 0.141257 | W45: 0.10122242 | X45: 0.12339444 | Y45: 0.12000141 | Z45: 0.14955176 | AA45: 0.089194368 | AB45: 0.078019514 | AC45: 0.11110746 | AD45: 0.1100513 | AE45: 0.088057888
A46: Spread
A47: Yields (A) | B47: 0.13058609 | C47: 0.12755977 | D47: 0.16925303 | E47: 0.027531305 | F47: 0.1487194 | G47: 0.14408497 | H47: 0.14576477 | I47: 0.14345597 | J47: 0.10445958 | K47: 0.096226114 | L47: 0.11654526 | M47: 0.1096521 | N47: 0.17445988 | P47: 0.14682222 | Q47: 0.15276445 | R47: 0.16079373 | S47: 0.15114951 | T47: 0.13490304 | V47: 0.08817751 | W47: 0.080555646 | X47: 0.087343269 | Y47: 0.076958205 | Z47: 0.1130007 | AA47: 0.10534063 | AB47: 0.091571954 | AC47: 0.08581404 | AD47: 0.10613722 | AE47: 0.091374548
A48: Avg. Cost of Borrowing(B) | B48: 0.077933189 | C48: 0.06636737 | D48: 0.090943536 | E48: 0.079269384 | F48: 0.099608687 | G48: 0.083910524 | H48: 0.090789206 | I48: 0.088245716 | J48: 0.074507693 | K48: 0.06364897 | L48: 0.092792663 | M48: 0.081679947 | N48: 0.12324322 | P48: 0.086853015 | Q48: 0.083305871 | R48: 0.097309789 | S48: 0.092820848 | T48: 0.092498054 | V48: 0.072408954 | W48: 0.0655991 | X48: 0.066509862 | Y48: 0.056828688 | Z48: 0.079505851 | AA48: 0.069376723 | AB48: 0.068735464 | AC48: 0.058974522 | AD48: 0.08023934 | AE48: 0.072342956
A49: Spread(A-B) | B49: 0.052652899 | C49: 0.061192398 | D49: 0.078309491 | E49: -0.051738079 | F49: 0.049110709 | G49: 0.060174445 | H49: 0.054975561 | I49: 0.055210251 | J49: 0.029951887 | K49: 0.032577144 | L49: 0.023752598 | M49: 0.027972157 | N49: 0.05121666 | P49: 0.059969208 | Q49: 0.069458582 | R49: 0.063483937 | S49: 0.058328667 | T49: 0.042404982 | V49: 0.015768556 | W49: 0.014956546 | X49: 0.020833407 | Y49: 0.020129516 | Z49: 0.033494846 | AA49: 0.035963903 | AB49: 0.022836491 | AC49: 0.026839518 | AD49: 0.025897881 | AE49: 0.019031592

Sheet EdGro Finance
E1: Rs in Crores
B2: EdGro Finance
B3: Particulars | C3: FY 24 | D3: FY 25 | E3: FY 26 | G3: Particulars | H3: FY24 (A) | I3: FY25 (A) | J3: FY26 (A)
C4: Aud | D4: Aud | E4: Aud | G4: Profitability
C5: Ind AS | D5: Ind AS | E5: Ind AS | G5: Net Interest Margin | H5: - | I5: =D11/AVERAGE(C24:D24) -> 0.037037037 | J5: =E11/AVERAGE(D24:E24) -> 0.090191657
B6: Revenue from operations | C6: 4 | D6: 48 | E6: 102 | G6: Capitalization
B7: Interest Income | C7: 3 | D7: 32 | E7: 74 | G7: Leverage (Debt/NOF) | H7: =C22/C21 -> 1.4579439 | I7: =D22/D21 -> 1.9557522 | J7: =E22/E21 -> 1.2820513
B8: Treasury income | C8: 0 | D8: 0 | E8: 0 | G8: CAR | H8: 0.4737 | I8: 0.3398 | J8: 0.4502
B9: Other Operation Income | C9: 1 | D9: 16 | E9: 19 | G9: NOF/Loan Book | H9: =C21/C24 -> 0.69934641 | I9: =D21/D24 -> 0.40501792 | J9: =E21/E24 -> 0.57730263
B10: Interest expended | C10: 3 | D10: 24 | E10: 34 | G10: Operational Efficiency
B11: Net Interest Income | C11: 0 | D11: 8 | E11: =E7-E10 -> 40 | G11: Cost to Income (on total operating income net-off interest expenses) | H11: =C15/(C12-C10) -> 4 | I11: =D15/(D12-D10) -> 0.875 | J11: =E15/(E12-E10) -> 0.91525424
B12: Total Operating Income | C12: =C7+C8+C9 -> 4 | D12: =D7+D8+D9 -> 48 | E12: =E7+E8+E9 -> 93 | G12: Cost to Income (on total operating income) | H12: =C15/C12 -> 1 | I12: =D15/D12 -> 0.4375 | J12: =E15/E12 -> 0.58064516
B13: Other income | C13: 3 | D13: 3 | E13: 9 | G13: Operating Expenses: Avg. Assets | H13: =C15/AVERAGE(C24) -> 0.026143791 | I13: =D15/AVERAGE(C23:D23) -> 0.0672 | J13: =E15/AVERAGE(D23:E23) -> 0.091216216
B14: Total Income | C14: =C12+C13 -> 7 | D14: =D12+D13 -> 51 | E14: =E12+E13 -> 102 | G14: Loan Book Performance
B15: Operating expenses | C15: 4 | D15: 21 | E15: 54 | G15: Gross NPA % | H15: - | I15: 0.0095 | J15: 0.0039
B16: Operating profit | C16: =C12-C15 -> 0 | D16: =D12-D15 -> 27 | E16: =E12-E15 -> 39 | G16: Net NPA% | H16: - | I16: 0.0039 | J16: 0.0029
B17: Pre-provisioning operating profit | C17: =C16-C10 -> -3 | D17: =D16-D10 -> 3 | E17: =E16-E10 -> 5 | G17: Provision coverage Ratio | H17: - | I17: =(I15-I16)/I15 -> 0.58947368 | J17: =(J15-J16)/J15 -> 0.25641026
B18: Provisions | C18: 1 | D18: 3 | E18: 8 | G18: Credit Cost | H18: 0.008 | I18: 0.0136 | J18: =E18/AVERAGE(D24:E24) -> 0.018038331
B19: PAT | C19: 0.31 | D19: 2 | E19: 5 | G19: Return Indicators
B20: TNW | C20: 107 | D20: 113 | E20: 351 | G20: Pre Provisioning operating profit (PPOP)margin | H20: =C17/C23 -> -0.011070111 | I20: =D17/AVERAGE(C23:D23) -> 0.0096 | J20: =E17/AVERAGE(D23:E23) -> 0.0084459459
B21: Net Owned Funds | C21: 107 | D21: 113 | E21: 351 | G21: RoA | H21: 0.0022 | I21: 0.0136 | J21: =E19/AVERAGE(D23:E23) -> 0.0084459459
B22: Total Debt | C22: 156 | D22: 221 | E22: 450 | G22: RoE | H22: 0.0053 | I22: 0.0399 | J22: =E19/AVERAGE(D20:E20) -> 0.021551724
B23: Total Assets | C23: 271 | D23: 354 | E23: 830 | G23: Spread
B24: Loans & Advances (Gross) | C24: 153 | D24: 279 | E24: 608 | G24: Yields (A) | H24: 0.0354 | I24: =D7/AVERAGE(C24:D24) -> 0.14814815 | J24: =E7/AVERAGE(D24:E24) -> 0.16685457
B25: Gross NPAs | C25: 0 | D25: 3 | G25: Avg. Cost of Borrowing(B) | H25: 0.0359 | I25: =D10/AVERAGE(C22:D22) -> 0.12732095 | J25: =E10/AVERAGE(D22:E22) -> 0.10134128
B26: Net NPAs | C26: 0 | D26: 1 | G26: Spread(A-B) | H26: =H24-H25 -> -0.0005 | I26: =I24-I25 -> 0.020827193 | J26: =J24-J25 -> 0.065513284
G27: 45992
G28: Moratorium | J28: 0.2245
G29: Non-moratorium | J29: 0.7755
G30: DPD
G31: Current | H31: - | I31: 0.9745 | J31: 0.9696
G32: 31-60 | H32: - | I32: 0.0036 | J32: 0.0041
G33: 61-90 | H33: - | I33: 0.0017 | J33: 0.0018
G34: 91-180 | H34: - | I34: 0.0052 | J34: 0.0034
G35: >180 | H35: - | I35: 0.0057 | J35: 0.0115

Sheet Hdfc Credila
E1: Rs in Crores
B2: HDFC Credila
B3: Particulars | C3: FY 24 | D3: FY 25 | E3: FY 26 | G3: Particulars | H3: FY24 (A) | I3: FY25 (A) | J3: FY26 (A)
C4: Aud | D4: Aud | E4: Aud | G4: Profitability
C5: Ind AS | D5: Ind AS | E5: Ind AS | G5: Net Interest Margin | H5: 0.037 | I5: =D11/AVERAGE(C24:D24) -> 0.036400215 | J5: =E11/AVERAGE(D24:E24) -> 0.044412926
B6: Revenue from operations | C6: 2771.04 | D6: 4726 | E6: 6061.49 | G6: Capitalization
B7: Interest Income | C7: 2535.35 | D7: 4165.57 | E7: 5690.4 | G7: Leverage (Debt/NOF) | H7: =C22/C21 -> 5.2261851 | I7: =D22/D21 -> 4.5093908 | J7: =E22/E21 -> 4.6220485
B8: Treasury income | C8: 0 | D8: 0 | E8: 0 | G8: CAR | H8: 0.2045 | I8: 0.2181 | J8: 0.1989
B9: Other Operation Income | C9: 235.69 | D9: 560.43 | E9: 371.09 | G9: NOF/Loan Book | H9: =C21/C24 -> 0.17671957 | I9: =D21/D24 -> 0.20665654 | J9: =E21/E24 -> 0.19590548
B10: Interest expended | C10: 1731.02 | D10: 2893.44 | E10: 3639.34 | G10: Operational Efficiency
B11: Net Interest Income | C11: 804.33 | D11: 1272.13 | E11: 2051.06 | G11: Cost to Income (on total operating income net-off interest expenses) | H11: =C15/(C12-C10) -> 0.27102363 | I11: =D15/(D12-D10) -> 0.19646833 | J11: =E15/(E12-E10) -> 0.20565613
B12: Total Operating Income | C12: =SUM(C7:C9) -> 2771.04 | D12: =SUM(D7:D9) -> 4726 | E12: =SUM(E7:E9) -> 6061.49 | G12: Cost to Income (on total operating income) | H12: =C15/C12 -> 0.10171993 | I12: =D15/D12 -> 0.076182818 | J12: =E15/E12 -> 0.082179464
B13: Other income | C13: =C14-C12 -> 0 | D13: =D14-D12 -> 0 | E13: =E14-E12 -> 5.54 | G13: Operating Expenses: Avg. Assets | H13: =C15/AVERAGE(16403,C23) -> 0.011767422 | I13: =D15/AVERAGE(C23:D23) -> 0.0090435715 | J13: =E15/AVERAGE(D23:E23) -> 0.0094528709
B14: Total Income | C14: 2771.04 | D14: 4726 | E14: 6067.03 | G14: Loan Book Performance
B15: Operating expenses | C15: 281.87 | D15: 360.04 | E15: 498.13 | G15: Gross NPA % | H15: =C25/C24 -> 0.00076133848 | I15: =D25/D24 -> 0.0019151448 | J15: =E25/E24 -> 0.0026000147
B16: Operating profit | C16: =C12-C15 -> 2489.17 | D16: =D12-D15 -> 4365.96 | E16: =E12-E15 -> 5563.36 | G16: Net NPA% | H16: =C26/C24 -> 0.00034732077 | I16: =D26/D24 -> 0.00067010888 | J16: =E26/E24 -> 0.00099992972
B17: Pre-provisioning operating profit | C17: =C14-C15-C10 -> 758.15 | D17: =D14-D15-D10 -> 1472.52 | E17: =E14-E15-E10 -> 1929.56 | G17: Provision coverage Ratio | H17: =(H15-H16)/H15 -> 0.54380242 | I17: =(I15-I16)/I15 -> 0.65010015 | J17: =(J15-J16)/J15 -> 0.61541382
B18: Provisions | C18: 49.79 | D18: 146.54 | E18: 173.33 | G18: Credit Cost | H18: =C18/AVERAGE(15298,C24) -> 0.0022899745 | I18: =D18/AVERAGE(C24:D24) -> 0.0041930365 | J18: =E18/AVERAGE(D24:E24) -> 0.0037532264
B19: PAT | C19: 528.84 | D19: 989.96 | E19: 1316.3 | G19: Return Indicators
B20: TNW | C20: 4981.23 | D20: 8619.57 | E20: 9923.31 | G20: Pre Provisioning operating profit (PPOP)margin | H20: =C17/AVERAGE(16403,C23) -> 0.031651013 | I20: =D17/AVERAGE(C23:D23) -> 0.036987112 | J20: =E17/AVERAGE(D23:E23) -> 0.03661671
B21: Net Owned Funds | C21: 4981.23 | D21: 8619.57 | E21: 9923.31 | G21: RoA | H21: =C19/AVERAGE(16403,C23) -> 0.022077849 | I21: =D19/AVERAGE(C23:D23) -> 0.024866054 | J21: =E19/AVERAGE(D23:E23) -> 0.02497905
B22: Total Debt | C22: 26032.83 | D22: 38869.01 | E22: 45866.02 | G22: RoE | H22: =C19/AVERAGE(2392,C20) -> 0.14344866 | I22: =D19/AVERAGE(C20:D20) -> 0.14557379 | J22: =E19/AVERAGE(D20:E20) -> 0.14197363
B23: Total Assets | C23: 31503.84 | D23: 48119.57 | E23: 57272.75 | G23: Spread
B24: Loans & Advances (Gross) | C24: 28187.2 | D24: 41709.64 | E24: 50653.56 | G24: Yields (A) | H24: =C7/AVERAGE(15298,C24) -> 0.11660749 | I24: =D7/AVERAGE(C24:D24) -> 0.11919194 | J24: =E7/AVERAGE(D24:E24) -> 0.1232179
B25: Gross NPAs | C25: 21.46 | D25: 79.88 | E25: 131.7 | G25: Avg. Cost of Borrowing(B) | H25: =C10/AVERAGE(13655,C22) -> 0.087231779 | I25: =D10/AVERAGE(C22:D22) -> 0.089163574 | J25: =E10/AVERAGE(D22:E22) -> 0.085899303
B26: Net NPAs | C26: 9.79 | D26: 27.95 | E26: 50.65 | G26: Spread(A-B) | H26: =H24-H25 -> 0.029375711 | I26: =I24-I25 -> 0.030028367 | J26: =J24-J25 -> 0.037318602
G28: EMI | I28: 0.23
G29: Moratorium | I29: 0.77
B41: The Company received its NBFC license in 2007 and was the first financial services company established as a specialized institution for originating, holding and servicing education loans Line of activity: The Company provides education loan to Indian students to pursue higher education in India and abroad. § HDFC Credila distributes education loan products through its network at 8 locations, i.e., Mumbai, Pune, Hyderabad, Kolkata, Ahmedabad, Chennai, Bangalore and Delhi. The company has its registered office in Mumbai along with 1 Back-end office in Nashik which carries out tele calling and other operational work. § In addition to the 8 hubs and a registered office, the company has 7 HDFC Limited’s branches and 6 small branches spread across mentioned locations for business sourcing. The company also uses various channels for sourcing and marketing, which include the internet, branch network of HDFC Group and a few private sector banks, partnering with colleges, education consultants, and test preparation centers, advertising, and direct marketing. § HDFC Credila provides flexibility in terms of education loan. The credit team studies the student’s requirement and provides the customized solutions. It also provides the flexibility in repayment from India or Abroad (The amount should be equivalent to EMI in Indian rupees). § Education loan covers all of the tuition fees of the college/University, expenses including living and hostel expenses, examination fees, library/laboratory fees other necessary expenses for the course as assessed by the Company. Travel fare economy class return ticket between India and the country of study, if applicable. § The education loans are broadly classified under two heads- Unsecured loans and Secured loan.

Sheet Auxilo Finserve 
E1: Rs in Crores
B2: Auxilo Finserve
B3: Particulars | C3: FY 24 | D3: FY 25 | E3: FY 26 | G3: Particulars | H3: FY24(A) | I3: FY25(A) | J3: FY26(A)
C4: Aud | D4: Aud | E4: Aud | G4: Profitability
C5: Ind AS | D5: Ind AS | E5: Ind AS | G5: Net Interest Margin | H5: 0.051150961 | I5: =D11/AVERAGE(C24:D24) -> 0.05076908 | J5: =E11/AVERAGE(D24:E24) -> 0.045824671
B6: Revenue from operations | C6: 356.7 | D6: 528.1 | E6: 675.8 | G6: Capitalization
B7: Interest Income | C7: 312.1 | D7: 463.9 | E7: 596.3 | G7: Leverage (Debt/NOF) | H7: =C22/C21 -> 2.3867291 | I7: =D22/D21 -> 2.4632793 | J7: =E22/E21 -> 2.6122259
B8: Treasury income | C8: 0 | D8: 0 | E8: 0 | G8: CAR | H8: 0.3149 | I8: 0.3 | J8: 0.321
B9: Other Operation Income | C9: =C6-C7 -> 44.6 | D9: =D6-D7 -> 64.2 | E9: =E6-E7 -> 79.5 | G9: NOF/Loan Book | H9: =C21/C24 -> 0.34363853 | I9: =D21/D24 -> 0.32278702 | J9: =E21/E24 -> 0.30485952
B10: Interest expended | C10: 195.3 | D10: 282.2 | E10: 384.7 | G10: Operational Efficiency
B11: Net Interest Income | C11: 116.9 | D11: 181.7 | E11: 211.6 | G11: Cost to Income (on total operating income net-off interest expenses) | H11: =C15/(C12-C10) -> 0.44981413 | I11: =D15/(D12-D10) -> 0.40056934 | J11: =E15/(E12-E10) -> 0.46581931
B12: Total Operating Income | C12: =SUM(C7:C9) -> 356.7 | D12: =SUM(D7:D9) -> 528.1 | E12: =SUM(E7:E9) -> 675.8 | G12: Cost to Income (on total operating income) | H12: =C15/C12 -> 0.20353238 | I12: =D15/D12 -> 0.1865177 | J12: =E15/E12 -> 0.20065108
B13: Other income | C13: =C14-C12 -> 10.6 | D13: =D14-D12 -> 15.5 | E13: =E14-E12 -> 13.9 | G13: Operating Expenses: Avg. Assets | H13: 0.027262572 | I13: =D15/AVERAGE(C23:D23) -> 0.02395865 | J13: =E15/AVERAGE(D23:E23) -> 0.026207963
B14: Total Income | C14: 367.3 | D14: 543.6 | E14: 689.7 | G14: Loan Book Performance
B15: Operating expenses | C15: 72.6 | D15: 98.5 | E15: 135.6 | G15: Gross NPA % | H15: =C25/C24 -> 0.008743093 | I15: =D25/D24 -> 0.005257648 | J15: =E25/E24 -> 0.0036461604
B16: Operating profit | C16: =C12-C15 -> 284.1 | D16: =D12-D15 -> 429.6 | E16: =E12-E15 -> 540.2 | G16: Net NPA% | H16: =C26/C24 -> 0.0050360215 | I16: =D26/D24 -> 0.00081423752 | J16: =E26/E24 -> 0.0010128223
B17: Pre-provisioning operating profit | C17: =C14-C15-C10 -> 99.4 | D17: =D14-D15-D10 -> 162.9 | E17: =E14-E15-E10 -> 169.4 | G17: Provision coverage Ratio | H17: =(H15-H16)/H15 -> 0.424 | I17: =(I15-I16)/I15 -> 0.84513274 | J17: =(J15-J16)/J15 -> 0.72222222
B18: Provisions | C18: 6.8 | D18: 12.9 | E18: 12.7 | G18: Credit Cost | H18: 0.0029713043 | I18: =D18/AVERAGE(C24:D24) -> 0.0036044091 | J18: =E18/AVERAGE(D24:E24) -> 0.0027503465
B19: PAT | C19: 69.2 | D19: 111.9 | E19: 116.9 | G19: Return Indicators
B20: TNW | C20: 982.6 | D20: 1387.5 | E20: 1505 | G20: Pre Provisioning operating profit (PPOP)margin | H20: 0.03737469 | I20: =D17/AVERAGE(C23:D23) -> 0.039622986 | J20: =E17/AVERAGE(D23:E23) -> 0.032740626
B21: Net Owned Funds | C21: 982.6 | D21: 1387.5 | E21: 1505 | G21: RoA | H21: 0.026005085 | I21: =D19/AVERAGE(C23:D23) -> 0.027217999 | J21: =E19/AVERAGE(D23:E23) -> 0.022593738
B22: Total Debt | C22: 2345.2 | D22: 3417.8 | E22: 3931.4 | G22: RoE | H22: 0.096016949 | I22: =D19/AVERAGE(C20:D20) -> 0.094426396 | J22: =E19/AVERAGE(D20:E20) -> 0.080829732
B23: Total Assets | C23: 3363.6 | D23: 4858.9 | E23: 5489.1 | G23: Spread
B24: Loans & Advances (Gross) | C24: 2859.4 | D24: 4298.5 | E24: 4936.7 | G24: Yields (A) | H24: 0.13663242 | I24: =D7/AVERAGE(C24:D24) -> 0.12961902 | J24: =E7/AVERAGE(D24:E24) -> 0.12913635
B25: Gross NPAs | C25: 25 | D25: 22.6 | E25: 18 | G25: Avg. Cost of Borrowing(B) | H25: 0.1026412 | I25: =D10/AVERAGE(C22:D22) -> 0.097935103 | J25: =E10/AVERAGE(D22:E22) -> 0.10469167
B26: Net NPAs | C26: 14.4 | D26: 3.5 | E26: 5 | G26: Spread(A-B) | H26: =H24-H25 -> 0.033991216 | I26: =I24-I25 -> 0.031683919 | J26: =J24-J25 -> 0.024444681
G27: Prepayment Trend
G28: Prepayment % | H28: 0.15 | I28: 0.16 | J28: 0.2
G29: DPD
G30: Current | J30: 0.9898
G31: 31-60 | J31: 0.0028
G32: 61-90 | J32: 0.002
G34: Cumulative Prepayments | J34: 48.94% (May 2026) | K34: 39.46% (Aug 2026)

Sheet Avanse Financial
E1: Rs in Crores
B2: Avanse Financial
B3: Particulars | C3: FY 24 | D3: FY 25 | E3: FY 26 | G3: Particulars | H3: FY24(A) | I3: FY25(A) | J3: FY26(A)
C4: Aud | D4: Aud | E4: Aud | G4: Profitability
C5: Ind AS | D5: Ind AS | E5: Ind AS | G5: Net Interest Margin | H5: 0.0487 | I5: =D11/AVERAGE(C24:D24) -> 0.04987876 | J5: =E11/AVERAGE(D24:E24) -> 0.049047354
B6: Revenue from operations | C6: 1726.2 | D6: 2013 | E6: 2882 | G6: Capitalization
B7: Interest Income | C7: 1386.4 | D7: 1963.7 | E7: 2462.4 | G7: Leverage (Debt/NOF) | H7: =C22/C21 -> 2.8149424 | I7: =D22/D21 -> 3.5605412 | J7: =E22/E21 -> 3.0788746
B8: Treasury income | C8: 0 | D8: 0 | E8: 0 | G8: CAR | H8: 0.2752 | I8: 0.2244 | J8: 0.2673
B9: Other Operation Income | C9: 339.7 | D9: 49.3 | E9: 419.6 | G9: NOF/Loan Book | H9: =C21/C24 -> 0.28756379 | I9: =D21/D24 -> 0.23335381 | J9: =E21/E24 -> 0.29122594
B10: Interest expended | C10: 875.6 | D10: 1217 | E10: 1530 | G10: Operational Efficiency
B11: Net Interest Income | C11: 510.8 | D11: 746.7 | E11: 932.4 | G11: Cost to Income (on total operating income net-off interest expenses) | H11: =C15/(C12-C10) -> 0.36848912 | I11: =D15/(D12-D10) -> 0.49522613 | J11: =E15/(E12-E10) -> 0.32403846
B12: Total Operating Income | C12: =SUM(C7:C9) -> 1726.1 | D12: =SUM(D7:D9) -> 2013 | E12: =SUM(E7:E9) -> 2882 | G12: Cost to Income (on total operating income) | H12: =C15/C12 -> 0.18156538 | I12: =D15/D12 -> 0.19582712 | J12: =E15/E12 -> 0.15201249
B13: Other income | C13: =C14-C6 -> 2.1 | D13: =D14-D6 -> 337.8 | E13: =E14-E6 -> 6.9 | G13: Operating Expenses: Avg. Assets | H13: 0.026 | I13: =D15/AVERAGE(C23:D23) -> 0.023747346 | J13: =E15/AVERAGE(D23:E23) -> 0.019892749
B14: Total Income | C14: 1728.3 | D14: 2350.8 | E14: 2888.9 | G14: Loan Book Performance
B15: Operating expenses | C15: 313.4 | D15: 394.2 | E15: 438.1 | G15: Gross NPA % | H15: =C25/C24 -> 0.0042409769 | I15: =D25/D24 -> 0.0025545497 | J15: =E25/E24 -> 0.0036406883
B16: Operating profit | C16: =C12-C15 -> 1412.7 | D16: =D12-D15 -> 1618.8 | E16: =E12-E15 -> 2443.9 | G16: Net NPA% | H16: =C26/C24 -> 0.0012778838 | I16: =D26/D24 -> 0.00039035815 | J16: =E26/E24 -> 0.00059221864
B17: Pre-provisioning operating profit | C17: =C14-C15-C10 -> 539.3 | D17: =D14-D15-D10 -> 739.6 | E17: =E14-E15-E10 -> 920.8 | G17: Provision coverage Ratio | H17: =(H15-H16)/H15 -> 0.69868173 | I17: =(I15-I16)/I15 -> 0.84719101 | J17: =(J15-J16)/J15 -> 0.83733333
B18: Provisions | C18: 79.6 | D18: 64.7 | E18: 116.3 | G18: Credit Cost | H18: 0.0076 | I18: =D18/AVERAGE(C24:D24) -> 0.0043218907 | J18: =E18/AVERAGE(D24:E24) -> 0.0061177684
B19: PAT | C19: 342.6 | D19: 504.2 | E19: 597.9 | G19: Return Indicators
B20: TNW | C20: 3600.5 | D20: 4065 | E20: 5999.4 | G20: Pre Provisioning operating profit (PPOP)margin | H20: 0.044793131 | I20: =D17/AVERAGE(C23:D23) -> 0.044554888 | J20: =E17/AVERAGE(D23:E23) -> 0.041810644
B21: Net Owned Funds | C21: 3600.5 | D21: 4065 | E21: 5999.4 | G21: RoA | H21: 0.028457487 | I21: =D19/AVERAGE(C23:D23) -> 0.030373951 | J21: =E19/AVERAGE(D23:E23) -> 0.027148767
B22: Total Debt | C22: 10135.2 | D22: 14473.6 | E22: 18471.4 | G22: RoE | H22: 0.1180145 | I22: =D19/AVERAGE(C20:D20) -> 0.13155045 | J22: =E19/AVERAGE(D20:E20) -> 0.11881483
B23: Total Assets | C23: 14267.6 | D23: 18931.9 | E23: 25114.3 | G23: Spread
B24: Loans & Advances (Gross) | C24: 12520.7 | D24: 17419.9 | E24: 20600.5 | G24: Yields (A) | H24: 0.13212547 | I24: =D7/AVERAGE(C24:D24) -> 0.13117306 | J24: =E7/AVERAGE(D24:E24) -> 0.12953046
B25: Gross NPAs | C25: 53.1 | D25: 44.5 | E25: 75 | G25: Avg. Cost of Borrowing(B) | H25: 0.1036883 | I25: =D10/AVERAGE(C22:D22) -> 0.098907708 | J25: =E10/AVERAGE(D22:E22) -> 0.092882076
B26: Net NPAs | C26: 16 | D26: 6.8 | E26: 12.2 | G26: Spread(A-B) | H26: =H24-H25 -> 0.028437171 | I26: =I24-I25 -> 0.032265348 | J26: =J24-J25 -> 0.036648386
G27: Moratorium
G28: EMI | J28: 0.41
G29: PINT/SINT | J29: 0.59
G30: DPD
G31: Current | J31: 0.99
G32: 31-60 | J32: 0.0021
G33: 61-90 | J33: 0.0014

Sheet Kosamattam Finance
B2: Kosamattam Finance | F2: Rs in Crores
B3: Particulars | C3: FY 22 | D3: 23 | E3: 24 | F3: 25 | G3: 26 | I3: Profitability | J3: FY22 (A) | K3: FY23 (A) | L3: FY24 (A) | M3: FY25 (A) | N3: FY26 (A)
C4: Aud | D4: Aud | E4: Aud | F4: Aud | G4: Aud | I4: Net Interest Margin | J4: =C11/AVERAGE(C24:C24) -> 0.058619837 | K4: =D11/AVERAGE(C24:D24) -> 0.073271529 | L4: =E11/AVERAGE(D24:E24) -> 0.066452929 | M4: =F11/AVERAGE(E24:F24) -> 0.063682842 | N4: =G11/AVERAGE(F24:G24) -> 0.070690673
C5: Ind AS | D5: Ind AS | E5: Ind AS | F5: Ind AS | G5: Ind AS | I5: Capitalization
B6: Revenue from operations | C6: 610 | D6: 765 | E6: 859 | F6: 900 | G6: 1128 | I6: Leverage (Debt/NOF) | J6: =C22/C21 -> 6.0372093 | K6: =D22/D21 -> 6.1222076 | L6: =E22/E21 -> 5.4835526 | M6: =F22/F21 -> 5.0439351 | N6: =G22/G21 -> 6.4901593
B7: Interest Income | C7: 606 | D7: 761 | E7: 854 | F7: 894 | G7: 1107 | I7: CAR | J7: 0.1865 | K7: 0.1771 | L7: 0.1842 | M7: 0.1878 | N7: 19,23%
B8: Treasury income | C8: 0 | D8: 0 | E8: 0 | F8: 0 | I8: NOF/Loan Book | J8: =C21/C24 -> 0.159535 | K8: =D21/D24 -> 0.15498982 | L8: =E21/E24 -> 0.16942226 | M8: =F21/F24 -> 0.18158169 | N8: =G21/G24 -> 0.13704084
B9: Other Operation Income | C9: 3 | D9: 4 | E9: 4 | F9: 6 | G9: 21 | I9: Operational Efficiency
B10: Interest expended | C10: 369 | D10: 433 | E10: 512 | F10: 539 | G10: 628 | I10: Cost to Income (on total operating income net-off interest expenses) | J10: =C15/(C12-C10) -> 0.59583333 | K10: =D15/(D12-D10) -> 0.53012048 | L10: =E15/(E12-E10) -> 0.52890173 | M10: =F15/(F12-F10) -> 0.51246537 | N10: =G15/(G12-G10) -> 0.478
B11: Net Interest Income | C11: 237 | D11: 328 | E11: 342 | F11: 355 | G11: =G7-G10 -> 479 | I11: Cost to Income (on total operating income) | J11: =C15/C12 -> 0.23481117 | K11: =D15/D12 -> 0.23006536 | L11: =E15/E12 -> 0.21328671 | M11: =F15/F12 -> 0.20555556 | N11: =G15/G12 -> 0.21187943
B12: Total Operating Income | C12: =C7+C9 -> 609 | D12: =D7+D9 -> 765 | E12: =E7+E9 -> 858 | F12: =F7+F9 -> 900 | G12: =G7+G9 -> 1128 | I12: Operating Expenses: Avg. Assets | J12: =C15/AVERAGE(C23:C23) -> 0.035369775 | K12: =D15/AVERAGE(C23:D23) -> 0.037103405 | L12: =E15/AVERAGE(D23:E23) -> 0.032020997 | M12: =F15/AVERAGE(E23:F23) -> 0.029857973 | N12: =G15/AVERAGE(F23:G23) -> 0.032536927
B13: Other income | C13: 0 | D13: 0 | E13: 1 | F13: 0 | I13: Loan Book Performance
B14: Total Income | C14: =C12+C13 -> 609 | D14: =D12+D13 -> 765 | E14: =E12+E13 -> 859 | F14: =F12+F13 -> 900 | G14: =G12+G13 -> 1128 | I14: Gross NPA % | J14: =C25/C24 -> 0.014098442 | K14: =D25/D24 -> 0.015885947 | L14: =E25/E24 -> 0.014490061 | M14: =F25/F24 -> 0.013701006 | N14: =G25/G24 -> 0.012072951
B15: Operating expenses | C15: 143 | D15: 176 | E15: 183 | F15: 185 | G15: 239 | I15: Net NPA% | J15: =C26/C24 -> 0.0086569379 | K15: =D26/D24 -> 0.0067209776 | L15: =E26/E24 -> 0.0052015605 | M15: =F26/F24 -> 0.0046826223 | N15: =G26/G24 -> 0.0048805548
B16: Operating profit | C16: =C12-C15 -> 466 | D16: =D12-D15 -> 589 | E16: =E12-E15 -> 675 | F16: =F12-F15 -> 715 | G16: =G12-G15 -> 889 | I16: Provision coverage Ratio | J16: =(J14-J15)/J14 -> 0.38596491 | K16: =(K14-K15)/K14 -> 0.57692308 | L16: =(L14-L15)/L14 -> 0.64102564 | M16: =(M14-M15)/M14 -> 0.65822785 | N16: =(N14-N15)/N14 -> 0.59574468
B17: Pre-provisioning operating profit | C17: =C16-C10 -> 97 | D17: =D16-D10 -> 156 | E17: =E16-E10 -> 163 | F17: =F16-F10 -> 176 | G17: =G16-G10 -> 261 | I17: Credit Cost | J17: =C18/AVERAGE(C24:C24) -> 0.0014840465 | K17: =D18/AVERAGE(C24:D24) -> 0.0062548866 | L17: =E18/AVERAGE(D24:E24) -> 0.0019430681 | M17: =F18/AVERAGE(E24:F24) -> 0.0010763297 | N17: =G18/AVERAGE(F24:G24) -> 0.0016233766
B18: Provisions | C18: 6 | D18: 28 | E18: 10 | F18: 6 | G18: 11 | I18: Return Indicators
B19: PAT | C19: 80 | D19: 107 | E19: 114 | F19: 127 | G19: 185 | I19: Pre Provisioning operating profit (PPOP)margin | J19: =C17/AVERAGE(C23:C23) -> 0.023992085 | K19: =D17/AVERAGE(C23:D23) -> 0.032887109 | L19: =E17/AVERAGE(D23:E23) -> 0.028521435 | M19: =F17/AVERAGE(E23:F23) -> 0.028405423 | N19: =G17/AVERAGE(F23:G23) -> 0.035531958
B20: TNW | C20: 645 | D20: 761 | E20: 912 | F20: 1047 | G20: 1067 | I20: RoA | J20: =C19/AVERAGE(C23:C23) -> 0.019787287 | K20: =D19/AVERAGE(C23:D23) -> 0.022557184 | L20: =E19/AVERAGE(D23:E23) -> 0.019947507 | M20: =F19/AVERAGE(E23:F23) -> 0.020497095 | N20: =G19/AVERAGE(F23:G23) -> 0.025185488
B21: Net Owned Funds | C21: 645 | D21: 761 | E21: 912 | F21: 1047 | G21: 1067 | I21: RoE | J21: =C19/AVERAGE(C20:C20) -> 0.12403101 | K21: =D19/AVERAGE(C20:D20) -> 0.15220484 | L21: =E19/AVERAGE(D20:E20) -> 0.13628213 | M21: =F19/AVERAGE(E20:F20) -> 0.12965799 | N21: =G19/AVERAGE(F20:G20) -> 0.17502365
B22: Total Debt | C22: 3894 | D22: 4659 | E22: 5001 | F22: 5281 | G22: 6925 | I22: Spread
B23: Total Assets | C23: 4043 | D23: 5444 | E23: 5986 | F23: 6406 | G23: 8285 | I23: Yields (A) | J23: =C7/AVERAGE(C24:C24) -> 0.1498887 | K23: =D7/AVERAGE(C24:D24) -> 0.16999888 | L23: =E7/AVERAGE(D24:E24) -> 0.16593802 | M23: =F7/AVERAGE(E24:F24) -> 0.16037313 | N23: =G7/AVERAGE(F24:G24) -> 0.16337072
B24: Loans & Advances (Gross) | C24: 4043 | D24: 4910 | E24: 5383 | F24: 5766 | G24: 7786 | I24: Avg. Cost of Borrowing(B) | J24: =C10/AVERAGE(C22:C22) -> 0.094761171 | K24: =D10/AVERAGE(C22:D22) -> 0.10125102 | L24: =E10/AVERAGE(D22:E22) -> 0.10600414 | M24: =F10/AVERAGE(E22:F22) -> 0.10484342 | N24: =G10/AVERAGE(F22:G22) -> 0.10290021
B25: Gross NPAs | C25: 57 | D25: 78 | E25: 78 | F25: 79 | G25: 94 | I25: Spread(A-B) | J25: =J23-J24 -> 0.055127525 | K25: =K23-K24 -> 0.06874786 | L25: =L23-L24 -> 0.059933875 | M25: =M23-M24 -> 0.055529712 | N25: =N23-N24 -> 0.060470507
B26: Net NPAs | C26: 35 | D26: 33 | E26: 28 | F26: 27 | G26: 38

Sheet Muthoot MCred
B2: Muthoot MCred (erstwhile Muthootu Mini Financiers) | F2: Rs in Crores
B3: Particulars | C3: FY 22 | D3: 23 | E3: 24 | F3: 25 | G3: 26 | I3: Profitability | J3: FY22 (A) | K3: FY23 (A) | L3: FY24 (A) | M3: FY25 (A) | N3: FY26 (A)
C4: Aud | D4: Aud | E4: Aud | F4: Aud | G4: Aud | I4: Net Interest Margin | J4: =C11/AVERAGE(C24:C24) -> 0.075788422 | K4: =D11/AVERAGE(C24:D24) -> 0.081921623 | L4: =E11/AVERAGE(D24:E24) -> 0.08311229 | M4: =F11/AVERAGE(E24:F24) -> 0.090541422 | N4: =G11/AVERAGE(F24:G24) -> 0.095848426
C5: Ind AS | D5: Ind AS | E5: Ind AS | F5: Ind AS | G5: Ind AS | I5: Capitalization
B6: Revenue from operations | C6: 428.952 | D6: 544 | E6: 672 | F6: 815 | G6: =G14 -> 1113 | I6: Leverage (Debt/NOF) | J6: =C22/C21 -> 4.7529241 | K6: =D22/D21 -> 5.1559486 | L6: =E22/E21 -> 5.1084165 | M6: =F22/F21 -> 5.1681305 | N6: =G22/G21 -> 5.4020708
B7: Interest Income | C7: 413.0192 | D7: 519 | E7: 627 | F7: 744 | G7: 1046 | I7: CAR | J7: 0.2165 | K7: 0.2282 | L7: 0.2386 | M7: 0.2138 | N7: 0.1812
B8: Treasury income | C8: 0 | D8: 0 | E8: 0 | F8: 0 | G8: 0 | I8: NOF/Loan Book | J8: =C21/C24 -> 0.22320518 | K8: =D21/D24 -> 0.19062213 | L8: =E21/E24 -> 0.19897814 | M8: =F21/F24 -> 0.19241912 | N8: =G21/G24 -> 0.1749434
B9: Other Operation Income | C9: 15.9328 | D9: 24 | E9: 42 | F9: 67 | G9: 63 | I9: Operational Efficiency
B10: Interest expended | C10: 223.6539 | D10: 283 | E10: 345 | F10: 398 | G10: 530 | I10: Cost to Income (on total operating income net-off interest expenses) | J10: =C15/(C12-C10) -> 0.68143592 | K10: =D15/(D12-D10) -> 0.69615385 | L10: =E15/(E12-E10) -> 0.64506173 | M10: =F15/(F12-F10) -> 0.66343826 | N10: =G15/(G12-G10) -> 0.57512953
B11: Net Interest Income | C11: 189.3653 | D11: 236 | E11: 282 | F11: 347 | G11: =G7-G10 -> 516 | I11: Cost to Income (on total operating income) | J11: =C15/C12 -> 0.32613789 | K11: =D15/D12 -> 0.33333333 | L11: =E15/E12 -> 0.31240658 | M11: =F15/F12 -> 0.3378545 | N11: =G15/G12 -> 0.30027051
B12: Total Operating Income | C12: 428.952 | D12: =SUM(D7:D9) -> 543 | E12: =SUM(E7:E9) -> 669 | F12: =SUM(F7:F9) -> 811 | G12: =SUM(G7:G9) -> 1109 | I12: Operating Expenses: Avg. Assets | J12: =C15/AVERAGE(C23:C23) -> 0.043301161 | K12: =D15/AVERAGE(C23:D23) -> 0.051066453 | L12: =E15/AVERAGE(D23:E23) -> 0.051137754 | M12: =F15/AVERAGE(E23:F23) -> 0.059077188 | N12: =G15/AVERAGE(F23:G23) -> 0.053481089
B13: Other income | C13: 1.2939 | D13: 1 | E13: 2 | F13: 4 | G13: 4 | I13: Loan Book Performance
B14: Total Income | C14: 430.2459 | D14: =D12+D13 -> 544 | E14: =E12+E13 -> 671 | F14: =F12+F13 -> 815 | G14: =G12+G13 -> 1113 | I14: Gross NPA % | J14: =C25/C24 -> 0.0061088497 | K14: =D25/D24 -> 0.0042905302 | L14: =E25/E24 -> 0.0087993188 | M14: =F25/F24 -> 0.0084500241 | N14: =G25/G24 -> 0.0061886792
B15: Operating expenses | C15: 139.8975 | D15: 181 | E15: 209 | F15: 274 | G15: 333 | I15: Net NPA% | J15: =C26/C24 -> 0.0051984616 | K15: =D26/D24 -> 0.0036775973 | L15: =E26/E24 -> 0.0070962248 | M15: =F26/F24 -> 0.0050700145 | N15: =G26/G24 -> 0.0025660377
B16: Operating profit | C16: 289.0545 | D16: =D12-D15 -> 362 | E16: =E12-E15 -> 460 | F16: =F12-F15 -> 537 | G16: =G12-G15 -> 776 | I16: Provision coverage Ratio | J16: =(J14-J15)/J14 -> 0.14902775 | K16: =(K14-K15)/K14 -> 0.14285714 | L16: =(L14-L15)/L14 -> 0.19354839 | M16: =(M14-M15)/M14 -> 0.4 | N16: =(N14-N15)/N14 -> 0.58536585
B17: Pre-provisioning operating profit | C17: 66.6945 | D17: =D14-D15-D10 -> 80 | E17: =E14-E15-E10 -> 117 | F17: =F14-F15-F10 -> 143 | G17: =G14-G15-G10 -> 250 | I17: Credit Cost | J17: =C18/AVERAGE(C24:C24) -> 0.0029090237 | K17: =D18/AVERAGE(C24:D24) -> -0.00069425104 | L17: =E18/AVERAGE(D24:E24) -> 0.002063071 | M17: =F18/AVERAGE(E24:F24) -> 0.003652968 | N17: =G18/AVERAGE(F24:G24) -> 0.0020432804
B18: Provisions | C18: 7.2685 | D18: -2 | E18: 7 | F18: 14 | G18: 11 | I18: Return Indicators
B19: PAT | C19: 46.294 | D19: 67 | E19: 78 | F19: 94 | G19: 177 | I19: Pre Provisioning operating profit (PPOP)margin | J19: =C17/AVERAGE(C23:C23) -> 0.020643323 | K19: =D17/AVERAGE(C23:D23) -> 0.022570808 | L19: =E17/AVERAGE(D23:E23) -> 0.028627355 | M19: =F17/AVERAGE(E23:F23) -> 0.030832255 | N19: =G17/AVERAGE(F23:G23) -> 0.040150968
B20: TNW | C20: 557.7015 | D20: 622 | E20: 701 | F20: 797 | G20: 1159 | I20: RoA | J20: =C19/AVERAGE(C23:C23) -> 0.014328948 | K20: =D19/AVERAGE(C23:D23) -> 0.018903052 | L20: =E19/AVERAGE(D23:E23) -> 0.019084903 | M20: =F19/AVERAGE(E23:F23) -> 0.020267357 | N20: =G19/AVERAGE(F23:G23) -> 0.028426885
B21: Net Owned Funds | C21: 557.7015 | D21: 622 | E21: 701 | F21: 797 | G21: 1159 | I21: RoE | J21: =C19/AVERAGE(C20:C20) -> 0.083008563 | K21: =D19/AVERAGE(C20:D20) -> 0.11358806 | L21: =E19/AVERAGE(D20:E20) -> 0.11791383 | M21: =F19/AVERAGE(E20:F20) -> 0.12550067 | N21: =G19/AVERAGE(F20:G20) -> 0.1809816
B22: Total Debt | C22: 2650.7129 | D22: 3207 | E22: 3581 | F22: 4119 | G22: 6261 | I22: Spread
B23: Total Assets | C23: 3230.8025 | D23: 3858 | E23: 4316 | F23: 4960 | G23: 7493 | I23: Yields (A) | J23: =C7/AVERAGE(C24:C24) -> 0.16529994 | K23: =D7/AVERAGE(C24:D24) -> 0.18015815 | L23: =E7/AVERAGE(D24:E24) -> 0.18479222 | M23: =F7/AVERAGE(E24:F24) -> 0.19412916 | N23: =G7/AVERAGE(F24:G24) -> 0.19429739
B24: Loans & Advances (Gross) | C24: 2498.6046 | D24: 3263 | E24: 3523 | F24: 4142 | G24: 6625 | I24: Avg. Cost of Borrowing(B) | J24: =C10/AVERAGE(C22:C22) -> 0.084375 | K24: =D10/AVERAGE(C22:D22) -> 0.096624742 | L24: =E10/AVERAGE(D22:E22) -> 0.10164997 | M24: =F10/AVERAGE(E22:F22) -> 0.10337662 | N24: =G10/AVERAGE(F22:G22) -> 0.10211946
B25: Gross NPAs | C25: 15.2636 | D25: 14 | E25: 31 | F25: 35 | G25: 41 | I25: Spread(A-B) | J25: =J23-J24 -> 0.080924944 | K25: =K23-K24 -> 0.083533403 | L25: =L23-L24 -> 0.083142249 | M25: =M23-M24 -> 0.090752535 | N25: =N23-N24 -> 0.09217793
B26: Net NPAs | C26: 12.9889 | D26: 12 | E26: 25 | F26: 21 | G26: 17
B28: The company is primarily into the business of lending against security of gold jewelry which is 97% of standalone loan book. Based on wide & long industry experience, the company has designed an appropriate assessment and underwriting methodology. Assessing the purity of gold, fixing the sum that can be lent against a gram of gold, and determining appropriate LTV ratios are critical aspects in the assessment process. Outreach: The nature of the gold loan business results in high operating cost. With a network of over 800 branches as on March 31st, 2022, the company incurs substantial branch operating cost as proximity to the customer plays a key role in gold loan financing. This is partly offset by growing per branch book size of Rs 3.07 crores as of March 2022 amongst peers in the industry. Around 15% of the gold loan customers transact online in MFL. Assets Under Management: Gross Retail Assets (AUM) stood at Rs. 2499 crores in FY22 as against Rs. 1994 crores in FY21 with a growth of ~ 25.29%. As on March 31, 2022, gold loans constituted around 97% of the portfolio. Sourcing: Generally All GL-NBFCs, including Muthoottu Mini work on walk in for which there is centralized advertisement campaigning. Portfolio features: MMFL’s focussing on gold loans with shorter tenor, average LTV of around 65% and average ticket size of about Rs. 50000. The company’s gold loan portfolio is well insulated against gold price fluctuation due to short tenor or loans and comfortable LTV. In gold loan companies generally, people close their loans when they have liquidity on hand and avail again when required in times of need thus reducing the overall tenor.
B38: The company has a small microfinance book. It comprises of just 2.58% of the overall portfolio and hence is materially insignificant in terms of its impact on the Balance Sheet. The yield is 18.80% and tenure max 24 months

Sheet Muthoot Fincorp
B2: Muthoot Fincorp | F2: Rs in Crores
B3: Particulars | C3: FY 22 | D3: FY 23 | E3: FY 24 | F3: FY 25 | G3: FY 26 | I3: Profitability | J3: FY22 (A) | K3: FY23 (A) | L3: FY24 (A) | M3: FY25 (A) | N3: FY26 (A)
C4: Aud | D4: Aud | E4: Aud | F4: Aud | G4: Aud | I4: Net Interest Margin | J4: =C11/AVERAGE(C24:C24) -> 0.08881743 | K4: =D11/AVERAGE(C24:D24) -> 0.09931591 | L4: =E11/AVERAGE(D24:E24) -> 0.097946754 | M4: =F11/AVERAGE(E24:F24) -> 0.11122183 | N4: =G11/AVERAGE(F24:G24) -> 0.1295156
C5: Ind AS | D5: Ind AS | E5: Ind AS | F5: Ind AS | G5: Ind AS | I5: Capitalization
B6: Revenue from operations | C6: 3326.336 | D6: 3469.8253 | E6: 4011 | F6: 5540 | G6: 8364 | I6: Leverage (Debt/NOF) | J6: =C22/C21 -> 5.1354577 | K6: =D22/D21 -> 4.5782216 | L6: =E22/E21 -> 4.7842044 | M6: =F22/F21 -> 5.3752599 | N6: =G22/G21 -> 6.5292708
B7: Interest Income | C7: 3174.0742 | D7: 3304.8309 | E7: 3715 | F7: 4936 | G7: 7728 | I7: CAR | J7: 0.1942 | K7: 0.2134
B8: Treasury income | C8: 0 | D8: 0 | E8: 0 | F8: 0 | G8: 0 | I8: NOF/Loan Book | J8: =C21/C24 -> 0.19912639 | K8: =D21/D24 -> 0.22137398 | L8: =E21/E24 -> 0.20102732 | M8: =F21/F24 -> 0.18678161 | N8: =G21/G24 -> 0.14458901
B9: Other Operation Income | C9: 152.2618 | D9: 164.9944 | E9: 177 | F9: 273 | G9: 462 | I9: Operational Efficiency
B10: Interest expended | C10: 1635.4779 | D10: 1571.3255 | E10: 1805 | F10: 2313 | G10: 3069 | I10: Cost to Income (on total operating income net-off interest expenses) | J10: =C15/(C12-C10) -> 0.68040127 | K10: =D15/(D12-D10) -> 0.64652996 | L10: =E15/(E12-E10) -> 0.66890273 | M10: =F15/(F12-F10) -> 0.68059392 | N10: =G15/(G12-G10) -> 0.55711775
B11: Net Interest Income | C11: 1538.5963 | D11: 1733.5054 | E11: 1910 | F11: 2623 | G11: 4659 | I11: Cost to Income (on total operating income) | J11: =C15/C12 -> 0.34586464 | K11: =D15/D12 -> 0.35374605 | L11: =E15/E12 -> 0.35868448 | M11: =F15/F12 -> 0.37838357 | N11: =G15/G12 -> 0.34835165
B12: Total Operating Income | C12: 3326.336 | D12: 3469.8253 | E12: =E7+E9 -> 3892 | F12: =F7+F9 -> 5209 | G12: =G7+G9 -> 8190 | I12: Operating Expenses: Avg. Assets | J12: =C15/AVERAGE(C23:C23) -> 0.050230244 | K12: =D15/AVERAGE(C23:D23) -> 0.052676566 | L12: =E15/AVERAGE(D23:E23) -> 0.055495924 | M12: =F15/AVERAGE(E23:F23) -> 0.066339066 | N12: =G15/AVERAGE(F23:G23) -> 0.066750895
B13: Other income | C13: 1.5805 | D13: 21.4383 | E13: 119 | F13: 331 | G13: 174 | I13: Loan Book Performance
B14: Total Income | C14: 3327.9165 | D14: 3491.2636 | E14: =E12+E13 -> 4011 | F14: =F12+F13 -> 5540 | G14: =G12+G13 -> 8364 | I14: Gross NPA % | J14: =C25/C24 -> 0.028839636 | K14: =D25/D24 -> 0.021131349 | L14: =E25/E24 -> 0.016390381 | M14: =F25/F24 -> 0.020037279 | N14: =G25/G24 -> 0.010304592
B15: Operating expenses | C15: 1150.462 | D15: 1227.437 | E15: 1396 | F15: 1971 | G15: 2853 | I15: Net NPA% | J15: =C26/C24 -> 0.015695999 | K15: =D26/D24 -> 0.0058123205 | L15: =E26/E24 -> 0.0064907775 | M15: =F26/F24 -> 0.012892203 | N15: =G26/G24 -> 0.0056935033
B16: Operating profit | C16: 2175.874 | D16: 2242.3883 | E16: =E12-E15 -> 2496 | F16: =F12-F15 -> 3238 | G16: =G12-G15 -> 5337 | I16: Provision coverage Ratio | J16: =(J14-J15)/J14 -> 0.45574907 | K16: =(K14-K15)/K14 -> 0.72494324 | L16: =(L14-L15)/L14 -> 0.6039886 | M16: =(M14-M15)/M14 -> 0.35658915 | N16: =(N14-N15)/N14 -> 0.44747899
B17: Pre-provisioning operating profit | C17: 541.9766 | D17: 692.5011 | E17: =E14-E15-E10 -> 810 | F17: =F14-F15-F10 -> 1256 | G17: =G14-G15-G10 -> 2442 | I17: Credit Cost | J17: =C18/AVERAGE(C24:C24) -> 0.0041290102 | K17: =D18/AVERAGE(C24:D24) -> 0.0038483119 | L17: =E18/AVERAGE(D24:E24) -> 0.0015384307 | M17: =F18/AVERAGE(E24:F24) -> 0.0047066805 | N17: =G18/AVERAGE(F24:G24) -> 0.0071999444
B18: Provisions | C18: 71.5274 | D18: 67.1702 | E18: 30 | F18: 111 | G18: 259
B19: PAT | C19: 346.8513 | D19: 459.8108 | E19: 563 | F19: 787 | G19: 1640 | I19: Return Indicators
B20: TNW | C20: 3449.4933 | D20: 3893.0345 | E20: 4305 | F20: 4810 | G20: 6679 | I20: Pre Provisioning operating profit (PPOP)margin | J20: =C17/AVERAGE(C23:C23) -> 0.023663204 | K20: =D17/AVERAGE(C23:D23) -> 0.029719309 | L20: =E17/AVERAGE(D23:E23) -> 0.032200357 | M20: =F17/AVERAGE(E23:F23) -> 0.042273905 | N20: =G17/AVERAGE(F23:G23) -> 0.057134835
B21: Net Owned Funds | C21: 3449.4933 | D21: 3893.0345 | E21: 4305 | F21: 4810 | G21: 6679 | I21: RoA | J21: =C19/AVERAGE(C23:C23) -> 0.015143851 | K21: =D19/AVERAGE(C23:D23) -> 0.019733195 | L21: =E19/AVERAGE(D23:E23) -> 0.022381236 | M21: =F19/AVERAGE(E23:F23) -> 0.026488506 | N21: =G19/AVERAGE(F23:G23) -> 0.038370651
B22: Total Debt | C22: 17714.727 | D22: 17823.175 | E22: 20596 | F22: 25855 | G22: 43609 | I22: RoE | J22: =C19/AVERAGE(C20:C20) -> 0.10055138 | K22: =D19/AVERAGE(C20:D20) -> 0.12524591 | L22: =E19/AVERAGE(D20:E20) -> 0.13735 | M22: =F19/AVERAGE(E20:F20) -> 0.17268239 | N22: =G19/AVERAGE(F20:G20) -> 0.28549047
B23: Total Assets | C23: 22903.771 | D23: 23699.001 | E23: 26611 | F23: 32811 | G23: 52671 | I23: Spread
B24: Loans & Advances (Gross) | C24: 17323.135 | D24: 17585.782 | E24: 21415 | F24: 25752 | G24: 46193 | I24: Yields (A) | J24: =C7/AVERAGE(C24:C24) -> 0.18322747 | K24: =D7/AVERAGE(C24:D24) -> 0.18934022 | L24: =E7/AVERAGE(D24:E24) -> 0.190509 | M24: =F7/AVERAGE(E24:F24) -> 0.20929887 | N24: =G7/AVERAGE(F24:G24) -> 0.21483077
B25: Gross NPAs | C25: 499.5929 | D25: 371.6113 | E25: 351 | F25: 516 | G25: 476 | I25: Avg. Cost of Borrowing(B) | J25: =C10/AVERAGE(C22:C22) -> 0.092323066 | K25: =D10/AVERAGE(C22:D22) -> 0.088430967 | L25: =E10/AVERAGE(D22:E22) -> 0.093963497 | M25: =F10/AVERAGE(E22:F22) -> 0.099588814 | N25: =G10/AVERAGE(F22:G22) -> 0.088362317
B26: Net NPAs | C26: 271.9039 | D26: 102.2142 | E26: 139 | F26: 332 | G26: 263 | I26: Spread(A-B) | J26: =J24-J25 -> 0.090904407 | K26: =K24-K25 -> 0.10090925 | L26: =L24-L25 -> 0.096545505 | M26: =M24-M25 -> 0.10971006 | N26: =N24-N25 -> 0.12646846
B28: The company is primarily into the business of lending against security of gold jewelry which is 97% of standalone loan book in March 2021. In addition, the company has vehicle loan, corporate loan to NBFC-MFIs which constitute balance of standalone loan book. Based on wide & long industry experience, the company has designed an appropriate assessment and underwriting methodology. Assessing the purity of gold, fixing the sum that can be lent against a gram of gold, and determining appropriate LTV ratios are critical aspects in the assessment process.

Sheet Muthoot Finance
B2: Muthoot Finance | K2: Rs in Crores
B3: Particulars | C3: FY17 | D3: FY18 | E3: FY 19 | F3: FY20 | G3: FY 21 | H3: FY 22 | I3: FY 23 | J3: FY 24 | K3: FY 25 | L3: FY 26 | O3: FY22 (A) | P3: FY23 (A) | Q3: FY24 (A) | R3: FY25 (A) | S3: FY26 (A)
C4: Aud | D4: Aud. | E4: Aud. | F4: Aud. | G4: Aud | H4: Aud | I4: Aud | J4: Aud | K4: Aud | L4: Aud | N4: Profitability | U4: Time Period Particulars | W4: Latest Completed Quarter [A] | X4: Previous Completed Quarter [B=A-1] | Y4: A-2 Quarters | Z4: A-3 Quarters | AA4: Quarter 12M prior 'A' [C] | AB4: Latest Completed FY [G] | AC4: Previous Completed FY [H]
C5: I GAAP | D5: I GAAP | E5: Ind AS | F5: Ind AS | G5: Ind AS | H5: Ind AS | I5: Ind AS | J5: Ind AS | K5: Ind AS | L5: Ind AS | N5: Net Interest Margin | O5: =H11/AVERAGE(G24:H24) -> 0.12143213 | P5: =I11/AVERAGE(I24,60160) -> 0.10303727 | Q5: =J11/AVERAGE(I24:J24) -> 0.10535325 | R5: =K11/AVERAGE(J24:K24) -> 0.10730645 | S5: =L11/AVERAGE(K24:L24) -> 0.12515805
B6: Revenue from operations | E6: 68782.08 | F6: 87146.42 | G6: 105572.12 | H6: 110823.24 | I6: 10514.849 | J6: 12694 | K6: 17156 | L6: 27600 | N6: Capitalization | U6: S.No. | V6: Parameter | W6: Value in INR cr. [Ratios in %]
B7: Interest Income | E7: =66960.14+130.25+0.91+2.64+3.97+260.07+32.91 -> 67390.89 | F7: =84443.28+399.39+35.29+75.17+4+326.87+22.69 -> 85306.69 | G7: 102408.56 | H7: 108056.79 | I7: 10148.791 | J7: 12186 | K7: 16525 | L7: 27066 | N7: Leverage (Debt/NOF) | O7: =H22/H21 -> 2.7153127 | P7: =I22/I21 -> 2.3613369 | Q7: =J22/J21 -> 2.4237414 | R7: =K22/K21 -> 3.3610238 | S7: =L22/L21 -> 4.0621754 | U7: 1 | V7: Net Interest Margin (%) | W7: 0.1109 | X7: 0.1056 | AA7: 0.114 | AB7: 0.1097 | AC7: 0.1031
B8: Treasury income | G8: 0 | H8: 0 | I8: 0 | J8: 0 | K8: 0 | L8: 0 | N8: CAR | O8: 0.2997 | P8: 0.3177 | U8: 2 | V8: Net Profit/Loss | W8: 1056.29 | X8: 1027.3 | Y8: 991 | Z8: 975.1 | AB8: 4049.7 | AC8: 3473.5
B9: Other Operation Income | E9: =E6-E7-E8 -> 1391.19 | F9: =F6-F7-F8 -> 1839.73 | G9: =G6-G7-G8 -> 3163.56 | H9: =H6-H7-H8 -> 2766.45 | I9: =I6-I7-I8 -> 366.058 | J9: =J6-J7-J8 -> 508 | K9: =K6-K7-K8 -> 631 | L9: =L6-L7-L8 -> 534 | N9: NOF/Loan Book | O9: =H21/H24 -> 0.30520304 | P9: =I21/I24 -> 0.32387698 | Q9: =J21/J24 -> 0.31119123 | R9: =K21/K24 -> 0.24238576 | S9: =L21/L24 -> 0.20857405 | U9: 3 | V9: Gross NPA Ratio (%) | W9: 0.0328 | X9: 0.0362 | AA9: 0.0379 | AB9: 0.0328 | AC9: 0.0379
B10: Interest expended | E10: 22368.44 | F10: 27909.4 | G10: 36924.41 | H10: 38357.62 | I10: 3699.14 | J10: 4655 | K10: 6429 | L10: 9941 | N10: Operational Efficiency | U10: 4 | V10: Net NPA Ratio (%) | W10: 0.029 | X10: 0.0323 | AA10: 0.034 | AB10: 0.029 | AC10: 0.034
B11: Net Interest Income | C11: =C7-C10 -> 0 | D11: =D7-D10 -> 0 | E11: =E7-E10 -> 45022.45 | F11: =F7-F10 -> 57397.29 | G11: =G7-G10 -> 65484.15 | H11: =H7-H10 -> 69699.17 | I11: =I7-I10 -> 6449.651 | J11: 7531 | K11: 10097 | L11: 17125 | N11: Cost to Income (on total operating income net-off interest expenses) | O11: =H15/(H12-H10) -> 0.2520133 | P11: =I15/(I12-I10) -> 0.31070209 | Q11: =J15/(J12-J10) -> 0.29767384 | R11: =K15/(K12-K10) -> 0.26941363 | S11: =L15/(L12-L10) -> 0.20069087 | U11: 5 | V11: Credit Cost (%) | W11: 0.0045 | X11: 0.0008 | AA11: 0.0046 | AB11: 0.0028 | AC11: 0.001
B12: Total Operating Income | C12: =C6-C10 -> 0 | D12: =SUM(D7:D9) -> 0 | E12: =SUM(E7:E9) -> 68782.08 | F12: =SUM(F7:F9) -> 87146.42 | G12: =SUM(G7:G9) -> 105572.12 | H12: =SUM(H7:H9) -> 110823.24 | I12: =SUM(I7:I9) -> 10514.849 | J12: =SUM(J7:J9) -> 12694 | K12: =SUM(K7:K9) -> 17156 | L12: =SUM(L7:L9) -> 27600 | N12: Cost to Income (on total operating income) | O12: =H15/H12 -> 0.16478764 | P12: =I15/I12 -> 0.20139662 | Q12: =J15/J12 -> 0.18851426 | R12: =K15/K12 -> 0.16845419 | S12: =L15/L12 -> 0.1284058 | U12: 6 | V12: Cash & Liquid Investments up to 3 months in ALM
B13: Other income | E13: 24.22 | F13: 81.49 | G13: 171.47 | H13: 160.69 | I13: 28.899 | J13: 59 | K13: 57 | L13: 42 | N13: Operating Expenses: Avg. Assets | O13: =H15/AVERAGE(G23:H23) -> 0.027253175 | P13: =I15/AVERAGE(I23,70555) -> 0.02958139 | Q13: =J15/AVERAGE(I23:J23) -> 0.03035881 | R13: =K15/AVERAGE(J23:K23) -> 0.028020574 | S13: =L15/AVERAGE(K23:L23) -> 0.023533005 | U13: 7 | V13: Debt Obligations due for repayment in the next 3 months
B14: Total Income | E14: =E12+E13 -> 68806.3 | F14: =F12+F13 -> 87227.91 | G14: =G12+G13 -> 105743.59 | H14: =H12+H13 -> 110983.93 | I14: =I12+I13 -> 10543.748 | J14: =J12+J13 -> 12753 | K14: =K12+K13 -> 17213 | L14: =L12+L13 -> 27642 | N14: Loan Book Performance | U14: 8 | V14: 3M Liquidity Cover for Debt Obligations | W14: =W12/W13 -> #DIV/0!
B15: Operating expenses | E15: =8975.53+420.86+5997.83 -> 15394.22 | F15: =10289.55+430.89+7066.69 -> 17787.13 | G15: =10062.5+507.12+7234.66 -> 17804.28 | H15: =10302.16+539.14+7421 -> 18262.3 | I15: 2117.655 | J15: 2393 | K15: 2890 | L15: 3544 | N15: Gross NPA % | O15: =H25/H24 -> 0.028902612 | P15: =I25/I24 -> 0.036884089 | Q15: =J25/J24 -> 0.031885137 | R15: =K25/K24 -> 0.033558873 | S15: =L25/L24 -> 0.023402693 | U15: 9 | V15: Liquidity Coverage Ratio [%]
B16: Operating profit | E16: =E12-E15 -> 53387.86 | F16: =F12-F15 -> 69359.29 | G16: =G12-G15 -> 87767.84 | H16: =H12-H15 -> 92560.94 | I16: =I12-I15 -> 8397.194 | J16: =J12-J15 -> 10301 | K16: =K12-K15 -> 14266 | L16: =L12-L15 -> 24056 | N16: Net NPA% | O16: =H26/H24 -> 0.025842341 | P16: =I26/I24 -> 0.033093999 | Q16: =J26/J24 -> 0.028189797 | R16: =K26/K24 -> 0.027545486 | S16: =L26/L24 -> 0.020342717 | U16: 10 | V16: Reported Total CRAR [%] | W16: 0.3037
B17: Pre-provisioning operating profit | E17: =E14-E15-E10 -> 31043.64 | F17: =F14-F15-F10 -> 41531.38 | G17: =G14-G15-G10 -> 51014.9 | H17: =H14-H15-H10 -> 54364.01 | I17: =I14-I15-I10 -> 4726.953 | J17: =J14-J15-J10 -> 5705 | K17: =K14-K15-K10 -> 7894 | L17: =L14-L15-L10 -> 14157 | N17: Provision coverage Ratio | O17: =(O15-O16)/O15 -> 0.10588214 | P17: =(P15-P16)/P15 -> 0.10275678 | Q17: =(Q15-Q16)/Q15 -> 0.11589537 | R17: =(R15-R16)/R15 -> 0.17918919 | S17: =(S15-S16)/S15 -> 0.13075314
B18: Provisions | E18: 275.48 | F18: 957.28 | G18: 949.77 | H18: 1270.47 | I18: 60.527 | J18: 198 | K18: 767 | L18: 470 | N18: Credit Cost | O18: =H18/AVERAGE(G24:H24) -> 0.0022134537 | P18: =I18/AVERAGE(I24,60160) -> 0.00096695726 | Q18: =J18/AVERAGE(I24:J24) -> 0.0027698769 | R18: =K18/AVERAGE(J24:K24) -> 0.0081513364 | S18: =L18/AVERAGE(K24:L24) -> 0.0034349946 | V18: Cells Needing Value Inputs
B19: PAT | E19: 19721.42 | F19: 30183 | G19: 37221.78 | H19: 39543.04 | I19: 3473.531 | J19: 4050 | K19: 5201 | L19: 10134 | V19: Formula Cells
B20: TNW | E20: 97927.19 | F20: 115718.13 | G20: 152388.93 | H20: 183445.72 | I20: 21061.928 | J20: 24253 | K20: 26724 | L20: 34081 | N20: Return Indicators
B21: Net Owned Funds | E21: =E20-E72 -> 97927.19 | F21: =F20-F72 -> 115718.13 | G21: =G20-G72 -> 152388.93 | H21: =H20-H72 -> 183445.72 | I21: =I20-I72 -> 21061.928 | J21: =J20 -> 24253 | K21: =K20 -> 26724 | L21: =L20 -> 34081 | N21: Pre Provisioning operating profit (PPOP)margin | O21: =H17/AVERAGE(G23:H23) -> 0.08112844 | P21: =I17/AVERAGE(I23,70555) -> 0.06603051 | Q21: =J17/AVERAGE(I23:J23) -> 0.072376519 | R21: =K17/AVERAGE(J23:K23) -> 0.076537859 | S21: =L17/AVERAGE(K23:L23) -> 0.094005857
B22: Total Debt | E22: =79869.53+184174.79+4287.2 -> 268331.52 | F22: =99618.81+268705.85+2975.76 -> 371300.42 | G22: =137960.58+319405.81+2096.37 -> 459462.76 | H22: =124978.88+371709.88+1423.74 -> 498112.5 | I22: 49734.307 | J22: 58783 | K22: 89820 | L22: 138443 | N22: RoA | O22: =H19/AVERAGE(G23:H23) -> 0.059010826 | P22: =I19/AVERAGE(I23,70555) -> 0.048521537 | Q22: =J19/AVERAGE(I23:J23) -> 0.051380351 | R22: =K19/AVERAGE(J23:K23) -> 0.050427338 | S22: =L19/AVERAGE(K23:L23) -> 0.067292177
B23: Total Assets | E23: 380687 | F23: 504596.54 | G23: 634649.24 | H23: 705546.88 | I23: 72619.814 | J23: 85028 | K23: 121249 | L23: 179945 | N23: RoE | O23: =H19/AVERAGE(G20:H20) -> 0.23549113 | P23: =I19/AVERAGE(I20,18347) -> 0.17628143 | Q23: =J19/AVERAGE(I20:J20) -> 0.17874904 | R23: =K19/AVERAGE(J20:K20) -> 0.20405281 | S23: =L19/AVERAGE(K20:L20) -> 0.33332785
B24: Loans & Advances (Gross) | E24: 355688.41 | F24: 431468.92 | G24: 546891.4 | H24: 601061.25 | I24: 65030.642 | J24: 77936 | K24: 110254 | L24: 163400 | N24: Spread
